Workbook
Name Area_Unit: [1]Intro!$I$8
Name BigNumber: 100000000
Name CALC: #REF!
Name Capex_sensitivity: [2]Dashboard!$N$17
Name CHECK: #REF!
Name CPI: #REF!
Name CPI_St: #REF!
Name Currency: [1]Intro!$I$6
Name days_in_month: 30
Name Days_in_Yr: #REF!
Name Days_per_Year: 365
Name Debtproportion_sensitivity: [2]Dashboard!$C$20
Name DynamicChart: '[2]Graph data'!A7:OFFSET('[2]Graph data'!A7,11,'[2]Graph data'!$Q$13)
Name Enddate: 54788
Name hours_per_day: 24
Name INPUT: #REF!
Name Landcost_sensitivity: [2]Dashboard!$N$18
Name Leaseexp_sensitivity: [2]Dashboard!$N$20
Name Million: #REF!
Name Monthly: [2]Global!$J$69
Name Months_per_Year: 12
Name Occupancy_sensitivity: [2]Dashboard!$N$16
Name Optcost_sensitivity: [2]Dashboard!$N$19
Name P1_PS_End_Date: #REF!
Name P1_PS_ST_Date: #REF!
Name P1_SDC_End_Date: #REF!
Name P1_SDC_St_Date: #REF!
Name P2_End_date: #REF!
Name P2_St_Date: #REF!
Name ProjStartDate: [1]Intro!$I$10
Name quarter: 0.25
Name Quarterly: [2]Global!$J$68
Name Revenue_sensitivity: [2]Dashboard!$N$15
Name rngCrncy: [3]Settings!$E$61
Name rngModelName: [4]Global!$E$16
Name rngProjName: [4]Global!$E$15
Name SemiAnnually: [2]Global!$J$67
Name Thousand: 1000
Name Todaydate: 42004
Name Unit_cent: 100
Name Unit_k: 1000
Name Unit_mn: 1000000
Name Units: 1000
Name Weekly: [2]Global!$J$70
Name z_ActivePeriods: '[2]Graph data'!$R$6:OFFSET('[2]Graph data'!$R$6,,'[2]Graph data'!$Q$13)
Name z_Constructionphase: ('[2]General Input'!$R$6:OFFSET('[2]General Input'!$R$6,,'[2]General Input'!$J$17/12-1))
Name z_EBITDAMargin: '[2]Graph data'!$R$33:OFFSET('[2]Graph data'!$R$33,,'[2]Graph data'!$Q$13)
Name z_EBIZMargin: '[2]Graph data'!$R$34:OFFSET('[2]Graph data'!$R$34,,'[2]Graph data'!$Q$13)
Name z_Entertainment_LeisureRevenue: '[2]Graph data'!$R$23:OFFSET('[2]Graph data'!$R$23,,'[2]Graph data'!$Q$13)
Name z_EntertainmentType: [2]Headings!#REF!
Name z_FinancingCash: '[2]Graph data'!$R$41:OFFSET('[2]Graph data'!$R$41,,'[2]Graph data'!$Q$13)
Name z_HospitalityRevenue: '[2]Graph data'!$R$18:OFFSET('[2]Graph data'!$R$18,,'[2]Graph data'!$Q$13)
Name z_IndustrialRevenue: '[2]Graph data'!$R$19:OFFSET('[2]Graph data'!$R$19,,'[2]Graph data'!$Q$13)
Name z_InvestingCash: '[2]Graph data'!$R$40:OFFSET('[2]Graph data'!$R$40,,'[2]Graph data'!$Q$13)
Name z_LaborAccomodationRevenue: '[2]Graph data'!$R$22:OFFSET('[2]Graph data'!$R$22,,'[2]Graph data'!$Q$13)
Name z_LandRevenue: '[2]Graph data'!$R$21:OFFSET('[2]Graph data'!$R$21,,'[2]Graph data'!$Q$13)
Name z_OfficeRevenue: '[2]Graph data'!$R$17:OFFSET('[2]Graph data'!$R$17,,'[2]Graph data'!$Q$13)
Name z_OperatingCash: '[2]Graph data'!$R$39:OFFSET('[2]Graph data'!$R$39,,'[2]Graph data'!$Q$13)
Name z_PATMargin: '[2]Graph data'!$R$36:OFFSET('[2]Graph data'!$R$36,,'[2]Graph data'!$Q$13)
Name z_PBTMargin: '[2]Graph data'!$R$35:OFFSET('[2]Graph data'!$R$35,,'[2]Graph data'!$Q$13)

Sheet Cover
B2: MAAD RESIDENTIAL
B3: Financial Feasibility Model
B5: PROJECT OVERVIEW
B6: Project name | C6: MAAD Residential - Mixed-use (Phase 1, 2 & 3)
B7: Asset mix | C7: Branded apartments (T2-T5), Tower 01, Hotel 01, Support Retail
B8: Currency | C8: SAR '000
B9: Time horizon | C9: 15 years (2025-2039), annual
B10: P&L scope | C10: Operating P&L to EBITDA only
B11: Source model | C11: MAAD Feasibility Scenario 7.0.xlsb
B13: WORKBOOK CONTENTS
B14: Tab | C14: Description
B15: Cover | C15: Project overview, contents, key headlines
B16: Revenue | C16: Pre-sales schedule + revenue build (residential, hospitality, retail)
B17: Costs | C17: Hospitality + retail OpEx with NOP / NOI methodology and AP working-capital adjustment
B18: Capex | C18: Asset cost stack (5 assets, sub-units, land), depreciation schedule
B19: Debt | C19: T1 (SNB Phase 1) + T2 (Phase 2 & 3) debt facilities, IDC, equity contribution
B20: CF | C20: Cash flow statement: revenue → costs → capex → financing → closing cash
B21: P&L | C21: Income Statement: Revenue → CoS → OpEx → NOI → D&A → EBIZ → PBZ → PAZ
B22: Wafi Escrow | C22: Per-asset cost-of-sales margin curve, REGA / Wafi escrow split, CF impact
B23: Land Summary | C23: Land area, price and value by sub-asset and phase; sourced by Capex tab
B24: Review Summary | C24: Snapshot of key totals plus consolidated variance vs KPMG (Source MAAD, Phase 2&3-only)
B26: KEY HEADLINES
B27: Metric | C27: SAR'000 | D27: Source
B28: Total Revenue Received (horizon) | C28: =CF!E21 -> 14527965 | D28: CF!D19
B29: Total Costs Paid (incl. Zakat) | C29: =CF!E37 -> -4506729.5 | D29: CF!D27
B30: Exit Value (2039) | C30: =CF!E39 -> 4996382.7 | D30: CF!D29
B31: Cash Flow from Operations (horizon) | C31: =CF!E40 -> 15819785 | D31: CF!D30
B32: Net Operating Income (P&L) | C32: ='P&L'!D45 -> 5703056.7 | D32: P&L!D44
B33: EBIZ (Earnings before interest & zakat) | C33: ='P&L'!D49 -> 5475571.8 | D33: P&L!D55
B34: Profit before Zakat (PBZ) | C34: ='P&L'!D55 -> 4388524.2 | D34: P&L!D61
B35: Profit after Zakat (PAZ) | C35: ='P&L'!D59 -> 4278811.1 | D35: P&L!D65
B36: Total Capex (Excl. Land) | C36: =Capex!K197 -> 3561464.5 | D36: Capex!K186
B37: Total Land Cost | C37: =Capex!K210 -> 1350681.9 | D37: Capex!K199
B38: Total Capex (Incl. Land) | C38: =Capex!K223 -> 4912146.4 | D38: Capex!K212
B39: Total Land Value | C39: =Debt!F9 -> 2408189 | D39: Debt!F8
B40: Land Value Phase 2 & 3 | C40: =Debt!F10 -> 1350681.9 | D40: Debt!F9
B41: Land Value Phase 1 | C41: =Debt!F11 -> 1057507.1 | D41: Debt!F10
B42: Pre-Capex VOCO | C42: =Debt!F12 -> 2624544 | D42: Debt!F11
B43: Total Pre-Capex (Land P1 + VOCO) | C43: =Debt!F13 -> 3682051 | D43: Debt!F12
B44: Tranche 1 Facility (SNB) | C44: =Debt!F15 -> 2400000 | D44: Debt!F14
B45: Tranche 2 Total Drawdown | C45: =Debt!F89 -> 381060.68 | D45: Debt!F59
B46: Total Funding (Debt + IDC) | C46: =Debt!F79 -> 381060.68 | D46: Debt!F48
B47: Pre-Equity Phase 1 (Pre-Capex - T1) | C47: =Debt!F14 -> 1282051 | D47: Debt!F13
B48: Wafi Escrow Locked / Released | C48: ='Wafi Escrow'!F21 -> 195739.79 | D48: Wafi Escrow!D46
B49: 2039 Closing Cash | C49: =CF!T71 -> 7870265.1 | D49: CF!S60
B51: End of Sheet

Sheet Revenue
B1: MAAD RESIDENTIAL WITH HOTEL - REVENUE
B2: All figures in SAR'000
B3: Pre-sales schedule + revenue build for residential, hospitality and retail (15-yr horizon).
C4: DESCRIPTION | D4: Phase | E4: uom | J4: Total | L4: 2025 | M4: =L4+1 -> 2026 | N4: =M4+1 -> 2027 | O4: =N4+1 -> 2028 | P4: =O4+1 -> 2029 | Q4: =P4+1 -> 2030 | R4: =Q4+1 -> 2031 | S4: =R4+1 -> 2032 | T4: =S4+1 -> 2033 | ... Z4: =Y4+1 -> 2039
C6: Period | E6: SAR'000 | G6: 1000 | L6: =K6+1 -> 1 | M6: =L6+1 -> 2 | N6: =M6+1 -> 3 | O6: =N6+1 -> 4 | P6: =O6+1 -> 5 | Q6: =P6+1 -> 6 | R6: =Q6+1 -> 7 | S6: =R6+1 -> 8 | ... Z6: =Y6+1 -> 15
B7: Revenue Summary
C8: Residential Revenue | J8: =SUM(L8:Z8) -> 6408977 | L8: =L22 -> 0 | M8: =M22 -> 37769.536 | N8: =N22 -> 725615.39 | O8: =O22 -> 1719744.3 | P8: =P22 -> 2002224.2 | Q8: =Q22 -> 1578069.8 | R8: =R22 -> 345553.85 | S8: =S22 -> 0 | ... Z8: =Z22 -> 0
C9: Hospitality Revenue | J9: =SUM(L9:Z9) -> 7782977.7 | L9: =L226 -> 0 | M9: =M226 -> 323867.37 | N9: =N226 -> 336217.37 | O9: =O226 -> 348567.37 | P9: =P226 -> 472864.73 | Q9: =Q226 -> 505432.65 | R9: =R226 -> 555815.71 | S9: =S226 -> 589664.3 | ... Z9: =Z226 -> 724616.46
C10: Retail Revenue | J10: =SUM(L10:Z10) -> 336010.5 | L10: =L326 -> 0 | M10: =M326 -> 0 | N10: =N326 -> 0 | O10: =O326 -> 0 | P10: =P326 -> 14651.584 | Q10: =Q326 -> 20023.831 | R10: =R326 -> 25655.534 | S10: =S326 -> 31556.306 | ... Z10: =Z326 -> 37510.532
B11: Total Pre-Sales Revenue Received - CF | J11: =SUM(J7:J10) -> 14527965 | L11: =SUM(L7:L10) -> 0 | M11: =SUM(M7:M10) -> 361636.91 | N11: =SUM(N7:N10) -> 1061832.8 | O11: =SUM(O7:O10) -> 2068311.7 | P11: =SUM(P7:P10) -> 2489740.5 | Q11: =SUM(Q7:Q10) -> 2103526.3 | R11: =SUM(R7:R10) -> 927025.09 | S11: =SUM(S7:S10) -> 621220.61 | ... Z11: =SUM(Z7:Z10) -> 762126.99
B13: Residential Revenue
B15: Pre-Sales Revenue Received
C16: Pre-Sales from Branded Apartments T2 & T3 | D16: 2 | J16: =SUM(L16:Z16) -> 2539826.9 | L16: =L51 -> 0 | M16: =M51 -> 28221.416 | N16: =N51 -> 465636.61 | O16: =O51 -> 973601.98 | P16: =P51 -> 945375.54 | Q16: =Q51 -> 126991.34 | R16: =R51 -> 0 | S16: =S51 -> 0 | ... Z16: =Z51 -> 0
C17: Pre-Sales from Branded Apartments T4 & T5 | D17: 3 | J17: =SUM(L17:Z17) -> 1594797 | L17: =L80 -> 0 | M17: =M80 -> 0 | N17: =N80 -> 106319.8 | O17: =O80 -> 425279.2 | P17: =P80 -> 744238.6 | Q17: =Q80 -> 239219.55 | R17: =R80 -> 79739.85 | S17: =S80 -> 0 | ... Z17: =Z80 -> 0
C18: Pre-Sales from Residential Tower 01 | D18: 2 | J18: =SUM(L18:Z18) -> 838610.8 | L18: =L112 -> 0 | M18: =M112 -> 9548.12 | N18: =N112 -> 153658.98 | O18: =O112 -> 320863.14 | P18: =P112 -> 312610.02 | Q18: =Q112 -> 41930.54 | R18: =R112 -> 0 | S18: =S112 -> 0 | ... Z18: =Z112 -> 0
C19: Branded Apartments T2 & T3 | D19: 2 | J19: =SUM(L19:Z19) -> 282214.16 | L19: =L129 -> 0 | M19: =M129 -> 0 | N19: =N129 -> 0 | O19: =O129 -> 0 | P19: =P129 -> 0 | Q19: =Q129 -> 282214.16 | R19: =R129 -> 0 | S19: =S129 -> 0 | ... Z19: =Z129 -> 0
C20: Branded Apartments T4 & T5 | D20: 3 | J20: =SUM(L20:Z20) -> 1063227 | L20: =L144 -> 0 | M20: =M144 -> 0 | N20: =N144 -> 0 | O20: =O144 -> 0 | P20: =P144 -> 0 | Q20: =Q144 -> 797413 | R20: =R144 -> 265814 | S20: =S144 -> 0 | ... Z20: =Z144 -> 0
C21: Residential Tower 01 | D21: 3 | J21: =SUM(L21:Z21) -> 90301.2 | L21: =L162 -> 0 | M21: =M162 -> 0 | N21: =N162 -> 0 | O21: =O162 -> 0 | P21: =P162 -> 0 | Q21: =Q162 -> 90301.2 | R21: =R162 -> 0 | S21: =S162 -> 0 | ... Z21: =Z162 -> 0
C22: Total Pre-Sales Revenue Received | J22: =SUM(J16:J21) -> 6408977 | L22: =SUM(L16:L21) -> 0 | M22: =SUM(M16:M21) -> 37769.536 | N22: =SUM(N16:N21) -> 725615.39 | O22: =SUM(O16:O21) -> 1719744.3 | P22: =SUM(P16:P21) -> 2002224.2 | Q22: =SUM(Q16:Q21) -> 1578069.8 | R22: =SUM(R16:R21) -> 345553.85 | S22: =SUM(S16:S21) -> 0 | ... Z22: =SUM(Z16:Z21) -> 0
B24: Pre-Sales from Branded Apartments T2 & T3 | D24: 2
C25: Indexation Factor | E25: % | G25: 0 | L25: =(1+$G25)^L$6 -> 1 | M25: =(1+$G25)^M$6 -> 1 | N25: =(1+$G25)^N$6 -> 1 | O25: =(1+$G25)^O$6 -> 1 | P25: =(1+$G25)^P$6 -> 1 | Q25: =(1+$G25)^Q$6 -> 1 | R25: =(1+$G25)^R$6 -> 1 | S25: =(1+$G25)^S$6 -> 1 | ... Z25: =(1+$G25)^Z$6 -> 1
C27: Pre-Sales from Branded Apartments T2 & T3 | G27: Area SQM | H27: SAR/SQM
C28: 1 BR | G28: 47800 | H28: 33456.067 | L28: 0 | M28: 0.05 | N28: 0.3 | O28: 0.3 | P28: 0.25 | Q28: 0 | R28: 0 | S28: 0 | T28: 0 | U28: 0 | V28: 0 | W28: 0 | X28: 0 | Y28: 0 | Z28: 0
C29: 2 BR | G29: 36497.1 | H29: 33505.248 | L29: 0 | M29: 0.05 | N29: 0.3 | O29: 0.3 | P29: 0.25 | Q29: 0 | R29: 0 | S29: 0 | T29: 0 | U29: 0 | V29: 0 | W29: 0 | X29: 0 | Y29: 0 | Z29: 0
C31: Pre-Sale Area
C32: 1 BR | E32: Area SQM | G32: {=SUM($L28:$Z28*$G28)} -> 43020 | J32: =SUM(L32:Z32) -> 43020 | L32: =ROUND($G28*L28,0) -> 0 | M32: =ROUND($G28*M28,0) -> 2390 | N32: =ROUND($G28*N28,0) -> 14340 | O32: =ROUND($G28*O28,0) -> 14340 | P32: =ROUND($G28*P28,0) -> 11950 | Q32: =ROUND($G28*Q28,0) -> 0 | R32: =ROUND($G28*R28,0) -> 0 | S32: =ROUND($G28*S28,0) -> 0 | ... Z32: =ROUND($G28*Z28,0) -> 0
C33: 2 BR | E33: Area SQM | G33: {=SUM($L29:$Z29*$G29)} -> 32847.39 | J33: =SUM(L33:Z33) -> 32847 | L33: =ROUND($G29*L29,0) -> 0 | M33: =ROUND($G29*M29,0) -> 1825 | N33: =ROUND($G29*N29,0) -> 10949 | O33: =ROUND($G29*O29,0) -> 10949 | P33: =ROUND($G29*P29,0) -> 9124 | Q33: =ROUND($G29*Q29,0) -> 0 | R33: =ROUND($G29*R29,0) -> 0 | S33: =ROUND($G29*S29,0) -> 0 | ... Z33: =ROUND($G29*Z29,0) -> 0
C34: Total Area | E34: Area SQM | G34: =SUM(G32:G33) -> 75867.39 | J34: =SUM(J32:J33) -> 75867 | L34: =SUM(L32:L33) -> 0 | M34: =SUM(M32:M33) -> 4215 | N34: =SUM(N32:N33) -> 25289 | O34: =SUM(O32:O33) -> 25289 | P34: =SUM(P32:P33) -> 21074 | Q34: =SUM(Q32:Q33) -> 0 | R34: =SUM(R32:R33) -> 0 | S34: =SUM(S32:S33) -> 0 | ... Z34: =SUM(Z32:Z33) -> 0
C36: Pre sales
C37: 1 BR | E37: SAR'000 | G37: =$H28 -> 33456.067 | J37: =SUM(L37:Z37) -> 1439280 | L37: =(($G37*L$25)*L32)/$G$6 -> 0 | M37: =(($G37*M$25)*M32)/$G$6 -> 79960 | N37: =(($G37*N$25)*N32)/$G$6 -> 479760 | O37: =(($G37*O$25)*O32)/$G$6 -> 479760 | P37: =(($G37*P$25)*P32)/$G$6 -> 399800 | Q37: =(($G37*Q$25)*Q32)/$G$6 -> 0 | R37: =(($G37*R$25)*R32)/$G$6 -> 0 | S37: =(($G37*S$25)*S32)/$G$6 -> 0 | ... Z37: =(($G37*Z$25)*Z32)/$G$6 -> 0
C38: 2 BR | E38: SAR'000 | G38: =$H29 -> 33505.248 | J38: =SUM(L38:Z38) -> 1100546.9 | L38: =(($G38*L$25)*L33)/$G$6 -> 0 | M38: =(($G38*M$25)*M33)/$G$6 -> 61147.078 | N38: =(($G38*N$25)*N33)/$G$6 -> 366848.96 | O38: =(($G38*O$25)*O33)/$G$6 -> 366848.96 | P38: =(($G38*P$25)*P33)/$G$6 -> 305701.89 | Q38: =(($G38*Q$25)*Q33)/$G$6 -> 0 | R38: =(($G38*R$25)*R33)/$G$6 -> 0 | S38: =(($G38*S$25)*S33)/$G$6 -> 0 | ... Z38: =(($G38*Z$25)*Z33)/$G$6 -> 0
C39: Total Pre Sales | E39: SAR'000 | G39: =AVERAGE(G37:G38) -> 33480.658 | J39: =SUM(L39:Z39) -> 2539826.9 | L39: =SUM(L37:L38) -> 0 | M39: =SUM(M37:M38) -> 141107.08 | N39: =SUM(N37:N38) -> 846608.96 | O39: =SUM(O37:O38) -> 846608.96 | P39: =SUM(P37:P38) -> 705501.89 | Q39: =SUM(Q37:Q38) -> 0 | R39: =SUM(R37:R38) -> 0 | S39: =SUM(S37:S38) -> 0 | ... Z39: =SUM(Z37:Z38) -> 0
C41: Cumulative cash payment profile
C42: Cash Payment Profile | E42: % | L42: 0 | M42: 0.2 | N42: 0.3 | O42: 0.3 | P42: 0.15 | Q42: 0.05 | R42: 0 | S42: 0 | T42: 0 | U42: 0 | V42: 0 | W42: 0 | X42: 0 | Y42: 0 | Z42: 0
C43: Cumulative Payment Profile | E43: % | L43: =K43+L42 -> 0 | M43: =L43+M42 -> 0.2 | N43: =M43+N42 -> 0.5 | O43: =N43+O42 -> 0.8 | P43: =O43+P42 -> 0.95 | Q43: =P43+Q42 -> 1 | R43: =Q43+R42 -> 1 | S43: =R43+S42 -> 1 | ... Z43: =Y43+Z42 -> 1
C45: 2025 | E45: SAR'000 | G45: =SUMIF($L$4:$Z$4,$C45,$L$39:$Z$39) -> 0 | J45: =SUM(L45:Z45) -> 0 | L45: {=IF(L$4<$C45,0,IF(L$4=$C45,SUMIF($L$4:$Z$4,$C45,$L$39:$Z$39)*INDEX($L$43:$Z$43,$C45-$L$4+1),SUMIF($L$4:$Z$4,$C45,$L$39:$Z$39)*L$42))} -> 0 | M45: {=IF(M$4<$C45,0,IF(M$4=$C45,SUMIF($L$4:$Z$4,$C45,$L$39:$Z$39)*INDEX($L$43:$Z$43,$C45-$L$4+1),SUMIF($L$4:$Z$4,$C45,$L$39:$Z$39)*M$42))} -> 0 | N45: {=IF(N$4<$C45,0,IF(N$4=$C45,SUMIF($L$4:$Z$4,$C45,$L$39:$Z$39)*INDEX($L$43:$Z$43,$C45-$L$4+1),SUMIF($L$4:$Z$4,$C45,$L$39:$Z$39)*N$42))} -> 0 | O45: {=IF(O$4<$C45,0,IF(O$4=$C45,SUMIF($L$4:$Z$4,$C45,$L$39:$Z$39)*INDEX($L$43:$Z$43,$C45-$L$4+1),SUMIF($L$4:$Z$4,$C45,$L$39:$Z$39)*O$42))} -> 0 | P45: {=IF(P$4<$C45,0,IF(P$4=$C45,SUMIF($L$4:$Z$4,$C45,$L$39:$Z$39)*INDEX($L$43:$Z$43,$C45-$L$4+1),SUMIF($L$4:$Z$4,$C45,$L$39:$Z$39)*P$42))} -> 0 | Q45: {=IF(Q$4<$C45,0,IF(Q$4=$C45,SUMIF($L$4:$Z$4,$C45,$L$39:$Z$39)*INDEX($L$43:$Z$43,$C45-$L$4+1),SUMIF($L$4:$Z$4,$C45,$L$39:$Z$39)*Q$42))} -> 0 | R45: {=IF(R$4<$C45,0,IF(R$4=$C45,SUMIF($L$4:$Z$4,$C45,$L$39:$Z$39)*INDEX($L$43:$Z$43,$C45-$L$4+1),SUMIF($L$4:$Z$4,$C45,$L$39:$Z$39)*R$42))} -> 0 | S45: {=IF(S$4<$C45,0,IF(S$4=$C45,SUMIF($L$4:$Z$4,$C45,$L$39:$Z$39)*INDEX($L$43:$Z$43,$C45-$L$4+1),SUMIF($L$4:$Z$4,$C45,$L$39:$Z$39)*S$42))} -> 0 | ... Z45: {=IF(Z$4<$C45,0,IF(Z$4=$C45,SUMIF($L$4:$Z$4,$C45,$L$39:$Z$39)*INDEX($L$43:$Z$43,$C45-$L$4+1),SUMIF($L$4:$Z$4,$C45,$L$39:$Z$39)*Z$42))} -> 0
C46: =C45+1 -> 2026 | E46: SAR'000 | G46: =SUMIF($L$4:$Z$4,$C46,$L$39:$Z$39) -> 141107.08 | J46: =SUM(L46:Z46) -> 141107.08 | L46: {=IF(L$4<$C46,0,IF(L$4=$C46,SUMIF($L$4:$Z$4,$C46,$L$39:$Z$39)*INDEX($L$43:$Z$43,$C46-$L$4+1),SUMIF($L$4:$Z$4,$C46,$L$39:$Z$39)*L$42))} -> 0 | M46: {=IF(M$4<$C46,0,IF(M$4=$C46,SUMIF($L$4:$Z$4,$C46,$L$39:$Z$39)*INDEX($L$43:$Z$43,$C46-$L$4+1),SUMIF($L$4:$Z$4,$C46,$L$39:$Z$39)*M$42))} -> 28221.416 | N46: {=IF(N$4<$C46,0,IF(N$4=$C46,SUMIF($L$4:$Z$4,$C46,$L$39:$Z$39)*INDEX($L$43:$Z$43,$C46-$L$4+1),SUMIF($L$4:$Z$4,$C46,$L$39:$Z$39)*N$42))} -> 42332.123 | O46: {=IF(O$4<$C46,0,IF(O$4=$C46,SUMIF($L$4:$Z$4,$C46,$L$39:$Z$39)*INDEX($L$43:$Z$43,$C46-$L$4+1),SUMIF($L$4:$Z$4,$C46,$L$39:$Z$39)*O$42))} -> 42332.123 | P46: {=IF(P$4<$C46,0,IF(P$4=$C46,SUMIF($L$4:$Z$4,$C46,$L$39:$Z$39)*INDEX($L$43:$Z$43,$C46-$L$4+1),SUMIF($L$4:$Z$4,$C46,$L$39:$Z$39)*P$42))} -> 21166.062 | Q46: {=IF(Q$4<$C46,0,IF(Q$4=$C46,SUMIF($L$4:$Z$4,$C46,$L$39:$Z$39)*INDEX($L$43:$Z$43,$C46-$L$4+1),SUMIF($L$4:$Z$4,$C46,$L$39:$Z$39)*Q$42))} -> 7055.3539 | R46: {=IF(R$4<$C46,0,IF(R$4=$C46,SUMIF($L$4:$Z$4,$C46,$L$39:$Z$39)*INDEX($L$43:$Z$43,$C46-$L$4+1),SUMIF($L$4:$Z$4,$C46,$L$39:$Z$39)*R$42))} -> 0 | S46: {=IF(S$4<$C46,0,IF(S$4=$C46,SUMIF($L$4:$Z$4,$C46,$L$39:$Z$39)*INDEX($L$43:$Z$43,$C46-$L$4+1),SUMIF($L$4:$Z$4,$C46,$L$39:$Z$39)*S$42))} -> 0 | ... Z46: {=IF(Z$4<$C46,0,IF(Z$4=$C46,SUMIF($L$4:$Z$4,$C46,$L$39:$Z$39)*INDEX($L$43:$Z$43,$C46-$L$4+1),SUMIF($L$4:$Z$4,$C46,$L$39:$Z$39)*Z$42))} -> 0
C47: =C46+1 -> 2027 | E47: SAR'000 | G47: =SUMIF($L$4:$Z$4,$C47,$L$39:$Z$39) -> 846608.96 | J47: =SUM(L47:Z47) -> 846608.96 | L47: {=IF(L$4<$C47,0,IF(L$4=$C47,SUMIF($L$4:$Z$4,$C47,$L$39:$Z$39)*INDEX($L$43:$Z$43,$C47-$L$4+1),SUMIF($L$4:$Z$4,$C47,$L$39:$Z$39)*L$42))} -> 0 | M47: {=IF(M$4<$C47,0,IF(M$4=$C47,SUMIF($L$4:$Z$4,$C47,$L$39:$Z$39)*INDEX($L$43:$Z$43,$C47-$L$4+1),SUMIF($L$4:$Z$4,$C47,$L$39:$Z$39)*M$42))} -> 0 | N47: {=IF(N$4<$C47,0,IF(N$4=$C47,SUMIF($L$4:$Z$4,$C47,$L$39:$Z$39)*INDEX($L$43:$Z$43,$C47-$L$4+1),SUMIF($L$4:$Z$4,$C47,$L$39:$Z$39)*N$42))} -> 423304.48 | O47: {=IF(O$4<$C47,0,IF(O$4=$C47,SUMIF($L$4:$Z$4,$C47,$L$39:$Z$39)*INDEX($L$43:$Z$43,$C47-$L$4+1),SUMIF($L$4:$Z$4,$C47,$L$39:$Z$39)*O$42))} -> 253982.69 | P47: {=IF(P$4<$C47,0,IF(P$4=$C47,SUMIF($L$4:$Z$4,$C47,$L$39:$Z$39)*INDEX($L$43:$Z$43,$C47-$L$4+1),SUMIF($L$4:$Z$4,$C47,$L$39:$Z$39)*P$42))} -> 126991.34 | Q47: {=IF(Q$4<$C47,0,IF(Q$4=$C47,SUMIF($L$4:$Z$4,$C47,$L$39:$Z$39)*INDEX($L$43:$Z$43,$C47-$L$4+1),SUMIF($L$4:$Z$4,$C47,$L$39:$Z$39)*Q$42))} -> 42330.448 | R47: {=IF(R$4<$C47,0,IF(R$4=$C47,SUMIF($L$4:$Z$4,$C47,$L$39:$Z$39)*INDEX($L$43:$Z$43,$C47-$L$4+1),SUMIF($L$4:$Z$4,$C47,$L$39:$Z$39)*R$42))} -> 0 | S47: {=IF(S$4<$C47,0,IF(S$4=$C47,SUMIF($L$4:$Z$4,$C47,$L$39:$Z$39)*INDEX($L$43:$Z$43,$C47-$L$4+1),SUMIF($L$4:$Z$4,$C47,$L$39:$Z$39)*S$42))} -> 0 | ... Z47: {=IF(Z$4<$C47,0,IF(Z$4=$C47,SUMIF($L$4:$Z$4,$C47,$L$39:$Z$39)*INDEX($L$43:$Z$43,$C47-$L$4+1),SUMIF($L$4:$Z$4,$C47,$L$39:$Z$39)*Z$42))} -> 0
C48: =C47+1 -> 2028 | E48: SAR'000 | G48: =SUMIF($L$4:$Z$4,$C48,$L$39:$Z$39) -> 846608.96 | J48: =SUM(L48:Z48) -> 846608.96 | L48: {=IF(L$4<$C48,0,IF(L$4=$C48,SUMIF($L$4:$Z$4,$C48,$L$39:$Z$39)*INDEX($L$43:$Z$43,$C48-$L$4+1),SUMIF($L$4:$Z$4,$C48,$L$39:$Z$39)*L$42))} -> 0 | M48: {=IF(M$4<$C48,0,IF(M$4=$C48,SUMIF($L$4:$Z$4,$C48,$L$39:$Z$39)*INDEX($L$43:$Z$43,$C48-$L$4+1),SUMIF($L$4:$Z$4,$C48,$L$39:$Z$39)*M$42))} -> 0 | N48: {=IF(N$4<$C48,0,IF(N$4=$C48,SUMIF($L$4:$Z$4,$C48,$L$39:$Z$39)*INDEX($L$43:$Z$43,$C48-$L$4+1),SUMIF($L$4:$Z$4,$C48,$L$39:$Z$39)*N$42))} -> 0 | O48: {=IF(O$4<$C48,0,IF(O$4=$C48,SUMIF($L$4:$Z$4,$C48,$L$39:$Z$39)*INDEX($L$43:$Z$43,$C48-$L$4+1),SUMIF($L$4:$Z$4,$C48,$L$39:$Z$39)*O$42))} -> 677287.17 | P48: {=IF(P$4<$C48,0,IF(P$4=$C48,SUMIF($L$4:$Z$4,$C48,$L$39:$Z$39)*INDEX($L$43:$Z$43,$C48-$L$4+1),SUMIF($L$4:$Z$4,$C48,$L$39:$Z$39)*P$42))} -> 126991.34 | Q48: {=IF(Q$4<$C48,0,IF(Q$4=$C48,SUMIF($L$4:$Z$4,$C48,$L$39:$Z$39)*INDEX($L$43:$Z$43,$C48-$L$4+1),SUMIF($L$4:$Z$4,$C48,$L$39:$Z$39)*Q$42))} -> 42330.448 | R48: {=IF(R$4<$C48,0,IF(R$4=$C48,SUMIF($L$4:$Z$4,$C48,$L$39:$Z$39)*INDEX($L$43:$Z$43,$C48-$L$4+1),SUMIF($L$4:$Z$4,$C48,$L$39:$Z$39)*R$42))} -> 0 | S48: {=IF(S$4<$C48,0,IF(S$4=$C48,SUMIF($L$4:$Z$4,$C48,$L$39:$Z$39)*INDEX($L$43:$Z$43,$C48-$L$4+1),SUMIF($L$4:$Z$4,$C48,$L$39:$Z$39)*S$42))} -> 0 | ... Z48: {=IF(Z$4<$C48,0,IF(Z$4=$C48,SUMIF($L$4:$Z$4,$C48,$L$39:$Z$39)*INDEX($L$43:$Z$43,$C48-$L$4+1),SUMIF($L$4:$Z$4,$C48,$L$39:$Z$39)*Z$42))} -> 0
C49: =C48+1 -> 2029 | E49: SAR'000 | G49: =SUMIF($L$4:$Z$4,$C49,$L$39:$Z$39) -> 705501.89 | J49: =SUM(L49:Z49) -> 705501.89 | L49: {=IF(L$4<$C49,0,IF(L$4=$C49,SUMIF($L$4:$Z$4,$C49,$L$39:$Z$39)*INDEX($L$43:$Z$43,$C49-$L$4+1),SUMIF($L$4:$Z$4,$C49,$L$39:$Z$39)*L$42))} -> 0 | M49: {=IF(M$4<$C49,0,IF(M$4=$C49,SUMIF($L$4:$Z$4,$C49,$L$39:$Z$39)*INDEX($L$43:$Z$43,$C49-$L$4+1),SUMIF($L$4:$Z$4,$C49,$L$39:$Z$39)*M$42))} -> 0 | N49: {=IF(N$4<$C49,0,IF(N$4=$C49,SUMIF($L$4:$Z$4,$C49,$L$39:$Z$39)*INDEX($L$43:$Z$43,$C49-$L$4+1),SUMIF($L$4:$Z$4,$C49,$L$39:$Z$39)*N$42))} -> 0 | O49: {=IF(O$4<$C49,0,IF(O$4=$C49,SUMIF($L$4:$Z$4,$C49,$L$39:$Z$39)*INDEX($L$43:$Z$43,$C49-$L$4+1),SUMIF($L$4:$Z$4,$C49,$L$39:$Z$39)*O$42))} -> 0 | P49: {=IF(P$4<$C49,0,IF(P$4=$C49,SUMIF($L$4:$Z$4,$C49,$L$39:$Z$39)*INDEX($L$43:$Z$43,$C49-$L$4+1),SUMIF($L$4:$Z$4,$C49,$L$39:$Z$39)*P$42))} -> 670226.79 | Q49: {=IF(Q$4<$C49,0,IF(Q$4=$C49,SUMIF($L$4:$Z$4,$C49,$L$39:$Z$39)*INDEX($L$43:$Z$43,$C49-$L$4+1),SUMIF($L$4:$Z$4,$C49,$L$39:$Z$39)*Q$42))} -> 35275.094 | R49: {=IF(R$4<$C49,0,IF(R$4=$C49,SUMIF($L$4:$Z$4,$C49,$L$39:$Z$39)*INDEX($L$43:$Z$43,$C49-$L$4+1),SUMIF($L$4:$Z$4,$C49,$L$39:$Z$39)*R$42))} -> 0 | S49: {=IF(S$4<$C49,0,IF(S$4=$C49,SUMIF($L$4:$Z$4,$C49,$L$39:$Z$39)*INDEX($L$43:$Z$43,$C49-$L$4+1),SUMIF($L$4:$Z$4,$C49,$L$39:$Z$39)*S$42))} -> 0 | ... Z49: {=IF(Z$4<$C49,0,IF(Z$4=$C49,SUMIF($L$4:$Z$4,$C49,$L$39:$Z$39)*INDEX($L$43:$Z$43,$C49-$L$4+1),SUMIF($L$4:$Z$4,$C49,$L$39:$Z$39)*Z$42))} -> 0
C50: =C49+1 -> 2030 | E50: SAR'000 | G50: =SUMIF($L$4:$Z$4,$C50,$L$39:$Z$39) -> 0 | J50: =SUM(L50:Z50) -> 0 | L50: {=IF(L$4<$C50,0,IF(L$4=$C50,SUMIF($L$4:$Z$4,$C50,$L$39:$Z$39)*INDEX($L$43:$Z$43,$C50-$L$4+1),SUMIF($L$4:$Z$4,$C50,$L$39:$Z$39)*L$42))} -> 0 | M50: {=IF(M$4<$C50,0,IF(M$4=$C50,SUMIF($L$4:$Z$4,$C50,$L$39:$Z$39)*INDEX($L$43:$Z$43,$C50-$L$4+1),SUMIF($L$4:$Z$4,$C50,$L$39:$Z$39)*M$42))} -> 0 | N50: {=IF(N$4<$C50,0,IF(N$4=$C50,SUMIF($L$4:$Z$4,$C50,$L$39:$Z$39)*INDEX($L$43:$Z$43,$C50-$L$4+1),SUMIF($L$4:$Z$4,$C50,$L$39:$Z$39)*N$42))} -> 0 | O50: {=IF(O$4<$C50,0,IF(O$4=$C50,SUMIF($L$4:$Z$4,$C50,$L$39:$Z$39)*INDEX($L$43:$Z$43,$C50-$L$4+1),SUMIF($L$4:$Z$4,$C50,$L$39:$Z$39)*O$42))} -> 0 | P50: {=IF(P$4<$C50,0,IF(P$4=$C50,SUMIF($L$4:$Z$4,$C50,$L$39:$Z$39)*INDEX($L$43:$Z$43,$C50-$L$4+1),SUMIF($L$4:$Z$4,$C50,$L$39:$Z$39)*P$42))} -> 0 | Q50: {=IF(Q$4<$C50,0,IF(Q$4=$C50,SUMIF($L$4:$Z$4,$C50,$L$39:$Z$39)*INDEX($L$43:$Z$43,$C50-$L$4+1),SUMIF($L$4:$Z$4,$C50,$L$39:$Z$39)*Q$42))} -> 0 | R50: {=IF(R$4<$C50,0,IF(R$4=$C50,SUMIF($L$4:$Z$4,$C50,$L$39:$Z$39)*INDEX($L$43:$Z$43,$C50-$L$4+1),SUMIF($L$4:$Z$4,$C50,$L$39:$Z$39)*R$42))} -> 0 | S50: {=IF(S$4<$C50,0,IF(S$4=$C50,SUMIF($L$4:$Z$4,$C50,$L$39:$Z$39)*INDEX($L$43:$Z$43,$C50-$L$4+1),SUMIF($L$4:$Z$4,$C50,$L$39:$Z$39)*S$42))} -> 0 | ... Z50: {=IF(Z$4<$C50,0,IF(Z$4=$C50,SUMIF($L$4:$Z$4,$C50,$L$39:$Z$39)*INDEX($L$43:$Z$43,$C50-$L$4+1),SUMIF($L$4:$Z$4,$C50,$L$39:$Z$39)*Z$42))} -> 0
C51: Total | E51: SAR'000 | G51: =SUM(G45:G50) -> 2539826.9 | J51: =SUM(J45:J50) -> 2539826.9 | L51: =SUM(L45:L50) -> 0 | M51: =SUM(M45:M50) -> 28221.416 | N51: =SUM(N45:N50) -> 465636.61 | O51: =SUM(O45:O50) -> 973601.98 | P51: =SUM(P45:P50) -> 945375.54 | Q51: =SUM(Q45:Q50) -> 126991.34 | R51: =SUM(R45:R50) -> 0 | S51: =SUM(S45:S50) -> 0 | ... Z51: =SUM(Z45:Z50) -> 0
B53: Pre-Sales from Branded Apartments T4 & T5 | D53: 3
C54: Indexation Factor | E54: % | G54: 0 | L54: =(1+$G54)^L$6 -> 1 | M54: =(1+$G54)^M$6 -> 1 | N54: =(1+$G54)^N$6 -> 1 | O54: =(1+$G54)^O$6 -> 1 | P54: =(1+$G54)^P$6 -> 1 | Q54: =(1+$G54)^Q$6 -> 1 | R54: =(1+$G54)^R$6 -> 1 | S54: =(1+$G54)^S$6 -> 1 | ... Z54: =(1+$G54)^Z$6 -> 1
C56: Pre-Sales from Branded Apartments T2 & T3 | G56: Area SQM | H56: SAR/SQM
C57: 1 BR | G57: 56200 | H57: 29000 | L57: 0 | M57: 0 | N57: 0.2 | O57: 0.2 | P57: 0.2 | Q57: 0 | R57: 0 | S57: 0 | T57: 0 | U57: 0 | V57: 0 | W57: 0 | X57: 0 | Y57: 0 | Z57: 0
C58: 2 BR | G58: 35456.1 | H58: 29000 | L58: 0 | M58: 0 | N58: 0.2 | O58: 0.2 | P58: 0.2 | Q58: 0 | R58: 0 | S58: 0 | T58: 0 | U58: 0 | V58: 0 | W58: 0 | X58: 0 | Y58: 0 | Z58: 0
C60: Pre-Sale Area
C61: 1 BR | E61: Area SQM | G61: {=SUM($L57:$Z57*$G57)} -> 33720 | J61: =SUM(L61:Z61) -> 33720 | L61: =ROUND($G57*L57,0) -> 0 | M61: =ROUND($G57*M57,0) -> 0 | N61: =ROUND($G57*N57,0) -> 11240 | O61: =ROUND($G57*O57,0) -> 11240 | P61: =ROUND($G57*P57,0) -> 11240 | Q61: =ROUND($G57*Q57,0) -> 0 | R61: =ROUND($G57*R57,0) -> 0 | S61: =ROUND($G57*S57,0) -> 0 | ... Z61: =ROUND($G57*Z57,0) -> 0
C62: 2 BR | E62: Area SQM | G62: {=SUM($L58:$Z58*$G58)} -> 21273.66 | J62: =SUM(L62:Z62) -> 21273 | L62: =ROUND($G58*L58,0) -> 0 | M62: =ROUND($G58*M58,0) -> 0 | N62: =ROUND($G58*N58,0) -> 7091 | O62: =ROUND($G58*O58,0) -> 7091 | P62: =ROUND($G58*P58,0) -> 7091 | Q62: =ROUND($G58*Q58,0) -> 0 | R62: =ROUND($G58*R58,0) -> 0 | S62: =ROUND($G58*S58,0) -> 0 | ... Z62: =ROUND($G58*Z58,0) -> 0
C63: Total Area | E63: Area SQM | G63: =SUM(G61:G62) -> 54993.66 | J63: =SUM(J61:J62) -> 54993 | L63: =SUM(L61:L62) -> 0 | M63: =SUM(M61:M62) -> 0 | N63: =SUM(N61:N62) -> 18331 | O63: =SUM(O61:O62) -> 18331 | P63: =SUM(P61:P62) -> 18331 | Q63: =SUM(Q61:Q62) -> 0 | R63: =SUM(R61:R62) -> 0 | S63: =SUM(S61:S62) -> 0 | ... Z63: =SUM(Z61:Z62) -> 0
C65: Pre sales
C66: 1 BR | E66: SAR'000 | G66: =$H57 -> 29000 | J66: =SUM(L66:Z66) -> 977880 | L66: =(($G66*L$25)*L61)/$G$6 -> 0 | M66: =(($G66*M$25)*M61)/$G$6 -> 0 | N66: =(($G66*N$25)*N61)/$G$6 -> 325960 | O66: =(($G66*O$25)*O61)/$G$6 -> 325960 | P66: =(($G66*P$25)*P61)/$G$6 -> 325960 | Q66: =(($G66*Q$25)*Q61)/$G$6 -> 0 | R66: =(($G66*R$25)*R61)/$G$6 -> 0 | S66: =(($G66*S$25)*S61)/$G$6 -> 0 | ... Z66: =(($G66*Z$25)*Z61)/$G$6 -> 0
C67: 2 BR | E67: SAR'000 | G67: =$H58 -> 29000 | J67: =SUM(L67:Z67) -> 616917 | L67: =(($G67*L$25)*L62)/$G$6 -> 0 | M67: =(($G67*M$25)*M62)/$G$6 -> 0 | N67: =(($G67*N$25)*N62)/$G$6 -> 205639 | O67: =(($G67*O$25)*O62)/$G$6 -> 205639 | P67: =(($G67*P$25)*P62)/$G$6 -> 205639 | Q67: =(($G67*Q$25)*Q62)/$G$6 -> 0 | R67: =(($G67*R$25)*R62)/$G$6 -> 0 | S67: =(($G67*S$25)*S62)/$G$6 -> 0 | ... Z67: =(($G67*Z$25)*Z62)/$G$6 -> 0
C68: Total Pre Sales | E68: SAR'000 | G68: =AVERAGE(G66:G67) -> 29000 | J68: =SUM(L68:Z68) -> 1594797 | L68: =SUM(L66:L67) -> 0 | M68: =SUM(M66:M67) -> 0 | N68: =SUM(N66:N67) -> 531599 | O68: =SUM(O66:O67) -> 531599 | P68: =SUM(P66:P67) -> 531599 | Q68: =SUM(Q66:Q67) -> 0 | R68: =SUM(R66:R67) -> 0 | S68: =SUM(S66:S67) -> 0 | ... Z68: =SUM(Z66:Z67) -> 0
C70: Cumulative cash payment profile
C71: Cash Payment Profile | E71: % | L71: 0 | M71: 0 | N71: 0.2 | O71: 0.3 | P71: 0.3 | Q71: 0.15 | R71: 0.05 | S71: 0 | T71: 0 | U71: 0 | V71: 0 | W71: 0 | X71: 0 | Y71: 0 | Z71: 0
C72: Cumulative Payment Profile | E72: % | L72: =K72+L71 -> 0 | M72: =L72+M71 -> 0 | N72: 0.2 | O72: 0.5 | P72: 0.8 | Q72: 0.95 | R72: 1 | S72: =R72+S71 -> 1 | T72: =S72+T71 -> 1 | U72: =T72+U71 -> 1 | V72: =U72+V71 -> 1 | W72: =V72+W71 -> 1 | X72: =W72+X71 -> 1 | Y72: =X72+Y71 -> 1 | Z72: =Y72+Z71 -> 1
C74: 2025 | E74: SAR'000 | G74: =SUMIF($L$4:$Z$4,$C74,$L$39:$Z$39) -> 0 | J74: =SUM(L74:Z74) -> 0 | L74: {=IF(L$4<$C74,0,IF(L$4=$C74,SUMIF($L$4:$Z$4,$C74,$L$68:$Z$68)*INDEX($L$72:$Z$72,$C74-$L$4+1),SUMIF($L$4:$Z$4,$C74,$L$68:$Z$68)*L$71))} -> 0 | M74: {=IF(M$4<$C74,0,IF(M$4=$C74,SUMIF($L$4:$Z$4,$C74,$L$68:$Z$68)*INDEX($L$72:$Z$72,$C74-$L$4+1),SUMIF($L$4:$Z$4,$C74,$L$68:$Z$68)*M$71))} -> 0 | N74: {=IF(N$4<$C74,0,IF(N$4=$C74,SUMIF($L$4:$Z$4,$C74,$L$68:$Z$68)*INDEX($L$72:$Z$72,$C74-$L$4+1),SUMIF($L$4:$Z$4,$C74,$L$68:$Z$68)*N$71))} -> 0 | O74: {=IF(O$4<$C74,0,IF(O$4=$C74,SUMIF($L$4:$Z$4,$C74,$L$68:$Z$68)*INDEX($L$72:$Z$72,$C74-$L$4+1),SUMIF($L$4:$Z$4,$C74,$L$68:$Z$68)*O$71))} -> 0 | P74: {=IF(P$4<$C74,0,IF(P$4=$C74,SUMIF($L$4:$Z$4,$C74,$L$68:$Z$68)*INDEX($L$72:$Z$72,$C74-$L$4+1),SUMIF($L$4:$Z$4,$C74,$L$68:$Z$68)*P$71))} -> 0 | Q74: {=IF(Q$4<$C74,0,IF(Q$4=$C74,SUMIF($L$4:$Z$4,$C74,$L$68:$Z$68)*INDEX($L$72:$Z$72,$C74-$L$4+1),SUMIF($L$4:$Z$4,$C74,$L$68:$Z$68)*Q$71))} -> 0 | R74: {=IF(R$4<$C74,0,IF(R$4=$C74,SUMIF($L$4:$Z$4,$C74,$L$68:$Z$68)*INDEX($L$72:$Z$72,$C74-$L$4+1),SUMIF($L$4:$Z$4,$C74,$L$68:$Z$68)*R$71))} -> 0 | S74: {=IF(S$4<$C74,0,IF(S$4=$C74,SUMIF($L$4:$Z$4,$C74,$L$68:$Z$68)*INDEX($L$72:$Z$72,$C74-$L$4+1),SUMIF($L$4:$Z$4,$C74,$L$68:$Z$68)*S$71))} -> 0 | ... Z74: {=IF(Z$4<$C74,0,IF(Z$4=$C74,SUMIF($L$4:$Z$4,$C74,$L$68:$Z$68)*INDEX($L$72:$Z$72,$C74-$L$4+1),SUMIF($L$4:$Z$4,$C74,$L$68:$Z$68)*Z$71))} -> 0
C75: =C74+1 -> 2026 | E75: SAR'000 | G75: =SUMIF($L$4:$Z$4,$C75,$L$39:$Z$39) -> 141107.08 | J75: =SUM(L75:Z75) -> 0 | L75: {=IF(L$4<$C75,0,IF(L$4=$C75,SUMIF($L$4:$Z$4,$C75,$L$68:$Z$68)*INDEX($L$72:$Z$72,$C75-$L$4+1),SUMIF($L$4:$Z$4,$C75,$L$68:$Z$68)*L$71))} -> 0 | M75: {=IF(M$4<$C75,0,IF(M$4=$C75,SUMIF($L$4:$Z$4,$C75,$L$68:$Z$68)*INDEX($L$72:$Z$72,$C75-$L$4+1),SUMIF($L$4:$Z$4,$C75,$L$68:$Z$68)*M$71))} -> 0 | N75: {=IF(N$4<$C75,0,IF(N$4=$C75,SUMIF($L$4:$Z$4,$C75,$L$68:$Z$68)*INDEX($L$72:$Z$72,$C75-$L$4+1),SUMIF($L$4:$Z$4,$C75,$L$68:$Z$68)*N$71))} -> 0 | O75: {=IF(O$4<$C75,0,IF(O$4=$C75,SUMIF($L$4:$Z$4,$C75,$L$68:$Z$68)*INDEX($L$72:$Z$72,$C75-$L$4+1),SUMIF($L$4:$Z$4,$C75,$L$68:$Z$68)*O$71))} -> 0 | P75: {=IF(P$4<$C75,0,IF(P$4=$C75,SUMIF($L$4:$Z$4,$C75,$L$68:$Z$68)*INDEX($L$72:$Z$72,$C75-$L$4+1),SUMIF($L$4:$Z$4,$C75,$L$68:$Z$68)*P$71))} -> 0 | Q75: {=IF(Q$4<$C75,0,IF(Q$4=$C75,SUMIF($L$4:$Z$4,$C75,$L$68:$Z$68)*INDEX($L$72:$Z$72,$C75-$L$4+1),SUMIF($L$4:$Z$4,$C75,$L$68:$Z$68)*Q$71))} -> 0 | R75: {=IF(R$4<$C75,0,IF(R$4=$C75,SUMIF($L$4:$Z$4,$C75,$L$68:$Z$68)*INDEX($L$72:$Z$72,$C75-$L$4+1),SUMIF($L$4:$Z$4,$C75,$L$68:$Z$68)*R$71))} -> 0 | S75: {=IF(S$4<$C75,0,IF(S$4=$C75,SUMIF($L$4:$Z$4,$C75,$L$68:$Z$68)*INDEX($L$72:$Z$72,$C75-$L$4+1),SUMIF($L$4:$Z$4,$C75,$L$68:$Z$68)*S$71))} -> 0 | ... Z75: {=IF(Z$4<$C75,0,IF(Z$4=$C75,SUMIF($L$4:$Z$4,$C75,$L$68:$Z$68)*INDEX($L$72:$Z$72,$C75-$L$4+1),SUMIF($L$4:$Z$4,$C75,$L$68:$Z$68)*Z$71))} -> 0
C76: =C75+1 -> 2027 | E76: SAR'000 | G76: =SUMIF($L$4:$Z$4,$C76,$L$39:$Z$39) -> 846608.96 | J76: =SUM(L76:Z76) -> 531599 | L76: {=IF(L$4<$C76,0,IF(L$4=$C76,SUMIF($L$4:$Z$4,$C76,$L$68:$Z$68)*INDEX($L$72:$Z$72,$C76-$L$4+1),SUMIF($L$4:$Z$4,$C76,$L$68:$Z$68)*L$71))} -> 0 | M76: {=IF(M$4<$C76,0,IF(M$4=$C76,SUMIF($L$4:$Z$4,$C76,$L$68:$Z$68)*INDEX($L$72:$Z$72,$C76-$L$4+1),SUMIF($L$4:$Z$4,$C76,$L$68:$Z$68)*M$71))} -> 0 | N76: {=IF(N$4<$C76,0,IF(N$4=$C76,SUMIF($L$4:$Z$4,$C76,$L$68:$Z$68)*INDEX($L$72:$Z$72,$C76-$L$4+1),SUMIF($L$4:$Z$4,$C76,$L$68:$Z$68)*N$71))} -> 106319.8 | O76: {=IF(O$4<$C76,0,IF(O$4=$C76,SUMIF($L$4:$Z$4,$C76,$L$68:$Z$68)*INDEX($L$72:$Z$72,$C76-$L$4+1),SUMIF($L$4:$Z$4,$C76,$L$68:$Z$68)*O$71))} -> 159479.7 | P76: {=IF(P$4<$C76,0,IF(P$4=$C76,SUMIF($L$4:$Z$4,$C76,$L$68:$Z$68)*INDEX($L$72:$Z$72,$C76-$L$4+1),SUMIF($L$4:$Z$4,$C76,$L$68:$Z$68)*P$71))} -> 159479.7 | Q76: {=IF(Q$4<$C76,0,IF(Q$4=$C76,SUMIF($L$4:$Z$4,$C76,$L$68:$Z$68)*INDEX($L$72:$Z$72,$C76-$L$4+1),SUMIF($L$4:$Z$4,$C76,$L$68:$Z$68)*Q$71))} -> 79739.85 | R76: {=IF(R$4<$C76,0,IF(R$4=$C76,SUMIF($L$4:$Z$4,$C76,$L$68:$Z$68)*INDEX($L$72:$Z$72,$C76-$L$4+1),SUMIF($L$4:$Z$4,$C76,$L$68:$Z$68)*R$71))} -> 26579.95 | S76: {=IF(S$4<$C76,0,IF(S$4=$C76,SUMIF($L$4:$Z$4,$C76,$L$68:$Z$68)*INDEX($L$72:$Z$72,$C76-$L$4+1),SUMIF($L$4:$Z$4,$C76,$L$68:$Z$68)*S$71))} -> 0 | ... Z76: {=IF(Z$4<$C76,0,IF(Z$4=$C76,SUMIF($L$4:$Z$4,$C76,$L$68:$Z$68)*INDEX($L$72:$Z$72,$C76-$L$4+1),SUMIF($L$4:$Z$4,$C76,$L$68:$Z$68)*Z$71))} -> 0
C77: =C76+1 -> 2028 | E77: SAR'000 | G77: =SUMIF($L$4:$Z$4,$C77,$L$39:$Z$39) -> 846608.96 | J77: =SUM(L77:Z77) -> 531599 | L77: {=IF(L$4<$C77,0,IF(L$4=$C77,SUMIF($L$4:$Z$4,$C77,$L$68:$Z$68)*INDEX($L$72:$Z$72,$C77-$L$4+1),SUMIF($L$4:$Z$4,$C77,$L$68:$Z$68)*L$71))} -> 0 | M77: {=IF(M$4<$C77,0,IF(M$4=$C77,SUMIF($L$4:$Z$4,$C77,$L$68:$Z$68)*INDEX($L$72:$Z$72,$C77-$L$4+1),SUMIF($L$4:$Z$4,$C77,$L$68:$Z$68)*M$71))} -> 0 | N77: {=IF(N$4<$C77,0,IF(N$4=$C77,SUMIF($L$4:$Z$4,$C77,$L$68:$Z$68)*INDEX($L$72:$Z$72,$C77-$L$4+1),SUMIF($L$4:$Z$4,$C77,$L$68:$Z$68)*N$71))} -> 0 | O77: {=IF(O$4<$C77,0,IF(O$4=$C77,SUMIF($L$4:$Z$4,$C77,$L$68:$Z$68)*INDEX($L$72:$Z$72,$C77-$L$4+1),SUMIF($L$4:$Z$4,$C77,$L$68:$Z$68)*O$71))} -> 265799.5 | P77: {=IF(P$4<$C77,0,IF(P$4=$C77,SUMIF($L$4:$Z$4,$C77,$L$68:$Z$68)*INDEX($L$72:$Z$72,$C77-$L$4+1),SUMIF($L$4:$Z$4,$C77,$L$68:$Z$68)*P$71))} -> 159479.7 | Q77: {=IF(Q$4<$C77,0,IF(Q$4=$C77,SUMIF($L$4:$Z$4,$C77,$L$68:$Z$68)*INDEX($L$72:$Z$72,$C77-$L$4+1),SUMIF($L$4:$Z$4,$C77,$L$68:$Z$68)*Q$71))} -> 79739.85 | R77: {=IF(R$4<$C77,0,IF(R$4=$C77,SUMIF($L$4:$Z$4,$C77,$L$68:$Z$68)*INDEX($L$72:$Z$72,$C77-$L$4+1),SUMIF($L$4:$Z$4,$C77,$L$68:$Z$68)*R$71))} -> 26579.95 | S77: {=IF(S$4<$C77,0,IF(S$4=$C77,SUMIF($L$4:$Z$4,$C77,$L$68:$Z$68)*INDEX($L$72:$Z$72,$C77-$L$4+1),SUMIF($L$4:$Z$4,$C77,$L$68:$Z$68)*S$71))} -> 0 | ... Z77: {=IF(Z$4<$C77,0,IF(Z$4=$C77,SUMIF($L$4:$Z$4,$C77,$L$68:$Z$68)*INDEX($L$72:$Z$72,$C77-$L$4+1),SUMIF($L$4:$Z$4,$C77,$L$68:$Z$68)*Z$71))} -> 0
C78: =C77+1 -> 2029 | E78: SAR'000 | G78: =SUMIF($L$4:$Z$4,$C78,$L$39:$Z$39) -> 705501.89 | J78: =SUM(L78:Z78) -> 531599 | L78: {=IF(L$4<$C78,0,IF(L$4=$C78,SUMIF($L$4:$Z$4,$C78,$L$68:$Z$68)*INDEX($L$72:$Z$72,$C78-$L$4+1),SUMIF($L$4:$Z$4,$C78,$L$68:$Z$68)*L$71))} -> 0 | M78: {=IF(M$4<$C78,0,IF(M$4=$C78,SUMIF($L$4:$Z$4,$C78,$L$68:$Z$68)*INDEX($L$72:$Z$72,$C78-$L$4+1),SUMIF($L$4:$Z$4,$C78,$L$68:$Z$68)*M$71))} -> 0 | N78: {=IF(N$4<$C78,0,IF(N$4=$C78,SUMIF($L$4:$Z$4,$C78,$L$68:$Z$68)*INDEX($L$72:$Z$72,$C78-$L$4+1),SUMIF($L$4:$Z$4,$C78,$L$68:$Z$68)*N$71))} -> 0 | O78: {=IF(O$4<$C78,0,IF(O$4=$C78,SUMIF($L$4:$Z$4,$C78,$L$68:$Z$68)*INDEX($L$72:$Z$72,$C78-$L$4+1),SUMIF($L$4:$Z$4,$C78,$L$68:$Z$68)*O$71))} -> 0 | P78: {=IF(P$4<$C78,0,IF(P$4=$C78,SUMIF($L$4:$Z$4,$C78,$L$68:$Z$68)*INDEX($L$72:$Z$72,$C78-$L$4+1),SUMIF($L$4:$Z$4,$C78,$L$68:$Z$68)*P$71))} -> 425279.2 | Q78: {=IF(Q$4<$C78,0,IF(Q$4=$C78,SUMIF($L$4:$Z$4,$C78,$L$68:$Z$68)*INDEX($L$72:$Z$72,$C78-$L$4+1),SUMIF($L$4:$Z$4,$C78,$L$68:$Z$68)*Q$71))} -> 79739.85 | R78: {=IF(R$4<$C78,0,IF(R$4=$C78,SUMIF($L$4:$Z$4,$C78,$L$68:$Z$68)*INDEX($L$72:$Z$72,$C78-$L$4+1),SUMIF($L$4:$Z$4,$C78,$L$68:$Z$68)*R$71))} -> 26579.95 | S78: {=IF(S$4<$C78,0,IF(S$4=$C78,SUMIF($L$4:$Z$4,$C78,$L$68:$Z$68)*INDEX($L$72:$Z$72,$C78-$L$4+1),SUMIF($L$4:$Z$4,$C78,$L$68:$Z$68)*S$71))} -> 0 | ... Z78: {=IF(Z$4<$C78,0,IF(Z$4=$C78,SUMIF($L$4:$Z$4,$C78,$L$68:$Z$68)*INDEX($L$72:$Z$72,$C78-$L$4+1),SUMIF($L$4:$Z$4,$C78,$L$68:$Z$68)*Z$71))} -> 0
C79: =C78+1 -> 2030 | E79: SAR'000 | G79: =SUMIF($L$4:$Z$4,$C79,$L$39:$Z$39) -> 0 | J79: =SUM(L79:Z79) -> 0 | L79: {=IF(L$4<$C79,0,IF(L$4=$C79,SUMIF($L$4:$Z$4,$C79,$L$68:$Z$68)*INDEX($L$72:$Z$72,$C79-$L$4+1),SUMIF($L$4:$Z$4,$C79,$L$68:$Z$68)*L$71))} -> 0 | M79: {=IF(M$4<$C79,0,IF(M$4=$C79,SUMIF($L$4:$Z$4,$C79,$L$68:$Z$68)*INDEX($L$72:$Z$72,$C79-$L$4+1),SUMIF($L$4:$Z$4,$C79,$L$68:$Z$68)*M$71))} -> 0 | N79: {=IF(N$4<$C79,0,IF(N$4=$C79,SUMIF($L$4:$Z$4,$C79,$L$68:$Z$68)*INDEX($L$72:$Z$72,$C79-$L$4+1),SUMIF($L$4:$Z$4,$C79,$L$68:$Z$68)*N$71))} -> 0 | O79: {=IF(O$4<$C79,0,IF(O$4=$C79,SUMIF($L$4:$Z$4,$C79,$L$68:$Z$68)*INDEX($L$72:$Z$72,$C79-$L$4+1),SUMIF($L$4:$Z$4,$C79,$L$68:$Z$68)*O$71))} -> 0 | P79: {=IF(P$4<$C79,0,IF(P$4=$C79,SUMIF($L$4:$Z$4,$C79,$L$68:$Z$68)*INDEX($L$72:$Z$72,$C79-$L$4+1),SUMIF($L$4:$Z$4,$C79,$L$68:$Z$68)*P$71))} -> 0 | Q79: {=IF(Q$4<$C79,0,IF(Q$4=$C79,SUMIF($L$4:$Z$4,$C79,$L$68:$Z$68)*INDEX($L$72:$Z$72,$C79-$L$4+1),SUMIF($L$4:$Z$4,$C79,$L$68:$Z$68)*Q$71))} -> 0 | R79: {=IF(R$4<$C79,0,IF(R$4=$C79,SUMIF($L$4:$Z$4,$C79,$L$68:$Z$68)*INDEX($L$72:$Z$72,$C79-$L$4+1),SUMIF($L$4:$Z$4,$C79,$L$68:$Z$68)*R$71))} -> 0 | S79: {=IF(S$4<$C79,0,IF(S$4=$C79,SUMIF($L$4:$Z$4,$C79,$L$68:$Z$68)*INDEX($L$72:$Z$72,$C79-$L$4+1),SUMIF($L$4:$Z$4,$C79,$L$68:$Z$68)*S$71))} -> 0 | ... Z79: {=IF(Z$4<$C79,0,IF(Z$4=$C79,SUMIF($L$4:$Z$4,$C79,$L$68:$Z$68)*INDEX($L$72:$Z$72,$C79-$L$4+1),SUMIF($L$4:$Z$4,$C79,$L$68:$Z$68)*Z$71))} -> 0
C80: Total | E80: SAR'000 | G80: =SUM(G74:G79) -> 2539826.9 | J80: =SUM(J74:J79) -> 1594797 | L80: =SUM(L74:L79) -> 0 | M80: =SUM(M74:M79) -> 0 | N80: =SUM(N74:N79) -> 106319.8 | O80: =SUM(O74:O79) -> 425279.2 | P80: =SUM(P74:P79) -> 744238.6 | Q80: =SUM(Q74:Q79) -> 239219.55 | R80: =SUM(R74:R79) -> 79739.85 | S80: =SUM(S74:S79) -> 0 | ... Z80: =SUM(Z74:Z79) -> 0
B82: Residential Tower 01 (Phase 2) | D82: 2
C83: Indexation Factor | E83: % | G83: 0 | L83: =(1+$G83)^L$6 -> 1 | M83: =(1+$G83)^M$6 -> 1 | N83: =(1+$G83)^N$6 -> 1 | O83: =(1+$G83)^O$6 -> 1 | P83: =(1+$G83)^P$6 -> 1 | Q83: =(1+$G83)^Q$6 -> 1 | R83: =(1+$G83)^R$6 -> 1 | S83: =(1+$G83)^S$6 -> 1 | ... Z83: =(1+$G83)^Z$6 -> 1
C85: Pre Sales Units | G85: Units | H85: SAR/Unit
C86: Branded Suites | G86: 70 | H86: 2590000 | L86: 0 | M86: 0.05 | N86: 0.3 | O86: 0.3 | P86: 0.25 | Q86: 0 | R86: 0 | S86: 0 | T86: 0 | U86: 0 | V86: 0 | W86: 0 | X86: 0 | Y86: 0 | Z86: 0
C87: 1 BR Apartment | G87: 160 | H87: 2705625 | L87: 0 | M87: 0.05 | N87: 0.3 | O87: 0.3 | P87: 0.25 | Q87: 0 | R87: 0 | S87: 0 | T87: 0 | U87: 0 | V87: 0 | W87: 0 | X87: 0 | Y87: 0 | Z87: 0
C88: 2 BR Apartment | G88: 80 | H88: 3933900 | L88: 0 | M88: 0.05 | N88: 0.3 | O88: 0.3 | P88: 0.25 | Q88: 0 | R88: 0 | S88: 0 | T88: 0 | U88: 0 | V88: 0 | W88: 0 | X88: 0 | Y88: 0 | Z88: 0
C90: Pre-Sale Area
C91: Branded Suites | E91: Units | G91: =J91 -> 64 | J91: =SUM(L91:Z91) -> 64 | L91: =IF(ROUND($G86-SUM($K91:K91),0)>ROUND($G86*L86,0),ROUND($G86*L86,0),ROUND($G86-SUM($K91:K91),0)) -> 0 | M91: =IF(ROUND($G86-SUM($K91:L91),0)>ROUND($G86*M86,0),ROUND($G86*M86,0),ROUND($G86-SUM($K91:L91),0)) -> 4 | N91: =IF(ROUND($G86-SUM($K91:M91),0)>ROUND($G86*N86,0),ROUND($G86*N86,0),ROUND($G86-SUM($K91:M91),0)) -> 21 | O91: =IF(ROUND($G86-SUM($K91:N91),0)>ROUND($G86*O86,0),ROUND($G86*O86,0),ROUND($G86-SUM($K91:N91),0)) -> 21 | P91: =IF(ROUND($G86-SUM($K91:O91),0)>ROUND($G86*P86,0),ROUND($G86*P86,0),ROUND($G86-SUM($K91:O91),0)) -> 18 | Q91: =IF(ROUND($G86-SUM($K91:P91),0)>ROUND($G86*Q86,0),ROUND($G86*Q86,0),ROUND($G86-SUM($K91:P91),0)) -> 0 | R91: =IF(ROUND($G86-SUM($K91:Q91),0)>ROUND($G86*R86,0),ROUND($G86*R86,0),ROUND($G86-SUM($K91:Q91),0)) -> 0 | S91: =IF(ROUND($G86-SUM($K91:R91),0)>ROUND($G86*S86,0),ROUND($G86*S86,0),ROUND($G86-SUM($K91:R91),0)) -> 0 | ... Z91: =IF(ROUND($G86-SUM($K91:Y91),0)>ROUND($G86*Z86,0),ROUND($G86*Z86,0),ROUND($G86-SUM($K91:Y91),0)) -> 0
C92: 1 BR Apartment | E92: Units | G92: =J92 -> 144 | J92: =SUM(L92:Z92) -> 144 | L92: =IF(ROUND($G87-SUM($K92:K92),0)>ROUND($G87*L87,0),ROUND($G87*L87,0),ROUND($G87-SUM($K92:K92),0)) -> 0 | M92: =IF(ROUND($G87-SUM($K92:L92),0)>ROUND($G87*M87,0),ROUND($G87*M87,0),ROUND($G87-SUM($K92:L92),0)) -> 8 | N92: =IF(ROUND($G87-SUM($K92:M92),0)>ROUND($G87*N87,0),ROUND($G87*N87,0),ROUND($G87-SUM($K92:M92),0)) -> 48 | O92: =IF(ROUND($G87-SUM($K92:N92),0)>ROUND($G87*O87,0),ROUND($G87*O87,0),ROUND($G87-SUM($K92:N92),0)) -> 48 | P92: =IF(ROUND($G87-SUM($K92:O92),0)>ROUND($G87*P87,0),ROUND($G87*P87,0),ROUND($G87-SUM($K92:O92),0)) -> 40 | Q92: =IF(ROUND($G87-SUM($K92:P92),0)>ROUND($G87*Q87,0),ROUND($G87*Q87,0),ROUND($G87-SUM($K92:P92),0)) -> 0 | R92: =IF(ROUND($G87-SUM($K92:Q92),0)>ROUND($G87*R87,0),ROUND($G87*R87,0),ROUND($G87-SUM($K92:Q92),0)) -> 0 | S92: =IF(ROUND($G87-SUM($K92:R92),0)>ROUND($G87*S87,0),ROUND($G87*S87,0),ROUND($G87-SUM($K92:R92),0)) -> 0 | ... Z92: =IF(ROUND($G87-SUM($K92:Y92),0)>ROUND($G87*Z87,0),ROUND($G87*Z87,0),ROUND($G87-SUM($K92:Y92),0)) -> 0
C93: 2 BR Apartment | E93: Units | G93: =J93 -> 72 | J93: =SUM(L93:Z93) -> 72 | L93: =IF(ROUND($G88-SUM($K93:K93),0)>ROUND($G88*L88,0),ROUND($G88*L88,0),ROUND($G88-SUM($K93:K93),0)) -> 0 | M93: =IF(ROUND($G88-SUM($K93:L93),0)>ROUND($G88*M88,0),ROUND($G88*M88,0),ROUND($G88-SUM($K93:L93),0)) -> 4 | N93: =IF(ROUND($G88-SUM($K93:M93),0)>ROUND($G88*N88,0),ROUND($G88*N88,0),ROUND($G88-SUM($K93:M93),0)) -> 24 | O93: =IF(ROUND($G88-SUM($K93:N93),0)>ROUND($G88*O88,0),ROUND($G88*O88,0),ROUND($G88-SUM($K93:N93),0)) -> 24 | P93: =IF(ROUND($G88-SUM($K93:O93),0)>ROUND($G88*P88,0),ROUND($G88*P88,0),ROUND($G88-SUM($K93:O93),0)) -> 20 | Q93: =IF(ROUND($G88-SUM($K93:P93),0)>ROUND($G88*Q88,0),ROUND($G88*Q88,0),ROUND($G88-SUM($K93:P93),0)) -> 0 | R93: =IF(ROUND($G88-SUM($K93:Q93),0)>ROUND($G88*R88,0),ROUND($G88*R88,0),ROUND($G88-SUM($K93:Q93),0)) -> 0 | S93: =IF(ROUND($G88-SUM($K93:R93),0)>ROUND($G88*S88,0),ROUND($G88*S88,0),ROUND($G88-SUM($K93:R93),0)) -> 0 | ... Z93: =IF(ROUND($G88-SUM($K93:Y93),0)>ROUND($G88*Z88,0),ROUND($G88*Z88,0),ROUND($G88-SUM($K93:Y93),0)) -> 0
C94: Total Area | E94: Area SQM | G94: =SUM(G91:G93) -> 280 | J94: =SUM(J91:J93) -> 280 | L94: =SUM(L91:L93) -> 0 | M94: =SUM(M91:M93) -> 16 | N94: =SUM(N91:N93) -> 93 | O94: =SUM(O91:O93) -> 93 | P94: =SUM(P91:P93) -> 78 | Q94: =SUM(Q91:Q93) -> 0 | R94: =SUM(R91:R93) -> 0 | S94: =SUM(S91:S93) -> 0 | ... Z94: =SUM(Z91:Z93) -> 0
C96: Pre sales
C97: Branded Suites | E97: SAR'000 | G97: =$H86 -> 2590000 | J97: =SUM(L97:Z97) -> 165760 | L97: =(($G97*L$83)*L91)/$G$6 -> 0 | M97: =(($G97*M$83)*M91)/$G$6 -> 10360 | N97: =(($G97*N$83)*N91)/$G$6 -> 54390 | O97: =(($G97*O$83)*O91)/$G$6 -> 54390 | P97: =(($G97*P$83)*P91)/$G$6 -> 46620 | Q97: =(($G97*Q$83)*Q91)/$G$6 -> 0 | R97: =(($G97*R$83)*R91)/$G$6 -> 0 | S97: =(($G97*S$83)*S91)/$G$6 -> 0 | ... Z97: =(($G97*Z$83)*Z91)/$G$6 -> 0
C98: 1 BR Apartment | E98: SAR'000 | G98: =$H87 -> 2705625 | J98: =SUM(L98:Z98) -> 389610 | L98: =(($G98*L$83)*L92)/$G$6 -> 0 | M98: =(($G98*M$83)*M92)/$G$6 -> 21645 | N98: =(($G98*N$83)*N92)/$G$6 -> 129870 | O98: =(($G98*O$83)*O92)/$G$6 -> 129870 | P98: =(($G98*P$83)*P92)/$G$6 -> 108225 | Q98: =(($G98*Q$83)*Q92)/$G$6 -> 0 | R98: =(($G98*R$83)*R92)/$G$6 -> 0 | S98: =(($G98*S$83)*S92)/$G$6 -> 0 | ... Z98: =(($G98*Z$83)*Z92)/$G$6 -> 0
C99: 2 BR Apartment | E99: SAR'000 | G99: =$H88 -> 3933900 | J99: =SUM(L99:Z99) -> 283240.8 | L99: =(($G99*L$83)*L93)/$G$6 -> 0 | M99: =(($G99*M$83)*M93)/$G$6 -> 15735.6 | N99: =(($G99*N$83)*N93)/$G$6 -> 94413.6 | O99: =(($G99*O$83)*O93)/$G$6 -> 94413.6 | P99: =(($G99*P$83)*P93)/$G$6 -> 78678 | Q99: =(($G99*Q$83)*Q93)/$G$6 -> 0 | R99: =(($G99*R$83)*R93)/$G$6 -> 0 | S99: =(($G99*S$83)*S93)/$G$6 -> 0 | ... Z99: =(($G99*Z$83)*Z93)/$G$6 -> 0
C100: Total Pre Sales | E100: SAR'000 | G100: =AVERAGE(G97:G99) -> 3076508.3 | J100: =SUM(L100:Z100) -> 838610.8 | L100: =SUM(L97:L99) -> 0 | M100: =SUM(M97:M99) -> 47740.6 | N100: =SUM(N97:N99) -> 278673.6 | O100: =SUM(O97:O99) -> 278673.6 | P100: =SUM(P97:P99) -> 233523 | Q100: =SUM(Q97:Q99) -> 0 | R100: =SUM(R97:R99) -> 0 | S100: =SUM(S97:S99) -> 0 | ... Z100: =SUM(Z97:Z99) -> 0
C102: Cumulative cash payment profile
C103: Cash Payment Profile | E103: % | L103: 0 | M103: 0.2 | N103: 0.3 | O103: 0.3 | P103: 0.15 | Q103: 0.05 | R103: 0 | S103: 0 | T103: 0 | U103: 0 | V103: 0 | W103: 0 | X103: 0 | Y103: 0 | Z103: 0
C104: Cumulative Payment Profile | E104: % | L104: =K104+L103 -> 0 | M104: =L104+M103 -> 0.2 | N104: =M104+N103 -> 0.5 | O104: =N104+O103 -> 0.8 | P104: =O104+P103 -> 0.95 | Q104: =P104+Q103 -> 1 | R104: =Q104+R103 -> 1 | S104: =R104+S103 -> 1 | ... Z104: =Y104+Z103 -> 1
C106: 2025 | E106: SAR'000 | G106: =SUMIF($L$4:$Z$4,$C106,$L$100:$Z$100) -> 0 | J106: =SUM(L106:Z106) -> 0 | L106: {=IF(L$4<$C106,0,IF(L$4=$C106,SUMIF($L$4:$Z$4,$C106,$L$100:$Z$100)*INDEX($L$104:$Z$104,$C106-$L$4+1),SUMIF($L$4:$Z$4,$C106,$L$100:$Z$100)*L$103))} -> 0 | M106: {=IF(M$4<$C106,0,IF(M$4=$C106,SUMIF($L$4:$Z$4,$C106,$L$100:$Z$100)*INDEX($L$104:$Z$104,$C106-$L$4+1),SUMIF($L$4:$Z$4,$C106,$L$100:$Z$100)*M$103))} -> 0 | N106: {=IF(N$4<$C106,0,IF(N$4=$C106,SUMIF($L$4:$Z$4,$C106,$L$100:$Z$100)*INDEX($L$104:$Z$104,$C106-$L$4+1),SUMIF($L$4:$Z$4,$C106,$L$100:$Z$100)*N$103))} -> 0 | O106: {=IF(O$4<$C106,0,IF(O$4=$C106,SUMIF($L$4:$Z$4,$C106,$L$100:$Z$100)*INDEX($L$104:$Z$104,$C106-$L$4+1),SUMIF($L$4:$Z$4,$C106,$L$100:$Z$100)*O$103))} -> 0 | P106: {=IF(P$4<$C106,0,IF(P$4=$C106,SUMIF($L$4:$Z$4,$C106,$L$100:$Z$100)*INDEX($L$104:$Z$104,$C106-$L$4+1),SUMIF($L$4:$Z$4,$C106,$L$100:$Z$100)*P$103))} -> 0 | Q106: {=IF(Q$4<$C106,0,IF(Q$4=$C106,SUMIF($L$4:$Z$4,$C106,$L$100:$Z$100)*INDEX($L$104:$Z$104,$C106-$L$4+1),SUMIF($L$4:$Z$4,$C106,$L$100:$Z$100)*Q$103))} -> 0 | R106: {=IF(R$4<$C106,0,IF(R$4=$C106,SUMIF($L$4:$Z$4,$C106,$L$100:$Z$100)*INDEX($L$104:$Z$104,$C106-$L$4+1),SUMIF($L$4:$Z$4,$C106,$L$100:$Z$100)*R$103))} -> 0 | S106: {=IF(S$4<$C106,0,IF(S$4=$C106,SUMIF($L$4:$Z$4,$C106,$L$100:$Z$100)*INDEX($L$104:$Z$104,$C106-$L$4+1),SUMIF($L$4:$Z$4,$C106,$L$100:$Z$100)*S$103))} -> 0 | ... Z106: {=IF(Z$4<$C106,0,IF(Z$4=$C106,SUMIF($L$4:$Z$4,$C106,$L$100:$Z$100)*INDEX($L$104:$Z$104,$C106-$L$4+1),SUMIF($L$4:$Z$4,$C106,$L$100:$Z$100)*Z$103))} -> 0
C107: =C106+1 -> 2026 | E107: SAR'000 | G107: =SUMIF($L$4:$Z$4,$C107,$L$100:$Z$100) -> 47740.6 | J107: =SUM(L107:Z107) -> 47740.6 | L107: {=IF(L$4<$C107,0,IF(L$4=$C107,SUMIF($L$4:$Z$4,$C107,$L$100:$Z$100)*INDEX($L$104:$Z$104,$C107-$L$4+1),SUMIF($L$4:$Z$4,$C107,$L$100:$Z$100)*L$103))} -> 0 | M107: {=IF(M$4<$C107,0,IF(M$4=$C107,SUMIF($L$4:$Z$4,$C107,$L$100:$Z$100)*INDEX($L$104:$Z$104,$C107-$L$4+1),SUMIF($L$4:$Z$4,$C107,$L$100:$Z$100)*M$103))} -> 9548.12 | N107: {=IF(N$4<$C107,0,IF(N$4=$C107,SUMIF($L$4:$Z$4,$C107,$L$100:$Z$100)*INDEX($L$104:$Z$104,$C107-$L$4+1),SUMIF($L$4:$Z$4,$C107,$L$100:$Z$100)*N$103))} -> 14322.18 | O107: {=IF(O$4<$C107,0,IF(O$4=$C107,SUMIF($L$4:$Z$4,$C107,$L$100:$Z$100)*INDEX($L$104:$Z$104,$C107-$L$4+1),SUMIF($L$4:$Z$4,$C107,$L$100:$Z$100)*O$103))} -> 14322.18 | P107: {=IF(P$4<$C107,0,IF(P$4=$C107,SUMIF($L$4:$Z$4,$C107,$L$100:$Z$100)*INDEX($L$104:$Z$104,$C107-$L$4+1),SUMIF($L$4:$Z$4,$C107,$L$100:$Z$100)*P$103))} -> 7161.09 | Q107: {=IF(Q$4<$C107,0,IF(Q$4=$C107,SUMIF($L$4:$Z$4,$C107,$L$100:$Z$100)*INDEX($L$104:$Z$104,$C107-$L$4+1),SUMIF($L$4:$Z$4,$C107,$L$100:$Z$100)*Q$103))} -> 2387.03 | R107: {=IF(R$4<$C107,0,IF(R$4=$C107,SUMIF($L$4:$Z$4,$C107,$L$100:$Z$100)*INDEX($L$104:$Z$104,$C107-$L$4+1),SUMIF($L$4:$Z$4,$C107,$L$100:$Z$100)*R$103))} -> 0 | S107: {=IF(S$4<$C107,0,IF(S$4=$C107,SUMIF($L$4:$Z$4,$C107,$L$100:$Z$100)*INDEX($L$104:$Z$104,$C107-$L$4+1),SUMIF($L$4:$Z$4,$C107,$L$100:$Z$100)*S$103))} -> 0 | ... Z107: {=IF(Z$4<$C107,0,IF(Z$4=$C107,SUMIF($L$4:$Z$4,$C107,$L$100:$Z$100)*INDEX($L$104:$Z$104,$C107-$L$4+1),SUMIF($L$4:$Z$4,$C107,$L$100:$Z$100)*Z$103))} -> 0
C108: =C107+1 -> 2027 | E108: SAR'000 | G108: =SUMIF($L$4:$Z$4,$C108,$L$100:$Z$100) -> 278673.6 | J108: =SUM(L108:Z108) -> 278673.6 | L108: {=IF(L$4<$C108,0,IF(L$4=$C108,SUMIF($L$4:$Z$4,$C108,$L$100:$Z$100)*INDEX($L$104:$Z$104,$C108-$L$4+1),SUMIF($L$4:$Z$4,$C108,$L$100:$Z$100)*L$103))} -> 0 | M108: {=IF(M$4<$C108,0,IF(M$4=$C108,SUMIF($L$4:$Z$4,$C108,$L$100:$Z$100)*INDEX($L$104:$Z$104,$C108-$L$4+1),SUMIF($L$4:$Z$4,$C108,$L$100:$Z$100)*M$103))} -> 0 | N108: {=IF(N$4<$C108,0,IF(N$4=$C108,SUMIF($L$4:$Z$4,$C108,$L$100:$Z$100)*INDEX($L$104:$Z$104,$C108-$L$4+1),SUMIF($L$4:$Z$4,$C108,$L$100:$Z$100)*N$103))} -> 139336.8 | O108: {=IF(O$4<$C108,0,IF(O$4=$C108,SUMIF($L$4:$Z$4,$C108,$L$100:$Z$100)*INDEX($L$104:$Z$104,$C108-$L$4+1),SUMIF($L$4:$Z$4,$C108,$L$100:$Z$100)*O$103))} -> 83602.08 | P108: {=IF(P$4<$C108,0,IF(P$4=$C108,SUMIF($L$4:$Z$4,$C108,$L$100:$Z$100)*INDEX($L$104:$Z$104,$C108-$L$4+1),SUMIF($L$4:$Z$4,$C108,$L$100:$Z$100)*P$103))} -> 41801.04 | Q108: {=IF(Q$4<$C108,0,IF(Q$4=$C108,SUMIF($L$4:$Z$4,$C108,$L$100:$Z$100)*INDEX($L$104:$Z$104,$C108-$L$4+1),SUMIF($L$4:$Z$4,$C108,$L$100:$Z$100)*Q$103))} -> 13933.68 | R108: {=IF(R$4<$C108,0,IF(R$4=$C108,SUMIF($L$4:$Z$4,$C108,$L$100:$Z$100)*INDEX($L$104:$Z$104,$C108-$L$4+1),SUMIF($L$4:$Z$4,$C108,$L$100:$Z$100)*R$103))} -> 0 | S108: {=IF(S$4<$C108,0,IF(S$4=$C108,SUMIF($L$4:$Z$4,$C108,$L$100:$Z$100)*INDEX($L$104:$Z$104,$C108-$L$4+1),SUMIF($L$4:$Z$4,$C108,$L$100:$Z$100)*S$103))} -> 0 | ... Z108: {=IF(Z$4<$C108,0,IF(Z$4=$C108,SUMIF($L$4:$Z$4,$C108,$L$100:$Z$100)*INDEX($L$104:$Z$104,$C108-$L$4+1),SUMIF($L$4:$Z$4,$C108,$L$100:$Z$100)*Z$103))} -> 0
C109: =C108+1 -> 2028 | E109: SAR'000 | G109: =SUMIF($L$4:$Z$4,$C109,$L$100:$Z$100) -> 278673.6 | J109: =SUM(L109:Z109) -> 278673.6 | L109: {=IF(L$4<$C109,0,IF(L$4=$C109,SUMIF($L$4:$Z$4,$C109,$L$100:$Z$100)*INDEX($L$104:$Z$104,$C109-$L$4+1),SUMIF($L$4:$Z$4,$C109,$L$100:$Z$100)*L$103))} -> 0 | M109: {=IF(M$4<$C109,0,IF(M$4=$C109,SUMIF($L$4:$Z$4,$C109,$L$100:$Z$100)*INDEX($L$104:$Z$104,$C109-$L$4+1),SUMIF($L$4:$Z$4,$C109,$L$100:$Z$100)*M$103))} -> 0 | N109: {=IF(N$4<$C109,0,IF(N$4=$C109,SUMIF($L$4:$Z$4,$C109,$L$100:$Z$100)*INDEX($L$104:$Z$104,$C109-$L$4+1),SUMIF($L$4:$Z$4,$C109,$L$100:$Z$100)*N$103))} -> 0 | O109: {=IF(O$4<$C109,0,IF(O$4=$C109,SUMIF($L$4:$Z$4,$C109,$L$100:$Z$100)*INDEX($L$104:$Z$104,$C109-$L$4+1),SUMIF($L$4:$Z$4,$C109,$L$100:$Z$100)*O$103))} -> 222938.88 | P109: {=IF(P$4<$C109,0,IF(P$4=$C109,SUMIF($L$4:$Z$4,$C109,$L$100:$Z$100)*INDEX($L$104:$Z$104,$C109-$L$4+1),SUMIF($L$4:$Z$4,$C109,$L$100:$Z$100)*P$103))} -> 41801.04 | Q109: {=IF(Q$4<$C109,0,IF(Q$4=$C109,SUMIF($L$4:$Z$4,$C109,$L$100:$Z$100)*INDEX($L$104:$Z$104,$C109-$L$4+1),SUMIF($L$4:$Z$4,$C109,$L$100:$Z$100)*Q$103))} -> 13933.68 | R109: {=IF(R$4<$C109,0,IF(R$4=$C109,SUMIF($L$4:$Z$4,$C109,$L$100:$Z$100)*INDEX($L$104:$Z$104,$C109-$L$4+1),SUMIF($L$4:$Z$4,$C109,$L$100:$Z$100)*R$103))} -> 0 | S109: {=IF(S$4<$C109,0,IF(S$4=$C109,SUMIF($L$4:$Z$4,$C109,$L$100:$Z$100)*INDEX($L$104:$Z$104,$C109-$L$4+1),SUMIF($L$4:$Z$4,$C109,$L$100:$Z$100)*S$103))} -> 0 | ... Z109: {=IF(Z$4<$C109,0,IF(Z$4=$C109,SUMIF($L$4:$Z$4,$C109,$L$100:$Z$100)*INDEX($L$104:$Z$104,$C109-$L$4+1),SUMIF($L$4:$Z$4,$C109,$L$100:$Z$100)*Z$103))} -> 0
C110: =C109+1 -> 2029 | E110: SAR'000 | G110: =SUMIF($L$4:$Z$4,$C110,$L$100:$Z$100) -> 233523 | J110: =SUM(L110:Z110) -> 233523 | L110: {=IF(L$4<$C110,0,IF(L$4=$C110,SUMIF($L$4:$Z$4,$C110,$L$100:$Z$100)*INDEX($L$104:$Z$104,$C110-$L$4+1),SUMIF($L$4:$Z$4,$C110,$L$100:$Z$100)*L$103))} -> 0 | M110: {=IF(M$4<$C110,0,IF(M$4=$C110,SUMIF($L$4:$Z$4,$C110,$L$100:$Z$100)*INDEX($L$104:$Z$104,$C110-$L$4+1),SUMIF($L$4:$Z$4,$C110,$L$100:$Z$100)*M$103))} -> 0 | N110: {=IF(N$4<$C110,0,IF(N$4=$C110,SUMIF($L$4:$Z$4,$C110,$L$100:$Z$100)*INDEX($L$104:$Z$104,$C110-$L$4+1),SUMIF($L$4:$Z$4,$C110,$L$100:$Z$100)*N$103))} -> 0 | O110: {=IF(O$4<$C110,0,IF(O$4=$C110,SUMIF($L$4:$Z$4,$C110,$L$100:$Z$100)*INDEX($L$104:$Z$104,$C110-$L$4+1),SUMIF($L$4:$Z$4,$C110,$L$100:$Z$100)*O$103))} -> 0 | P110: {=IF(P$4<$C110,0,IF(P$4=$C110,SUMIF($L$4:$Z$4,$C110,$L$100:$Z$100)*INDEX($L$104:$Z$104,$C110-$L$4+1),SUMIF($L$4:$Z$4,$C110,$L$100:$Z$100)*P$103))} -> 221846.85 | Q110: {=IF(Q$4<$C110,0,IF(Q$4=$C110,SUMIF($L$4:$Z$4,$C110,$L$100:$Z$100)*INDEX($L$104:$Z$104,$C110-$L$4+1),SUMIF($L$4:$Z$4,$C110,$L$100:$Z$100)*Q$103))} -> 11676.15 | R110: {=IF(R$4<$C110,0,IF(R$4=$C110,SUMIF($L$4:$Z$4,$C110,$L$100:$Z$100)*INDEX($L$104:$Z$104,$C110-$L$4+1),SUMIF($L$4:$Z$4,$C110,$L$100:$Z$100)*R$103))} -> 0 | S110: {=IF(S$4<$C110,0,IF(S$4=$C110,SUMIF($L$4:$Z$4,$C110,$L$100:$Z$100)*INDEX($L$104:$Z$104,$C110-$L$4+1),SUMIF($L$4:$Z$4,$C110,$L$100:$Z$100)*S$103))} -> 0 | ... Z110: {=IF(Z$4<$C110,0,IF(Z$4=$C110,SUMIF($L$4:$Z$4,$C110,$L$100:$Z$100)*INDEX($L$104:$Z$104,$C110-$L$4+1),SUMIF($L$4:$Z$4,$C110,$L$100:$Z$100)*Z$103))} -> 0
C111: =C110+1 -> 2030 | E111: SAR'000 | G111: =SUMIF($L$4:$Z$4,$C111,$L$100:$Z$100) -> 0 | J111: =SUM(L111:Z111) -> 0 | L111: {=IF(L$4<$C111,0,IF(L$4=$C111,SUMIF($L$4:$Z$4,$C111,$L$100:$Z$100)*INDEX($L$104:$Z$104,$C111-$L$4+1),SUMIF($L$4:$Z$4,$C111,$L$100:$Z$100)*L$103))} -> 0 | M111: {=IF(M$4<$C111,0,IF(M$4=$C111,SUMIF($L$4:$Z$4,$C111,$L$100:$Z$100)*INDEX($L$104:$Z$104,$C111-$L$4+1),SUMIF($L$4:$Z$4,$C111,$L$100:$Z$100)*M$103))} -> 0 | N111: {=IF(N$4<$C111,0,IF(N$4=$C111,SUMIF($L$4:$Z$4,$C111,$L$100:$Z$100)*INDEX($L$104:$Z$104,$C111-$L$4+1),SUMIF($L$4:$Z$4,$C111,$L$100:$Z$100)*N$103))} -> 0 | O111: {=IF(O$4<$C111,0,IF(O$4=$C111,SUMIF($L$4:$Z$4,$C111,$L$100:$Z$100)*INDEX($L$104:$Z$104,$C111-$L$4+1),SUMIF($L$4:$Z$4,$C111,$L$100:$Z$100)*O$103))} -> 0 | P111: {=IF(P$4<$C111,0,IF(P$4=$C111,SUMIF($L$4:$Z$4,$C111,$L$100:$Z$100)*INDEX($L$104:$Z$104,$C111-$L$4+1),SUMIF($L$4:$Z$4,$C111,$L$100:$Z$100)*P$103))} -> 0 | Q111: {=IF(Q$4<$C111,0,IF(Q$4=$C111,SUMIF($L$4:$Z$4,$C111,$L$100:$Z$100)*INDEX($L$104:$Z$104,$C111-$L$4+1),SUMIF($L$4:$Z$4,$C111,$L$100:$Z$100)*Q$103))} -> 0 | R111: {=IF(R$4<$C111,0,IF(R$4=$C111,SUMIF($L$4:$Z$4,$C111,$L$100:$Z$100)*INDEX($L$104:$Z$104,$C111-$L$4+1),SUMIF($L$4:$Z$4,$C111,$L$100:$Z$100)*R$103))} -> 0 | S111: {=IF(S$4<$C111,0,IF(S$4=$C111,SUMIF($L$4:$Z$4,$C111,$L$100:$Z$100)*INDEX($L$104:$Z$104,$C111-$L$4+1),SUMIF($L$4:$Z$4,$C111,$L$100:$Z$100)*S$103))} -> 0 | ... Z111: {=IF(Z$4<$C111,0,IF(Z$4=$C111,SUMIF($L$4:$Z$4,$C111,$L$100:$Z$100)*INDEX($L$104:$Z$104,$C111-$L$4+1),SUMIF($L$4:$Z$4,$C111,$L$100:$Z$100)*Z$103))} -> 0
C112: Total | E112: SAR'000 | G112: =SUM(G106:G111) -> 838610.8 | J112: =SUM(J106:J111) -> 838610.8 | L112: =SUM(L106:L111) -> 0 | M112: =SUM(M106:M111) -> 9548.12 | N112: =SUM(N106:N111) -> 153658.98 | O112: =SUM(O106:O111) -> 320863.14 | P112: =SUM(P106:P111) -> 312610.02 | Q112: =SUM(Q106:Q111) -> 41930.54 | R112: =SUM(R106:R111) -> 0 | S112: =SUM(S106:S111) -> 0 | ... Z112: =SUM(Z106:Z111) -> 0
B114: Sales Revenue During Operation
B116: Branded Apartments T2 & T3 | D116: 2
G117: Area SQM | H117: SAR/SQM
C118: 1 BR | G118: =G28 -> 47800 | H118: =H28 -> 33456.067 | L118: 0 | M118: 0 | N118: 0 | O118: 0 | P118: 0 | Q118: 0.1 | R118: 0 | S118: 0 | T118: 0 | U118: 0 | V118: 0 | W118: 0 | X118: 0 | Y118: 0 | Z118: 0
C119: 2 BR | G119: =G29 -> 36497.1 | H119: =H29 -> 33505.248 | L119: 0 | M119: 0 | N119: 0 | O119: 0 | P119: 0 | Q119: 0.1 | R119: 0 | S119: 0 | T119: 0 | U119: 0 | V119: 0 | W119: 0 | X119: 0 | Y119: 0 | Z119: 0
C121: Area sold during operation
C122: 1 BR | E122: Area SQM | G122: {=SUM($L118:$Z118*$G118)} -> 4780 | J122: =SUM(L122:Z122) -> 4780 | L122: =ROUND($G118*L118,0) -> 0 | M122: =ROUND($G118*M118,0) -> 0 | N122: =ROUND($G118*N118,0) -> 0 | O122: =ROUND($G118*O118,0) -> 0 | P122: =ROUND($G118*P118,0) -> 0 | Q122: =ROUND($G118*Q118,0) -> 4780 | R122: =ROUND($G118*R118,0) -> 0 | S122: =ROUND($G118*S118,0) -> 0 | ... Z122: =ROUND($G118*Z118,0) -> 0
C123: 2 BR | E123: Area SQM | G123: {=SUM($L119:$Z119*$G119)} -> 3649.71 | J123: =SUM(L123:Z123) -> 3650 | L123: =ROUND($G119*L119,0) -> 0 | M123: =ROUND($G119*M119,0) -> 0 | N123: =ROUND($G119*N119,0) -> 0 | O123: =ROUND($G119*O119,0) -> 0 | P123: =ROUND($G119*P119,0) -> 0 | Q123: =ROUND($G119*Q119,0) -> 3650 | R123: =ROUND($G119*R119,0) -> 0 | S123: =ROUND($G119*S119,0) -> 0 | ... Z123: =ROUND($G119*Z119,0) -> 0
C124: Total Area | E124: Area SQM | G124: =SUM(G122:G123) -> 8429.71 | J124: =SUM(J122:J123) -> 8430 | L124: =SUM(L122:L123) -> 0 | M124: =SUM(M122:M123) -> 0 | N124: =SUM(N122:N123) -> 0 | O124: =SUM(O122:O123) -> 0 | P124: =SUM(P122:P123) -> 0 | Q124: =SUM(Q122:Q123) -> 8430 | R124: =SUM(R122:R123) -> 0 | S124: =SUM(S122:S123) -> 0 | ... Z124: =SUM(Z122:Z123) -> 0
...

Sheet Costs
B1: MAAD RESIDENTIAL WITH HOTEL - OPERATING COSTS
B2: All figures in SAR'000
B3: Hospitality + retail OpEx build with NOP / NOI methodology and accounts-payable working capital adjustment.
B4: DESCRIPTION | D4: Phase | F4: uom / basis | G4: Rate | H4: Total | J4: =Revenue!L4 -> 2025 | K4: =J4+1 -> 2026 | L4: =K4+1 -> 2027 | M4: =L4+1 -> 2028 | N4: =M4+1 -> 2029 | O4: =N4+1 -> 2030 | P4: =O4+1 -> 2031 | Q4: =P4+1 -> 2032 | R4: =Q4+1 -> 2033 | ... X4: =W4+1 -> 2039
B6: Revenue (linked from Revenue sheet)
B7: VOCO Hotel | D7: 1
C8: Rooms revenue | H8: =SUM(J8:X8) -> 4770729.1 | J8: =Revenue!L316 -> 0 | K8: =Revenue!M316 -> 265571.24 | L8: =Revenue!N316 -> 275698.24 | M8: =Revenue!O316 -> 285825.24 | N8: =Revenue!P316 -> 297018.24 | O8: =Revenue!Q316 -> 309646.24 | P8: =Revenue!R316 -> 328470.82 | Q8: =Revenue!S316 -> 338324.95 | ... X8: =Revenue!Z316 -> 416097.01
C9: F&B revenue | H9: =SUM(J9:X9) -> 872604.83 | J9: =Revenue!L317 -> 0 | K9: =Revenue!M317 -> 48580.106 | L9: =Revenue!N317 -> 50432.606 | M9: =Revenue!O317 -> 52285.106 | N9: =Revenue!P317 -> 54332.606 | O9: =Revenue!Q317 -> 56642.606 | P9: =Revenue!R317 -> 60077.313 | Q9: =Revenue!S317 -> 61879.632 | ... X9: =Revenue!Z317 -> 76104.143
C10: Other Revenue | H10: =SUM(J10:X10) -> 170994.88 | J10: =Revenue!L318 -> 0 | K10: =Revenue!M318 -> 9716.021 | L10: =Revenue!N318 -> 10086.521 | M10: =Revenue!O318 -> 10457.021 | N10: =Revenue!P318 -> 10866.521 | O10: =Revenue!Q318 -> 11328.521 | P10: =Revenue!R318 -> 11668.377 | Q10: =Revenue!S318 -> 12018.428 | ... X10: =Revenue!Z318 -> 14781.15
B11: Total VOCO Revenue | H11: =SUM(J11:X11) -> 5814328.9 | J11: =SUM(J8:J10) -> 0 | K11: =SUM(K8:K10) -> 323867.37 | L11: =SUM(L8:L10) -> 336217.37 | M11: =SUM(M8:M10) -> 348567.37 | N11: =SUM(N8:N10) -> 362217.37 | O11: =SUM(O8:O10) -> 377617.37 | P11: =SUM(P8:P10) -> 400216.51 | Q11: =SUM(Q8:Q10) -> 412223.01 | ... X11: =SUM(X8:X10) -> 506982.3
B12: Residential Tower 01 (Hotel) | D12: 2
C13: Units (Rooms) revenue | H13: =SUM(J13:X13) -> 924446.76 | J13: =Revenue!L265 -> 0 | K13: =Revenue!M265 -> 0 | L13: =Revenue!N265 -> 0 | M13: =Revenue!O265 -> 0 | N13: =Revenue!P265 -> 46375.6 | O13: =Revenue!Q265 -> 55088.797 | P13: =Revenue!R265 -> 72542.88 | Q13: =Revenue!S265 -> 84567.544 | ... X13: =Revenue!Z265 -> 103723.24
C14: F&B revenue | H14: =SUM(J14:X14) -> 73955.741 | J14: =Revenue!L266 -> 0 | K14: =Revenue!M266 -> 0 | L14: =Revenue!N266 -> 0 | M14: =Revenue!O266 -> 0 | N14: =Revenue!P266 -> 3710.048 | O14: =Revenue!Q266 -> 4407.1037 | P14: =Revenue!R266 -> 5803.4304 | Q14: =Revenue!S266 -> 6765.4035 | ... X14: =Revenue!Z266 -> 8297.8591
B15: Total Tower 01 Revenue | H15: =SUM(J15:X15) -> 998402.5 | J15: =SUM(J13:J14) -> 0 | K15: =SUM(K13:K14) -> 0 | L15: =SUM(L13:L14) -> 0 | M15: =SUM(M13:M14) -> 0 | N15: =SUM(N13:N14) -> 50085.648 | O15: =SUM(O13:O14) -> 59495.9 | P15: =SUM(P13:P14) -> 78346.31 | Q15: =SUM(Q13:Q14) -> 91332.947 | ... X15: =SUM(X13:X14) -> 112021.1
B16: Hotel 01 - 336 Keys | D16: 2
C17: Units (Rooms) revenue | H17: =SUM(J17:X17) -> 746343.36 | J17: =Revenue!L296 -> 0 | K17: =Revenue!M296 -> 0 | L17: =Revenue!N296 -> 0 | M17: =Revenue!O296 -> 0 | N17: =Revenue!P296 -> 46585.935 | O17: =Revenue!Q296 -> 52553.372 | P17: =Revenue!R296 -> 59425.296 | Q17: =Revenue!S296 -> 66237.194 | ... X17: =Revenue!Z296 -> 81240.816
C18: F&B revenue | H18: =SUM(J18:X18) -> 223903.01 | J18: =Revenue!L297 -> 0 | K18: =Revenue!M297 -> 0 | L18: =Revenue!N297 -> 0 | M18: =Revenue!O297 -> 0 | N18: =Revenue!P297 -> 13975.781 | O18: =Revenue!Q297 -> 15766.011 | P18: =Revenue!R297 -> 17827.589 | Q18: =Revenue!S297 -> 19871.158 | ... X18: =Revenue!Z297 -> 24372.245
B19: Total Hotel 01 Revenue | H19: =SUM(J19:X19) -> 970246.36 | J19: =SUM(J17:J18) -> 0 | K19: =SUM(K17:K18) -> 0 | L19: =SUM(L17:L18) -> 0 | M19: =SUM(M17:M18) -> 0 | N19: =SUM(N17:N18) -> 60561.716 | O19: =SUM(O17:O18) -> 68319.383 | P19: =SUM(P17:P18) -> 77252.885 | Q19: =SUM(Q17:Q18) -> 86108.352 | ... X19: =SUM(X17:X18) -> 105613.06
C20: Support Retail (Phase 2) | D20: 2 | H20: =SUM(J20:X20) -> 220121.29 | J20: =Revenue!L324 -> 0 | K20: =Revenue!M324 -> 0 | L20: =Revenue!N324 -> 0 | M20: =Revenue!O324 -> 0 | N20: =Revenue!P324 -> 9598.2878 | O20: =Revenue!Q324 -> 13117.66 | P20: =Revenue!R324 -> 16807.002 | Q20: =Revenue!S324 -> 20672.612 | ... X20: =Revenue!Z324 -> 24573.24
C21: Support Retail (Phase 3) | D21: 3 | H21: =SUM(J21:X21) -> 115889.21 | J21: =Revenue!L325 -> 0 | K21: =Revenue!M325 -> 0 | L21: =Revenue!N325 -> 0 | M21: =Revenue!O325 -> 0 | N21: =Revenue!P325 -> 5053.296 | O21: =Revenue!Q325 -> 6906.1712 | P21: =Revenue!R325 -> 8848.5318 | Q21: =Revenue!S325 -> 10883.694 | ... X21: =Revenue!Z325 -> 12937.292
B22: Total Revenue (operated) | H22: =SUM(J22:X22) -> 8118988.2 | J22: =J11+J15+J19+J20+J21 -> 0 | K22: =K11+K15+K19+K20+K21 -> 323867.37 | L22: =L11+L15+L19+L20+L21 -> 336217.37 | M22: =M11+M15+M19+M20+M21 -> 348567.37 | N22: =N11+N15+N19+N20+N21 -> 487516.32 | O22: =O11+O15+O19+O20+O21 -> 525456.48 | P22: =P11+P15+P19+P20+P21 -> 581471.24 | Q22: =Q11+Q15+Q19+Q20+Q21 -> 621220.61 | ... X22: =X11+X15+X19+X20+X21 -> 762126.99
B24: Operating Costs
C26: VOCO Hotel - Operating Expenses | F26: % basis | G26: Rate | H26: Total
C27: NOP % (source: Phase 1 Projected Revenues) | F27: % of Rev | G27: =AVERAGE(J27:X27) -> 0.49174251 | J27: 0 | K27: 0.51804496 | L27: 0.51803861 | M27: 0.50315324 | N27: 0.51733738 | O27: 0.5315634 | P27: 0.532 | Q27: 0.532 | R27: 0.532 | S27: 0.532 | T27: 0.532 | U27: 0.532 | V27: 0.532 | W27: 0.532 | X27: 0.532
C28: Operating Cost = -NOP% × Total VOCO Revenue | H28: =SUM(J28:X28) -> -3068478.3 | J28: =-J27*J11 -> 0 | K28: =-K27*K11 -> -167777.86 | L28: =-L27*L11 -> -174173.58 | M28: =-M27*M11 -> -175382.8 | N28: =-N27*N11 -> -187388.59 | O28: =-O27*O11 -> -200727.57 | P28: =-P27*P11 -> -212915.18 | Q28: =-Q27*Q11 -> -219302.64 | ... X28: =-X27*X11 -> -269714.58
C29: Total VOCO Operating Costs | H29: =SUM(J29:X29) -> -3068478.3 | J29: =J28 -> 0 | K29: =K28 -> -167777.86 | L29: =L28 -> -174173.58 | M29: =M28 -> -175382.8 | N29: =N28 -> -187388.59 | O29: =O28 -> -200727.57 | P29: =P28 -> -212915.18 | Q29: =Q28 -> -219302.64 | ... X29: =X28 -> -269714.58
C31: Residential Tower 01 - Operating Expenses | F31: % basis | G31: Rate | H31: Total
C32: Departmental Expenses
C33: Units (Rooms) expense | F33: % Units rev | G33: 0 | H33: =SUM(J33:X33) -> 0 | J33: =-$G$33*J13 -> 0 | K33: =-$G$33*K13 -> 0 | L33: =-$G$33*L13 -> 0 | M33: =-$G$33*M13 -> 0 | N33: =-$G$33*N13 -> 0 | O33: =-$G$33*O13 -> 0 | P33: =-$G$33*P13 -> 0 | Q33: =-$G$33*Q13 -> 0 | ... X33: =-$G$33*X13 -> 0
C34: F&B expense | F34: % F&B rev | G34: 0.67 | H34: =SUM(J34:X34) -> -49550.346 | J34: =-$G$34*J14 -> 0 | K34: =-$G$34*K14 -> 0 | L34: =-$G$34*L14 -> 0 | M34: =-$G$34*M14 -> 0 | N34: =-$G$34*N14 -> -2485.7322 | O34: =-$G$34*O14 -> -2952.7595 | P34: =-$G$34*P14 -> -3888.2984 | Q34: =-$G$34*Q14 -> -4532.8203 | ... X34: =-$G$34*X14 -> -5559.5656
C35: Undistributed Expenses
C36: G&A | F36: % Units rev | G36: 0.75 | H36: =SUM(J36:X36) -> -693335.07 | J36: =-$G$36*J13 -> 0 | K36: =-$G$36*K13 -> 0 | L36: =-$G$36*L13 -> 0 | M36: =-$G$36*M13 -> 0 | N36: =-$G$36*N13 -> -34781.7 | O36: =-$G$36*O13 -> -41316.598 | P36: =-$G$36*P13 -> -54407.16 | Q36: =-$G$36*Q13 -> -63425.658 | ... X36: =-$G$36*X13 -> -77792.429
C37: Total Tower 01 OpEx | H37: =SUM(J37:X37) -> -742885.42 | J37: =SUM(J33:J34)+J36 -> 0 | K37: =SUM(K33:K34)+K36 -> 0 | L37: =SUM(L33:L34)+L36 -> 0 | M37: =SUM(M33:M34)+M36 -> 0 | N37: =SUM(N33:N34)+N36 -> -37267.432 | O37: =SUM(O33:O34)+O36 -> -44269.357 | P37: =SUM(P33:P34)+P36 -> -58295.458 | Q37: =SUM(Q33:Q34)+Q36 -> -67958.478 | ... X37: =SUM(X33:X34)+X36 -> -83351.995
C39: Hotel 01 (336 Keys) - Operating Expenses | F39: % basis | G39: Rate
C40: Departmental Expenses
C41: Units (Rooms) expense | F41: % Units rev | G41: 0.14 | H41: =SUM(J41:X41) -> -104488.07 | J41: =-$G$41*J17 -> 0 | K41: =-$G$41*K17 -> 0 | L41: =-$G$41*L17 -> 0 | M41: =-$G$41*M17 -> 0 | N41: =-$G$41*N17 -> -6522.0309 | O41: =-$G$41*O17 -> -7357.472 | P41: =-$G$41*P17 -> -8319.5415 | Q41: =-$G$41*Q17 -> -9273.2071 | ... X41: =-$G$41*X17 -> -11373.714
C42: F&B expense | F42: % F&B rev | G42: 0.65 | H42: =SUM(J42:X42) -> -145536.95 | J42: =-$G$42*J18 -> 0 | K42: =-$G$42*K18 -> 0 | L42: =-$G$42*L18 -> 0 | M42: =-$G$42*M18 -> 0 | N42: =-$G$42*N18 -> -9084.2574 | O42: =-$G$42*O18 -> -10247.907 | P42: =-$G$42*P18 -> -11587.933 | Q42: =-$G$42*Q18 -> -12916.253 | ... X42: =-$G$42*X18 -> -15841.959
C43: Undistributed Expenses
C44: G&A | F44: % total rev | G44: 0.09 | H44: =SUM(J44:X44) -> -87322.173 | J44: =-$G$44*J19 -> 0 | K44: =-$G$44*K19 -> 0 | L44: =-$G$44*L19 -> 0 | M44: =-$G$44*M19 -> 0 | N44: =-$G$44*N19 -> -5450.5544 | O44: =-$G$44*O19 -> -6148.7445 | P44: =-$G$44*P19 -> -6952.7597 | Q44: =-$G$44*Q19 -> -7749.7517 | ... X44: =-$G$44*X19 -> -9505.1755
C45: Sales & Marketing | F45: % total rev | G45: 0.05 | H45: =SUM(J45:X45) -> -48512.318 | J45: =-$G$45*J19 -> 0 | K45: =-$G$45*K19 -> 0 | L45: =-$G$45*L19 -> 0 | M45: =-$G$45*M19 -> 0 | N45: =-$G$45*N19 -> -3028.0858 | O45: =-$G$45*O19 -> -3415.9692 | P45: =-$G$45*P19 -> -3862.6443 | Q45: =-$G$45*Q19 -> -4305.4176 | ... X45: =-$G$45*X19 -> -5280.653
C46: Operations & Maintenance | F46: % total rev | G46: 0.1 | H46: =SUM(J46:X46) -> -97024.636 | J46: =-$G$46*J19 -> 0 | K46: =-$G$46*K19 -> 0 | L46: =-$G$46*L19 -> 0 | M46: =-$G$46*M19 -> 0 | N46: =-$G$46*N19 -> -6056.1716 | O46: =-$G$46*O19 -> -6831.9383 | P46: =-$G$46*P19 -> -7725.2885 | Q46: =-$G$46*Q19 -> -8610.8352 | ... X46: =-$G$46*X19 -> -10561.306
C47: Utilities | F47: % total rev | G47: 0.1 | H47: =SUM(J47:X47) -> -97024.636 | J47: =-$G$47*J19 -> 0 | K47: =-$G$47*K19 -> 0 | L47: =-$G$47*L19 -> 0 | M47: =-$G$47*M19 -> 0 | N47: =-$G$47*N19 -> -6056.1716 | O47: =-$G$47*O19 -> -6831.9383 | P47: =-$G$47*P19 -> -7725.2885 | Q47: =-$G$47*Q19 -> -8610.8352 | ... X47: =-$G$47*X19 -> -10561.306
C48: Total Hotel 01 OpEx | H48: =SUM(J48:X48) -> -579908.79 | J48: =SUM(J41:J42)+SUM(J44:J47) -> 0 | K48: =SUM(K41:K42)+SUM(K44:K47) -> 0 | L48: =SUM(L41:L42)+SUM(L44:L47) -> 0 | M48: =SUM(M41:M42)+SUM(M44:M47) -> 0 | N48: =SUM(N41:N42)+SUM(N44:N47) -> -36197.272 | O48: =SUM(O41:O42)+SUM(O44:O47) -> -40833.97 | P48: =SUM(P41:P42)+SUM(P44:P47) -> -46173.455 | Q48: =SUM(Q41:Q42)+SUM(Q44:Q47) -> -51466.3 | ... X48: =SUM(X41:X42)+SUM(X44:X47) -> -63124.114
C50: Support Retail - Operating Expenses | F50: % basis | G50: Rate
C51: Retail Phase 2 - OpEx | F51: % Ph2 rev | G51: 0.12 | H51: =SUM(J51:X51) -> -26414.554 | J51: =-$G$51*J20 -> 0 | K51: =-$G$51*K20 -> 0 | L51: =-$G$51*L20 -> 0 | M51: =-$G$51*M20 -> 0 | N51: =-$G$51*N20 -> -1151.7945 | O51: =-$G$51*O20 -> -1574.1192 | P51: =-$G$51*P20 -> -2016.8402 | Q51: =-$G$51*Q20 -> -2480.7135 | ... X51: =-$G$51*X20 -> -2948.7888
C52: Retail Phase 3 - OpEx | F52: % Ph3 rev | G52: 0.12 | H52: =SUM(J52:X52) -> -13906.705 | J52: =-$G$52*J21 -> 0 | K52: =-$G$52*K21 -> 0 | L52: =-$G$52*L21 -> 0 | M52: =-$G$52*M21 -> 0 | N52: =-$G$52*N21 -> -606.39552 | O52: =-$G$52*O21 -> -828.74054 | P52: =-$G$52*P21 -> -1061.8238 | Q52: =-$G$52*Q21 -> -1306.0433 | ... X52: =-$G$52*X21 -> -1552.4751
C53: Total Retail OpEx | H53: =SUM(J53:X53) -> -40321.26 | J53: =J51+J52 -> 0 | K53: =K51+K52 -> 0 | L53: =L51+L52 -> 0 | M53: =M51+M52 -> 0 | N53: =N51+N52 -> -1758.1901 | O53: =O51+O52 -> -2402.8597 | P53: =P51+P52 -> -3078.664 | Q53: =Q51+Q52 -> -3786.7568 | ... X53: =X51+X52 -> -4501.2638
B55: Asset Wise - Operating Cost Summary
C56: VOCO Hotel (Phase 1) | H56: =SUM(J56:X56) -> -3068478.3 | J56: =J29 -> 0 | K56: =K29 -> -167777.86 | L56: =L29 -> -174173.58 | M56: =M29 -> -175382.8 | N56: =N29 -> -187388.59 | O56: =O29 -> -200727.57 | P56: =P29 -> -212915.18 | Q56: =Q29 -> -219302.64 | ... X56: =X29 -> -269714.58
C57: Residential Tower 01 (Phase 2) | H57: =SUM(J57:X57) -> -742885.42 | J57: =J37 -> 0 | K57: =K37 -> 0 | L57: =L37 -> 0 | M57: =M37 -> 0 | N57: =N37 -> -37267.432 | O57: =O37 -> -44269.357 | P57: =P37 -> -58295.458 | Q57: =Q37 -> -67958.478 | ... X57: =X37 -> -83351.995
C58: Hotel 01 - 336 Keys (Phase 2) | H58: =SUM(J58:X58) -> -579908.79 | J58: =J48 -> 0 | K58: =K48 -> 0 | L58: =L48 -> 0 | M58: =M48 -> 0 | N58: =N48 -> -36197.272 | O58: =O48 -> -40833.97 | P58: =P48 -> -46173.455 | Q58: =Q48 -> -51466.3 | ... X58: =X48 -> -63124.114
C59: Retail operating expenses
C60: Support Retail (Phase 2) | H60: =SUM(J60:X60) -> -26414.554 | J60: =J51 -> 0 | K60: =K51 -> 0 | L60: =L51 -> 0 | M60: =M51 -> 0 | N60: =N51 -> -1151.7945 | O60: =O51 -> -1574.1192 | P60: =P51 -> -2016.8402 | Q60: =Q51 -> -2480.7135 | ... X60: =X51 -> -2948.7888
C61: Support Retail (Phase 3) | H61: =SUM(J61:X61) -> -13906.705 | J61: =J52 -> 0 | K61: =K52 -> 0 | L61: =L52 -> 0 | M61: =M52 -> 0 | N61: =N52 -> -606.39552 | O61: =O52 -> -828.74054 | P61: =P52 -> -1061.8238 | Q61: =Q52 -> -1306.0433 | ... X61: =X52 -> -1552.4751
B62: TOTAL OPERATING COSTS | H62: =SUM(J62:X62) -> -4431593.8 | J62: =J29+J37+J48+J53 -> 0 | K62: =K29+K37+K48+K53 -> -167777.86 | L62: =L29+L37+L48+L53 -> -174173.58 | M62: =M29+M37+M48+M53 -> -175382.8 | N62: =N29+N37+N48+N53 -> -262611.48 | O62: =O29+O37+O48+O53 -> -288233.76 | P62: =P29+P37+P48+P53 -> -320462.76 | Q62: =Q29+Q37+Q48+Q53 -> -342514.17 | ... X62: =X29+X37+X48+X53 -> -420691.96
B63: Operating margin (cross-check) | J63: =IFERROR(1+J62/J22,0) -> 0 | K63: =IFERROR(1+K62/K22,0) -> 0.48195504 | L63: =IFERROR(1+L62/L22,0) -> 0.48196139 | M63: =IFERROR(1+M62/M22,0) -> 0.49684676 | N63: =IFERROR(1+N62/N22,0) -> 0.46132781 | O63: =IFERROR(1+O62/O22,0) -> 0.45146027 | P63: =IFERROR(1+P62/P22,0) -> 0.44887599 | Q63: =IFERROR(1+Q62/Q22,0) -> 0.44864326 | ... X63: =IFERROR(1+X62/X22,0) -> 0.44800281
B65: VARIANCE vs MAIN MODEL (Consol_Financial Statements)
C67: TOTAL OPERATING COSTS (source row 55)
C68: Source MAAD (hardcoded) | H68: =SUM(J68:X68) -> -4431594.3 | J68: 0 | K68: -167777.86 | L68: -174173.58 | M68: -175382.8 | N68: -262611.48 | O68: -288233.76 | P68: -320462.87 | Q68: -342514.21 | R68: -352434.62 | S68: -362988.25 | T68: -373858.01 | U68: -385420.61 | V68: -396584.06 | W68: -408460.16 | X68: -420692
C69: Our model | H69: =SUM(J69:X69) -> -4431593.8 | J69: =J62 -> 0 | K69: =K62 -> -167777.86 | L69: =L62 -> -174173.58 | M69: =M62 -> -175382.8 | N69: =N62 -> -262611.48 | O69: =O62 -> -288233.76 | P69: =P62 -> -320462.76 | Q69: =Q62 -> -342514.17 | ... X69: =X62 -> -420691.96
C70: Variance (Our − Source) | H70: =SUM(J70:X70) -> 0.46197091 | J70: =J69-J68 -> 0 | K70: =K69-K68 -> 0 | L70: =L69-L68 -> 0 | M70: =M69-M68 -> 0 | N70: =N69-N68 -> 0 | O70: =O69-O68 -> 0 | P70: =P69-P68 -> 0.10892518 | Q70: =Q69-Q68 -> 0.036487737 | ... X70: =X69-X68 -> 0.043227765
C72: BY ASSET (source rows)
C73: Source Hospitality (row 46) | H73: =SUM(J73:X73) -> -4391272.6 | J73: 0 | K73: -167777.86 | L73: -174173.58 | M73: -175382.8 | N73: -260853.51 | O73: -285830.71 | P73: -317384.1 | Q73: -338727.42 | R73: -348553.15 | S73: -359009.75 | T73: -369780.04 | U73: -381240.69 | V73: -392299.64 | W73: -404068.63 | X73: -416190.69
C74: Our Hospitality (VOCO+T01+H01) | H74: =SUM(J74:X74) -> -4391272.5 | J74: =J29+J37+J48 -> 0 | K74: =K29+K37+K48 -> -167777.86 | L74: =L29+L37+L48 -> -174173.58 | M74: =M29+M37+M48 -> -175382.8 | N74: =N29+N37+N48 -> -260853.29 | O74: =O29+O37+O48 -> -285830.9 | P74: =P29+P37+P48 -> -317384.1 | Q74: =Q29+Q37+Q48 -> -338727.42 | ... X74: =X29+X37+X48 -> -416190.69
C75: Variance Hospitality | H75: =SUM(J75:X75) -> 0.021778246 | J75: =J74-J73 -> 0 | K75: =K74-K73 -> 0 | L75: =L74-L73 -> 0 | M75: =M74-M73 -> 0 | N75: =N74-N73 -> 0.22005058 | O75: =O74-O73 -> -0.19026421 | P75: =P74-P73 -> 0.0029616562 | Q75: =Q74-Q73 -> 0.0032526041 | ... X75: =X74-X73 -> -0.0029532302
C77: Source Retail (row 44) | H77: =SUM(J77:X77) -> -40321.69 | J77: 0 | K77: 0 | L77: 0 | M77: 0 | N77: -1757.98 | O77: -2403.04 | P77: -3078.78 | Q77: -3786.8 | R77: -3881.47 | S77: -3978.5 | T77: -4077.97 | U77: -4179.91 | V77: -4284.41 | W77: -4391.52 | X77: -4501.31
C78: Our Retail (Ph2+Ph3) | H78: =SUM(J78:X78) -> -40321.26 | J78: =J53 -> 0 | K78: =K53 -> 0 | L78: =L53 -> 0 | M78: =M53 -> 0 | N78: =N53 -> -1758.1901 | O78: =O53 -> -2402.8597 | P78: =P53 -> -3078.664 | Q78: =Q53 -> -3786.7568 | ... X78: =X53 -> -4501.2638
C79: Variance Retail | H79: =SUM(J79:X79) -> 0.43019266 | J79: =J78-J77 -> 0 | K79: =K78-K77 -> 0 | L79: =L78-L77 -> 0 | M79: =M78-M77 -> 0 | N79: =N78-N77 -> -0.21005058 | O79: =O78-O77 -> 0.18026421 | P79: =P78-P77 -> 0.11596352 | Q79: =Q78-Q77 -> 0.043235132 | ... X79: =X78-X77 -> 0.046180995
B81: OPERATING COSTS - CASH FLOW (Working Capital Adjusted)
C83: Inputs
C84: Payable days | H84: 30
C85: Days per year | H85: 365
C86: Exit period (1 = exit year) | J86: =IF(J4=$H$86,1,0) -> 0 | K86: =IF(K4=$H$86,1,0) -> 0 | L86: =IF(L4=$H$86,1,0) -> 0 | M86: =IF(M4=$H$86,1,0) -> 0 | N86: =IF(N4=$H$86,1,0) -> 0 | O86: =IF(O4=$H$86,1,0) -> 0 | P86: =IF(P4=$H$86,1,0) -> 0 | Q86: =IF(Q4=$H$86,1,0) -> 0 | ... X86: =IF(X4=$H$86,1,0) -> 0
C87: Accounts Payable Schedule
C88: Accrued Operating Expense
C89: Hospitality
C90: VOCO Hotel (Phase 1) | J90: =-IF($H$85=0,0,J56/$H$85*$H$84) -> 0 | K90: =-IF($H$85=0,0,K56/$H$85*$H$84) -> 13789.961 | L90: =-IF($H$85=0,0,L56/$H$85*$H$84) -> 14315.637 | M90: =-IF($H$85=0,0,M56/$H$85*$H$84) -> 14415.025 | N90: =-IF($H$85=0,0,N56/$H$85*$H$84) -> 15401.802 | O90: =-IF($H$85=0,0,O56/$H$85*$H$84) -> 16498.157 | P90: =-IF($H$85=0,0,P56/$H$85*$H$84) -> 17499.878 | Q90: =-IF($H$85=0,0,Q56/$H$85*$H$84) -> 18024.874 | ... X90: =-IF($H$85=0,0,X56/$H$85*$H$84) -> 22168.322
C91: Residential Tower 01 (Phase 2) | J91: =-IF($H$85=0,0,J57/$H$85*$H$84) -> 0 | K91: =-IF($H$85=0,0,K57/$H$85*$H$84) -> 0 | L91: =-IF($H$85=0,0,L57/$H$85*$H$84) -> 0 | M91: =-IF($H$85=0,0,M57/$H$85*$H$84) -> 0 | N91: =-IF($H$85=0,0,N57/$H$85*$H$84) -> 3063.0766 | O91: =-IF($H$85=0,0,O57/$H$85*$H$84) -> 3638.5773 | P91: =-IF($H$85=0,0,P57/$H$85*$H$84) -> 4791.4075 | Q91: =-IF($H$85=0,0,Q57/$H$85*$H$84) -> 5585.6283 | ... X91: =-IF($H$85=0,0,X57/$H$85*$H$84) -> 6850.8489
C92: Hotel 01 - 336 Keys (Phase 2) | J92: =-IF($H$85=0,0,J58/$H$85*$H$84) -> 0 | K92: =-IF($H$85=0,0,K58/$H$85*$H$84) -> 0 | L92: =-IF($H$85=0,0,L58/$H$85*$H$84) -> 0 | M92: =-IF($H$85=0,0,M58/$H$85*$H$84) -> 0 | N92: =-IF($H$85=0,0,N58/$H$85*$H$84) -> 2975.1182 | O92: =-IF($H$85=0,0,O58/$H$85*$H$84) -> 3356.2167 | P92: =-IF($H$85=0,0,P58/$H$85*$H$84) -> 3795.0785 | Q92: =-IF($H$85=0,0,Q58/$H$85*$H$84) -> 4230.1068 | ... X92: =-IF($H$85=0,0,X58/$H$85*$H$84) -> 5188.2833
C93: Retail
C94: Support Retail (Phase 2) | J94: =-IF($H$85=0,0,J60/$H$85*$H$84) -> 0 | K94: =-IF($H$85=0,0,K60/$H$85*$H$84) -> 0 | L94: =-IF($H$85=0,0,L60/$H$85*$H$84) -> 0 | M94: =-IF($H$85=0,0,M60/$H$85*$H$84) -> 0 | N94: =-IF($H$85=0,0,N60/$H$85*$H$84) -> 94.668044 | O94: =-IF($H$85=0,0,O60/$H$85*$H$84) -> 129.37966 | P94: =-IF($H$85=0,0,P60/$H$85*$H$84) -> 165.76769 | Q94: =-IF($H$85=0,0,Q60/$H$85*$H$84) -> 203.89426 | ... X94: =-IF($H$85=0,0,X60/$H$85*$H$84) -> 242.3662
C95: Support Retail (Phase 3) | J95: =-IF($H$85=0,0,J61/$H$85*$H$84) -> 0 | K95: =-IF($H$85=0,0,K61/$H$85*$H$84) -> 0 | L95: =-IF($H$85=0,0,L61/$H$85*$H$84) -> 0 | M95: =-IF($H$85=0,0,M61/$H$85*$H$84) -> 0 | N95: =-IF($H$85=0,0,N61/$H$85*$H$84) -> 49.840727 | O95: =-IF($H$85=0,0,O61/$H$85*$H$84) -> 68.115661 | P95: =-IF($H$85=0,0,P61/$H$85*$H$84) -> 87.27319 | Q95: =-IF($H$85=0,0,Q61/$H$85*$H$84) -> 107.34602 | ... X95: =-IF($H$85=0,0,X61/$H$85*$H$84) -> 127.60069
C96: Total Payable | H96: =X96 -> 34577.421 | J96: =SUM(J90:J95) -> 0 | K96: =SUM(K90:K95) -> 13789.961 | L96: =SUM(L90:L95) -> 14315.637 | M96: =SUM(M90:M95) -> 14415.025 | N96: =SUM(N90:N95) -> 21584.505 | O96: =SUM(O90:O95) -> 23690.446 | P96: =SUM(P90:P95) -> 26339.405 | Q96: =SUM(Q90:Q95) -> 28151.85 | ... X96: =SUM(X90:X95) -> 34577.421
C98: Operating Cost Paid (Cash)
C99: Hospitality
C100: VOCO Hotel (Phase 1) | J100: =J56+J90 -> 0 | K100: =K56+K90-J90 -> -153987.9 | L100: =L56+L90-K90 -> -173647.9 | M100: =M56+M90-L90 -> -175283.41 | N100: =N56+N90-M90 -> -186401.81 | O100: =O56+O90-N90 -> -199631.22 | P100: =P56+P90-O90 -> -211913.46 | Q100: =Q56+Q90-P90 -> -218777.64 | R100: =R56+R90-Q90 -> -225340.97 | ... X100: =X56+X90-W90 -> -269068.91
C101: Residential Tower 01 (Phase 2) | J101: =J57+J91 -> 0 | K101: =K57+K91-J91 -> 0 | L101: =L57+L91-K91 -> 0 | M101: =M57+M91-L91 -> 0 | N101: =N57+N91-M91 -> -34204.356 | O101: =O57+O91-N91 -> -43693.856 | P101: =P57+P91-O91 -> -57142.628 | Q101: =Q57+Q91-P91 -> -67164.257 | R101: =R57+R91-Q91 -> -69654.134 | ... X101: =X57+X91-W91 -> -83152.455
C102: Hotel 01 - 336 Keys (Phase 2) | J102: =J58+J92 -> 0 | K102: =K58+K92-J92 -> 0 | L102: =L58+L92-K92 -> 0 | M102: =M58+M92-L92 -> 0 | N102: =N58+N92-M92 -> -33222.153 | O102: =O58+O92-N92 -> -40452.871 | P102: =P58+P92-O92 -> -45734.593 | Q102: =Q58+Q92-P92 -> -51031.271 | R102: =R58+R92-Q92 -> -52750.453 | ... X102: =X58+X92-W92 -> -62972.999
C103: Retail
C104: Support Retail (Phase 2) | J104: =J60+J94 -> 0 | K104: =K60+K94-J94 -> 0 | L104: =L60+L94-K94 -> 0 | M104: =M60+M94-L94 -> 0 | N104: =N60+N94-M94 -> -1057.1265 | O104: =O60+O94-N94 -> -1539.4076 | P104: =P60+P94-O94 -> -1980.4522 | Q104: =Q60+Q94-P94 -> -2442.5869 | R104: =R60+R94-Q94 -> -2537.6339 | ... X104: =X60+X94-W94 -> -2942.8774
C105: Support Retail (Phase 3) | J105: =J61+J95 -> 0 | K105: =K61+K95-J95 -> 0 | L105: =L61+L95-K95 -> 0 | M105: =M61+M95-L95 -> 0 | N105: =N61+N95-M95 -> -556.55479 | O105: =O61+O95-N95 -> -810.46561 | P105: =P61+P95-O95 -> -1042.6663 | Q105: =Q61+Q95-P95 -> -1285.9705 | R105: =R61+R95-Q95 -> -1336.0107 | ... X105: =X61+X95-W95 -> -1549.3628
B106: Total Operating Cost Paid (Cash) | H106: =SUM(J106:X106) -> -4397016.4 | J106: =SUM(J100:J105) -> 0 | K106: =SUM(K100:K105) -> -153987.9 | L106: =SUM(L100:L105) -> -173647.9 | M106: =SUM(M100:M105) -> -175283.41 | N106: =SUM(N100:N105) -> -255442 | O106: =SUM(O100:O105) -> -286127.82 | P106: =SUM(P100:P105) -> -317813.8 | Q106: =SUM(Q100:Q105) -> -340701.73 | ... X106: =SUM(X100:X105) -> -419686.6
B108: VARIANCE vs MAIN MODEL (source Capex&WC row 169)
C109: Source MAAD (Cash Paid, hardcoded) | H109: =SUM(J109:X109) -> -3977330.2 | J109: 0 | K109: -153987.89 | L109: -173647.9 | M109: -175322.79 | N109: -255402.62 | O109: -286127.82 | P109: -317813.91 | Q109: -340778.69 | R109: -351542.33 | S109: -362120.83 | T109: -372964.6 | U109: -384556.81 | V109: -395579.96 | W109: -407484.04 | X109: 0
C110: Our model (row 99) | H110: =SUM(J110:X110) -> -4397016.4 | J110: =J106 -> 0 | K110: =K106 -> -153987.9 | L110: =L106 -> -173647.9 | M110: =M106 -> -175283.41 | N110: =N106 -> -255442 | O110: =O106 -> -286127.82 | P110: =P106 -> -317813.8 | Q110: =Q106 -> -340701.73 | ... X110: =X106 -> -419686.6
C111: Variance (Our - Source) | H111: =SUM(J111:X111) -> -419686.2 | J111: =J110-J109 -> 0 | K111: =K110-K109 -> -0.0089041097 | L111: =L110-L109 -> -0.0043835618 | M111: =M110-M109 -> 39.377945 | N111: =N110-N109 -> -39.379452 | O111: =O110-O109 -> 0.00082191773 | P111: =P110-P109 -> 0.10791763 | Q111: =Q110-Q109 -> 76.961346 | ... X111: =X110-X109 -> -419686.6
B113: COST OF SALES
B114: Each vintage year contains the cost of units pre-sold that year. Cost is released over the recognition profile starting at that vintage year (mirrors Revenue tab payment profile mechanism).
C116: Branded Apartments T2 & T3 | D116: 2
C117: Capex | D117: YES | H117: =SUM(J117:X117) -> 1876587.7 | J117: =IF($D117="Yes",Capex!L215,Capex!L88) -> 0 | K117: =IF($D117="Yes",Capex!M215,Capex!M88) -> 694341.78 | L117: =IF($D117="Yes",Capex!N215,Capex!N88) -> 328401.65 | M117: =IF($D117="Yes",Capex!O215,Capex!O88) -> 394081.98 | N117: =IF($D117="Yes",Capex!P215,Capex!P88) -> 328401.65 | O117: =IF($D117="Yes",Capex!Q215,Capex!Q88) -> 131360.66 | P117: =IF($D117="Yes",Capex!R215,Capex!R88) -> 0 | Q117: =IF($D117="Yes",Capex!S215,Capex!S88) -> 0 | ... X117: =IF($D117="Yes",Capex!Z215,Capex!Z88) -> 0
...

Sheet Capex
B1: MAAD RESIDENTIAL WITH HOTEL - CAPEX
B2: All figures in SAR'000
B3: Asset cost stack (5 assets, sub-units, land), depreciation schedule and variance vs main MAAD model.
B4: Capex Asset & Sub-Asset Cost Stack with Cash Flow Allocation | D4: Phase | G4: Driver | H4: Quantity / Base | I4: Rate | L4: Total | M4: 2026 | N4: 2027 | O4: 2028 | P4: 2029 | Q4: 2030 | R4: 2031 | S4: =R4+1 -> 2032 | T4: =S4+1 -> 2033 | U4: =T4+1 -> 2034 | V4: =U4+1 -> 2035 | W4: =V4+1 -> 2036 | X4: =W4+1 -> 2037 | Y4: =X4+1 -> 2038 | Z4: =Y4+1 -> 2039
B6: Cash Flow Allocation - by Year (% of category total)
C8: Branded Apartments T2 & T3 - Allocation %
C9: Land | K9: =SUM(L9:R9) -> 1 | M9: =CHOOSE(CF!$G$1,'Capex Allocation'!H9,'Capex Allocation'!H71) -> 1 | N9: =CHOOSE(CF!$G$1,'Capex Allocation'!I9,'Capex Allocation'!I71) -> 0 | O9: =CHOOSE(CF!$G$1,'Capex Allocation'!J9,'Capex Allocation'!J71) -> 0 | P9: =CHOOSE(CF!$G$1,'Capex Allocation'!K9,'Capex Allocation'!K71) -> 0 | Q9: =CHOOSE(CF!$G$1,'Capex Allocation'!L9,'Capex Allocation'!L71) -> 0 | R9: =CHOOSE(CF!$G$1,'Capex Allocation'!M9,'Capex Allocation'!M71) -> 0 | S9: =CHOOSE(CF!$G$1,'Capex Allocation'!N9,'Capex Allocation'!N71) -> 0 | T9: =CHOOSE(CF!$G$1,'Capex Allocation'!O9,'Capex Allocation'!O71) -> 0 | ... Z9: =CHOOSE(CF!$G$1,'Capex Allocation'!U9,'Capex Allocation'!U71) -> 0
C10: Construction (BUA + Parking) | K10: =SUM(L10:R10) -> 1 | M10: =CHOOSE(CF!$G$1,'Capex Allocation'!H10,'Capex Allocation'!H72) -> 0.1 | N10: =CHOOSE(CF!$G$1,'Capex Allocation'!I10,'Capex Allocation'!I72) -> 0.25 | O10: =CHOOSE(CF!$G$1,'Capex Allocation'!J10,'Capex Allocation'!J72) -> 0.3 | P10: =CHOOSE(CF!$G$1,'Capex Allocation'!K10,'Capex Allocation'!K72) -> 0.25 | Q10: =CHOOSE(CF!$G$1,'Capex Allocation'!L10,'Capex Allocation'!L72) -> 0.1 | R10: =CHOOSE(CF!$G$1,'Capex Allocation'!M10,'Capex Allocation'!M72) -> 0 | S10: =CHOOSE(CF!$G$1,'Capex Allocation'!N10,'Capex Allocation'!N72) -> 0 | T10: =CHOOSE(CF!$G$1,'Capex Allocation'!O10,'Capex Allocation'!O72) -> 0 | ... Z10: =CHOOSE(CF!$G$1,'Capex Allocation'!U10,'Capex Allocation'!U72) -> 0
C11: Infrastructure | K11: =SUM(L11:R11) -> 1 | M11: =CHOOSE(CF!$G$1,'Capex Allocation'!H11,'Capex Allocation'!H73) -> 0.1 | N11: =CHOOSE(CF!$G$1,'Capex Allocation'!I11,'Capex Allocation'!I73) -> 0.25 | O11: =CHOOSE(CF!$G$1,'Capex Allocation'!J11,'Capex Allocation'!J73) -> 0.3 | P11: =CHOOSE(CF!$G$1,'Capex Allocation'!K11,'Capex Allocation'!K73) -> 0.25 | Q11: =CHOOSE(CF!$G$1,'Capex Allocation'!L11,'Capex Allocation'!L73) -> 0.1 | R11: =CHOOSE(CF!$G$1,'Capex Allocation'!M11,'Capex Allocation'!M73) -> 0 | S11: =CHOOSE(CF!$G$1,'Capex Allocation'!N11,'Capex Allocation'!N73) -> 0 | T11: =CHOOSE(CF!$G$1,'Capex Allocation'!O11,'Capex Allocation'!O73) -> 0 | ... Z11: =CHOOSE(CF!$G$1,'Capex Allocation'!U11,'Capex Allocation'!U73) -> 0
C12: Landscaping | K12: =SUM(L12:R12) -> 1 | M12: =CHOOSE(CF!$G$1,'Capex Allocation'!H12,'Capex Allocation'!H74) -> 0.1 | N12: =CHOOSE(CF!$G$1,'Capex Allocation'!I12,'Capex Allocation'!I74) -> 0.25 | O12: =CHOOSE(CF!$G$1,'Capex Allocation'!J12,'Capex Allocation'!J74) -> 0.3 | P12: =CHOOSE(CF!$G$1,'Capex Allocation'!K12,'Capex Allocation'!K74) -> 0.25 | Q12: =CHOOSE(CF!$G$1,'Capex Allocation'!L12,'Capex Allocation'!L74) -> 0.1 | R12: =CHOOSE(CF!$G$1,'Capex Allocation'!M12,'Capex Allocation'!M74) -> 0 | S12: =CHOOSE(CF!$G$1,'Capex Allocation'!N12,'Capex Allocation'!N74) -> 0 | T12: =CHOOSE(CF!$G$1,'Capex Allocation'!O12,'Capex Allocation'!O74) -> 0 | ... Z12: =CHOOSE(CF!$G$1,'Capex Allocation'!U12,'Capex Allocation'!U74) -> 0
C13: Pre-operating | K13: =SUM(L13:R13) -> 1 | M13: =CHOOSE(CF!$G$1,'Capex Allocation'!H13,'Capex Allocation'!H75) -> 0.1 | N13: =CHOOSE(CF!$G$1,'Capex Allocation'!I13,'Capex Allocation'!I75) -> 0.25 | O13: =CHOOSE(CF!$G$1,'Capex Allocation'!J13,'Capex Allocation'!J75) -> 0.3 | P13: =CHOOSE(CF!$G$1,'Capex Allocation'!K13,'Capex Allocation'!K75) -> 0.25 | Q13: =CHOOSE(CF!$G$1,'Capex Allocation'!L13,'Capex Allocation'!L75) -> 0.1 | R13: =CHOOSE(CF!$G$1,'Capex Allocation'!M13,'Capex Allocation'!M75) -> 0 | S13: =CHOOSE(CF!$G$1,'Capex Allocation'!N13,'Capex Allocation'!N75) -> 0 | T13: =CHOOSE(CF!$G$1,'Capex Allocation'!O13,'Capex Allocation'!O75) -> 0 | ... Z13: =CHOOSE(CF!$G$1,'Capex Allocation'!U13,'Capex Allocation'!U75) -> 0
C14: Professional fee | K14: =SUM(L14:R14) -> 1 | M14: =CHOOSE(CF!$G$1,'Capex Allocation'!H14,'Capex Allocation'!H76) -> 0.1 | N14: =CHOOSE(CF!$G$1,'Capex Allocation'!I14,'Capex Allocation'!I76) -> 0.25 | O14: =CHOOSE(CF!$G$1,'Capex Allocation'!J14,'Capex Allocation'!J76) -> 0.3 | P14: =CHOOSE(CF!$G$1,'Capex Allocation'!K14,'Capex Allocation'!K76) -> 0.25 | Q14: =CHOOSE(CF!$G$1,'Capex Allocation'!L14,'Capex Allocation'!L76) -> 0.1 | R14: =CHOOSE(CF!$G$1,'Capex Allocation'!M14,'Capex Allocation'!M76) -> 0 | S14: =CHOOSE(CF!$G$1,'Capex Allocation'!N14,'Capex Allocation'!N76) -> 0 | T14: =CHOOSE(CF!$G$1,'Capex Allocation'!O14,'Capex Allocation'!O76) -> 0 | ... Z14: =CHOOSE(CF!$G$1,'Capex Allocation'!U14,'Capex Allocation'!U76) -> 0
C15: Commission | K15: =SUM(L15:R15) -> 1 | M15: =CHOOSE(CF!$G$1,'Capex Allocation'!H15,'Capex Allocation'!H77) -> 0.1 | N15: =CHOOSE(CF!$G$1,'Capex Allocation'!I15,'Capex Allocation'!I77) -> 0.25 | O15: =CHOOSE(CF!$G$1,'Capex Allocation'!J15,'Capex Allocation'!J77) -> 0.3 | P15: =CHOOSE(CF!$G$1,'Capex Allocation'!K15,'Capex Allocation'!K77) -> 0.25 | Q15: =CHOOSE(CF!$G$1,'Capex Allocation'!L15,'Capex Allocation'!L77) -> 0.1 | R15: =CHOOSE(CF!$G$1,'Capex Allocation'!M15,'Capex Allocation'!M77) -> 0 | S15: =CHOOSE(CF!$G$1,'Capex Allocation'!N15,'Capex Allocation'!N77) -> 0 | T15: =CHOOSE(CF!$G$1,'Capex Allocation'!O15,'Capex Allocation'!O77) -> 0 | ... Z15: =CHOOSE(CF!$G$1,'Capex Allocation'!U15,'Capex Allocation'!U77) -> 0
C16: Contingency | K16: =SUM(L16:R16) -> 1 | M16: =CHOOSE(CF!$G$1,'Capex Allocation'!H16,'Capex Allocation'!H78) -> 0.1 | N16: =CHOOSE(CF!$G$1,'Capex Allocation'!I16,'Capex Allocation'!I78) -> 0.25 | O16: =CHOOSE(CF!$G$1,'Capex Allocation'!J16,'Capex Allocation'!J78) -> 0.3 | P16: =CHOOSE(CF!$G$1,'Capex Allocation'!K16,'Capex Allocation'!K78) -> 0.25 | Q16: =CHOOSE(CF!$G$1,'Capex Allocation'!L16,'Capex Allocation'!L78) -> 0.1 | R16: =CHOOSE(CF!$G$1,'Capex Allocation'!M16,'Capex Allocation'!M78) -> 0 | S16: =CHOOSE(CF!$G$1,'Capex Allocation'!N16,'Capex Allocation'!N78) -> 0 | T16: =CHOOSE(CF!$G$1,'Capex Allocation'!O16,'Capex Allocation'!O78) -> 0 | ... Z16: =CHOOSE(CF!$G$1,'Capex Allocation'!U16,'Capex Allocation'!U78) -> 0
C17: Check (=100%)
C19: Branded Apartments T4 & T5 - Allocation %
C20: Land | K20: =SUM(L20:R20) -> 1 | M20: =CHOOSE(CF!$G$1,'Capex Allocation'!H19,'Capex Allocation'!H81) -> 1 | N20: =CHOOSE(CF!$G$1,'Capex Allocation'!I19,'Capex Allocation'!I81) -> 0 | O20: =CHOOSE(CF!$G$1,'Capex Allocation'!J19,'Capex Allocation'!J81) -> 0 | P20: =CHOOSE(CF!$G$1,'Capex Allocation'!K19,'Capex Allocation'!K81) -> 0 | Q20: =CHOOSE(CF!$G$1,'Capex Allocation'!L19,'Capex Allocation'!L81) -> 0 | R20: =CHOOSE(CF!$G$1,'Capex Allocation'!M19,'Capex Allocation'!M81) -> 0 | S20: =CHOOSE(CF!$G$1,'Capex Allocation'!N19,'Capex Allocation'!N81) -> 0 | T20: =CHOOSE(CF!$G$1,'Capex Allocation'!O19,'Capex Allocation'!O81) -> 0 | ... Z20: =CHOOSE(CF!$G$1,'Capex Allocation'!U19,'Capex Allocation'!U81) -> 0
C21: Construction (BUA + Parking) | K21: =SUM(L21:R21) -> 1 | M21: =CHOOSE(CF!$G$1,'Capex Allocation'!H20,'Capex Allocation'!H82) -> 0.1 | N21: =CHOOSE(CF!$G$1,'Capex Allocation'!I20,'Capex Allocation'!I82) -> 0.1 | O21: =CHOOSE(CF!$G$1,'Capex Allocation'!J20,'Capex Allocation'!J82) -> 0.25 | P21: =CHOOSE(CF!$G$1,'Capex Allocation'!K20,'Capex Allocation'!K82) -> 0.25 | Q21: =CHOOSE(CF!$G$1,'Capex Allocation'!L20,'Capex Allocation'!L82) -> 0.25 | R21: =CHOOSE(CF!$G$1,'Capex Allocation'!M20,'Capex Allocation'!M82) -> 0.05 | S21: =CHOOSE(CF!$G$1,'Capex Allocation'!N20,'Capex Allocation'!N82) -> 0 | T21: =CHOOSE(CF!$G$1,'Capex Allocation'!O20,'Capex Allocation'!O82) -> 0 | ... Z21: =CHOOSE(CF!$G$1,'Capex Allocation'!U20,'Capex Allocation'!U82) -> 0
C22: Infrastructure | K22: =SUM(L22:R22) -> 1 | M22: =CHOOSE(CF!$G$1,'Capex Allocation'!H21,'Capex Allocation'!H83) -> 0.1 | N22: =CHOOSE(CF!$G$1,'Capex Allocation'!I21,'Capex Allocation'!I83) -> 0.1 | O22: =CHOOSE(CF!$G$1,'Capex Allocation'!J21,'Capex Allocation'!J83) -> 0.25 | P22: =CHOOSE(CF!$G$1,'Capex Allocation'!K21,'Capex Allocation'!K83) -> 0.25 | Q22: =CHOOSE(CF!$G$1,'Capex Allocation'!L21,'Capex Allocation'!L83) -> 0.25 | R22: =CHOOSE(CF!$G$1,'Capex Allocation'!M21,'Capex Allocation'!M83) -> 0.05 | S22: =CHOOSE(CF!$G$1,'Capex Allocation'!N21,'Capex Allocation'!N83) -> 0 | T22: =CHOOSE(CF!$G$1,'Capex Allocation'!O21,'Capex Allocation'!O83) -> 0 | ... Z22: =CHOOSE(CF!$G$1,'Capex Allocation'!U21,'Capex Allocation'!U83) -> 0
C23: Landscaping | K23: =SUM(L23:R23) -> 1 | M23: =CHOOSE(CF!$G$1,'Capex Allocation'!H22,'Capex Allocation'!H84) -> 0.1 | N23: =CHOOSE(CF!$G$1,'Capex Allocation'!I22,'Capex Allocation'!I84) -> 0.1 | O23: =CHOOSE(CF!$G$1,'Capex Allocation'!J22,'Capex Allocation'!J84) -> 0.25 | P23: =CHOOSE(CF!$G$1,'Capex Allocation'!K22,'Capex Allocation'!K84) -> 0.25 | Q23: =CHOOSE(CF!$G$1,'Capex Allocation'!L22,'Capex Allocation'!L84) -> 0.25 | R23: =CHOOSE(CF!$G$1,'Capex Allocation'!M22,'Capex Allocation'!M84) -> 0.05 | S23: =CHOOSE(CF!$G$1,'Capex Allocation'!N22,'Capex Allocation'!N84) -> 0 | T23: =CHOOSE(CF!$G$1,'Capex Allocation'!O22,'Capex Allocation'!O84) -> 0 | ... Z23: =CHOOSE(CF!$G$1,'Capex Allocation'!U22,'Capex Allocation'!U84) -> 0
C24: Pre-operating | K24: =SUM(L24:R24) -> 1 | M24: =CHOOSE(CF!$G$1,'Capex Allocation'!H23,'Capex Allocation'!H85) -> 0.1 | N24: =CHOOSE(CF!$G$1,'Capex Allocation'!I23,'Capex Allocation'!I85) -> 0.1 | O24: =CHOOSE(CF!$G$1,'Capex Allocation'!J23,'Capex Allocation'!J85) -> 0.25 | P24: =CHOOSE(CF!$G$1,'Capex Allocation'!K23,'Capex Allocation'!K85) -> 0.25 | Q24: =CHOOSE(CF!$G$1,'Capex Allocation'!L23,'Capex Allocation'!L85) -> 0.25 | R24: =CHOOSE(CF!$G$1,'Capex Allocation'!M23,'Capex Allocation'!M85) -> 0.05 | S24: =CHOOSE(CF!$G$1,'Capex Allocation'!N23,'Capex Allocation'!N85) -> 0 | T24: =CHOOSE(CF!$G$1,'Capex Allocation'!O23,'Capex Allocation'!O85) -> 0 | ... Z24: =CHOOSE(CF!$G$1,'Capex Allocation'!U23,'Capex Allocation'!U85) -> 0
C25: Professional fee | K25: =SUM(L25:R25) -> 1 | M25: =CHOOSE(CF!$G$1,'Capex Allocation'!H24,'Capex Allocation'!H86) -> 0.1 | N25: =CHOOSE(CF!$G$1,'Capex Allocation'!I24,'Capex Allocation'!I86) -> 0.1 | O25: =CHOOSE(CF!$G$1,'Capex Allocation'!J24,'Capex Allocation'!J86) -> 0.25 | P25: =CHOOSE(CF!$G$1,'Capex Allocation'!K24,'Capex Allocation'!K86) -> 0.25 | Q25: =CHOOSE(CF!$G$1,'Capex Allocation'!L24,'Capex Allocation'!L86) -> 0.25 | R25: =CHOOSE(CF!$G$1,'Capex Allocation'!M24,'Capex Allocation'!M86) -> 0.05 | S25: =CHOOSE(CF!$G$1,'Capex Allocation'!N24,'Capex Allocation'!N86) -> 0 | T25: =CHOOSE(CF!$G$1,'Capex Allocation'!O24,'Capex Allocation'!O86) -> 0 | ... Z25: =CHOOSE(CF!$G$1,'Capex Allocation'!U24,'Capex Allocation'!U86) -> 0
C26: Commission | K26: =SUM(L26:R26) -> 1 | M26: =CHOOSE(CF!$G$1,'Capex Allocation'!H25,'Capex Allocation'!H87) -> 0.1 | N26: =CHOOSE(CF!$G$1,'Capex Allocation'!I25,'Capex Allocation'!I87) -> 0.1 | O26: =CHOOSE(CF!$G$1,'Capex Allocation'!J25,'Capex Allocation'!J87) -> 0.25 | P26: =CHOOSE(CF!$G$1,'Capex Allocation'!K25,'Capex Allocation'!K87) -> 0.25 | Q26: =CHOOSE(CF!$G$1,'Capex Allocation'!L25,'Capex Allocation'!L87) -> 0.25 | R26: =CHOOSE(CF!$G$1,'Capex Allocation'!M25,'Capex Allocation'!M87) -> 0.05 | S26: =CHOOSE(CF!$G$1,'Capex Allocation'!N25,'Capex Allocation'!N87) -> 0 | T26: =CHOOSE(CF!$G$1,'Capex Allocation'!O25,'Capex Allocation'!O87) -> 0 | ... Z26: =CHOOSE(CF!$G$1,'Capex Allocation'!U25,'Capex Allocation'!U87) -> 0
C27: Contingency | K27: =SUM(L27:R27) -> 1 | M27: =CHOOSE(CF!$G$1,'Capex Allocation'!H26,'Capex Allocation'!H88) -> 0.1 | N27: =CHOOSE(CF!$G$1,'Capex Allocation'!I26,'Capex Allocation'!I88) -> 0.1 | O27: =CHOOSE(CF!$G$1,'Capex Allocation'!J26,'Capex Allocation'!J88) -> 0.25 | P27: =CHOOSE(CF!$G$1,'Capex Allocation'!K26,'Capex Allocation'!K88) -> 0.25 | Q27: =CHOOSE(CF!$G$1,'Capex Allocation'!L26,'Capex Allocation'!L88) -> 0.25 | R27: =CHOOSE(CF!$G$1,'Capex Allocation'!M26,'Capex Allocation'!M88) -> 0.05 | S27: =CHOOSE(CF!$G$1,'Capex Allocation'!N26,'Capex Allocation'!N88) -> 0 | T27: =CHOOSE(CF!$G$1,'Capex Allocation'!O26,'Capex Allocation'!O88) -> 0 | ... Z27: =CHOOSE(CF!$G$1,'Capex Allocation'!U26,'Capex Allocation'!U88) -> 0
C28: Check (=100%)
C30: Residential Tower 01 - Allocation %
C31: Land | K31: =SUM(L31:R31) -> 1 | M31: =CHOOSE(CF!$G$1,'Capex Allocation'!H29,'Capex Allocation'!H91) -> 1 | N31: =CHOOSE(CF!$G$1,'Capex Allocation'!I29,'Capex Allocation'!I91) -> 0 | O31: =CHOOSE(CF!$G$1,'Capex Allocation'!J29,'Capex Allocation'!J91) -> 0 | P31: =CHOOSE(CF!$G$1,'Capex Allocation'!K29,'Capex Allocation'!K91) -> 0 | Q31: =CHOOSE(CF!$G$1,'Capex Allocation'!L29,'Capex Allocation'!L91) -> 0 | R31: =CHOOSE(CF!$G$1,'Capex Allocation'!M29,'Capex Allocation'!M91) -> 0 | S31: =CHOOSE(CF!$G$1,'Capex Allocation'!N29,'Capex Allocation'!N91) -> 0 | T31: =CHOOSE(CF!$G$1,'Capex Allocation'!O29,'Capex Allocation'!O91) -> 0 | ... Z31: =CHOOSE(CF!$G$1,'Capex Allocation'!U29,'Capex Allocation'!U91) -> 0
C32: Construction (BUA + Parking) | K32: =SUM(L32:R32) -> 1 | M32: =CHOOSE(CF!$G$1,'Capex Allocation'!H30,'Capex Allocation'!H92) -> 0.1 | N32: =CHOOSE(CF!$G$1,'Capex Allocation'!I30,'Capex Allocation'!I92) -> 0.25 | O32: =CHOOSE(CF!$G$1,'Capex Allocation'!J30,'Capex Allocation'!J92) -> 0.3 | P32: =CHOOSE(CF!$G$1,'Capex Allocation'!K30,'Capex Allocation'!K92) -> 0.25 | Q32: =CHOOSE(CF!$G$1,'Capex Allocation'!L30,'Capex Allocation'!L92) -> 0.1 | R32: =CHOOSE(CF!$G$1,'Capex Allocation'!M30,'Capex Allocation'!M92) -> 0 | S32: =CHOOSE(CF!$G$1,'Capex Allocation'!N30,'Capex Allocation'!N92) -> 0 | T32: =CHOOSE(CF!$G$1,'Capex Allocation'!O30,'Capex Allocation'!O92) -> 0 | ... Z32: =CHOOSE(CF!$G$1,'Capex Allocation'!U30,'Capex Allocation'!U92) -> 0
C33: Infrastructure | K33: =SUM(L33:R33) -> 1 | M33: =CHOOSE(CF!$G$1,'Capex Allocation'!H31,'Capex Allocation'!H93) -> 0.1 | N33: =CHOOSE(CF!$G$1,'Capex Allocation'!I31,'Capex Allocation'!I93) -> 0.25 | O33: =CHOOSE(CF!$G$1,'Capex Allocation'!J31,'Capex Allocation'!J93) -> 0.3 | P33: =CHOOSE(CF!$G$1,'Capex Allocation'!K31,'Capex Allocation'!K93) -> 0.25 | Q33: =CHOOSE(CF!$G$1,'Capex Allocation'!L31,'Capex Allocation'!L93) -> 0.1 | R33: =CHOOSE(CF!$G$1,'Capex Allocation'!M31,'Capex Allocation'!M93) -> 0 | S33: =CHOOSE(CF!$G$1,'Capex Allocation'!N31,'Capex Allocation'!N93) -> 0 | T33: =CHOOSE(CF!$G$1,'Capex Allocation'!O31,'Capex Allocation'!O93) -> 0 | ... Z33: =CHOOSE(CF!$G$1,'Capex Allocation'!U31,'Capex Allocation'!U93) -> 0
C34: Landscaping | K34: =SUM(L34:R34) -> 1 | M34: =CHOOSE(CF!$G$1,'Capex Allocation'!H32,'Capex Allocation'!H94) -> 0.1 | N34: =CHOOSE(CF!$G$1,'Capex Allocation'!I32,'Capex Allocation'!I94) -> 0.25 | O34: =CHOOSE(CF!$G$1,'Capex Allocation'!J32,'Capex Allocation'!J94) -> 0.3 | P34: =CHOOSE(CF!$G$1,'Capex Allocation'!K32,'Capex Allocation'!K94) -> 0.25 | Q34: =CHOOSE(CF!$G$1,'Capex Allocation'!L32,'Capex Allocation'!L94) -> 0.1 | R34: =CHOOSE(CF!$G$1,'Capex Allocation'!M32,'Capex Allocation'!M94) -> 0 | S34: =CHOOSE(CF!$G$1,'Capex Allocation'!N32,'Capex Allocation'!N94) -> 0 | T34: =CHOOSE(CF!$G$1,'Capex Allocation'!O32,'Capex Allocation'!O94) -> 0 | ... Z34: =CHOOSE(CF!$G$1,'Capex Allocation'!U32,'Capex Allocation'!U94) -> 0
C35: Pre-operating | K35: =SUM(L35:R35) -> 1 | M35: =CHOOSE(CF!$G$1,'Capex Allocation'!H33,'Capex Allocation'!H95) -> 0.1 | N35: =CHOOSE(CF!$G$1,'Capex Allocation'!I33,'Capex Allocation'!I95) -> 0.25 | O35: =CHOOSE(CF!$G$1,'Capex Allocation'!J33,'Capex Allocation'!J95) -> 0.3 | P35: =CHOOSE(CF!$G$1,'Capex Allocation'!K33,'Capex Allocation'!K95) -> 0.25 | Q35: =CHOOSE(CF!$G$1,'Capex Allocation'!L33,'Capex Allocation'!L95) -> 0.1 | R35: =CHOOSE(CF!$G$1,'Capex Allocation'!M33,'Capex Allocation'!M95) -> 0 | S35: =CHOOSE(CF!$G$1,'Capex Allocation'!N33,'Capex Allocation'!N95) -> 0 | T35: =CHOOSE(CF!$G$1,'Capex Allocation'!O33,'Capex Allocation'!O95) -> 0 | ... Z35: =CHOOSE(CF!$G$1,'Capex Allocation'!U33,'Capex Allocation'!U95) -> 0
C36: Professional fee | K36: =SUM(L36:R36) -> 1 | M36: =CHOOSE(CF!$G$1,'Capex Allocation'!H34,'Capex Allocation'!H96) -> 0.1 | N36: =CHOOSE(CF!$G$1,'Capex Allocation'!I34,'Capex Allocation'!I96) -> 0.25 | O36: =CHOOSE(CF!$G$1,'Capex Allocation'!J34,'Capex Allocation'!J96) -> 0.3 | P36: =CHOOSE(CF!$G$1,'Capex Allocation'!K34,'Capex Allocation'!K96) -> 0.25 | Q36: =CHOOSE(CF!$G$1,'Capex Allocation'!L34,'Capex Allocation'!L96) -> 0.1 | R36: =CHOOSE(CF!$G$1,'Capex Allocation'!M34,'Capex Allocation'!M96) -> 0 | S36: =CHOOSE(CF!$G$1,'Capex Allocation'!N34,'Capex Allocation'!N96) -> 0 | T36: =CHOOSE(CF!$G$1,'Capex Allocation'!O34,'Capex Allocation'!O96) -> 0 | ... Z36: =CHOOSE(CF!$G$1,'Capex Allocation'!U34,'Capex Allocation'!U96) -> 0
C37: Commission | K37: =SUM(L37:R37) -> 1 | M37: =CHOOSE(CF!$G$1,'Capex Allocation'!H35,'Capex Allocation'!H97) -> 0.1 | N37: =CHOOSE(CF!$G$1,'Capex Allocation'!I35,'Capex Allocation'!I97) -> 0.25 | O37: =CHOOSE(CF!$G$1,'Capex Allocation'!J35,'Capex Allocation'!J97) -> 0.3 | P37: =CHOOSE(CF!$G$1,'Capex Allocation'!K35,'Capex Allocation'!K97) -> 0.25 | Q37: =CHOOSE(CF!$G$1,'Capex Allocation'!L35,'Capex Allocation'!L97) -> 0.1 | R37: =CHOOSE(CF!$G$1,'Capex Allocation'!M35,'Capex Allocation'!M97) -> 0 | S37: =CHOOSE(CF!$G$1,'Capex Allocation'!N35,'Capex Allocation'!N97) -> 0 | T37: =CHOOSE(CF!$G$1,'Capex Allocation'!O35,'Capex Allocation'!O97) -> 0 | ... Z37: =CHOOSE(CF!$G$1,'Capex Allocation'!U35,'Capex Allocation'!U97) -> 0
C38: Contingency | K38: =SUM(L38:R38) -> 1 | M38: =CHOOSE(CF!$G$1,'Capex Allocation'!H36,'Capex Allocation'!H98) -> 0.1 | N38: =CHOOSE(CF!$G$1,'Capex Allocation'!I36,'Capex Allocation'!I98) -> 0.25 | O38: =CHOOSE(CF!$G$1,'Capex Allocation'!J36,'Capex Allocation'!J98) -> 0.3 | P38: =CHOOSE(CF!$G$1,'Capex Allocation'!K36,'Capex Allocation'!K98) -> 0.25 | Q38: =CHOOSE(CF!$G$1,'Capex Allocation'!L36,'Capex Allocation'!L98) -> 0.1 | R38: =CHOOSE(CF!$G$1,'Capex Allocation'!M36,'Capex Allocation'!M98) -> 0 | S38: =CHOOSE(CF!$G$1,'Capex Allocation'!N36,'Capex Allocation'!N98) -> 0 | T38: =CHOOSE(CF!$G$1,'Capex Allocation'!O36,'Capex Allocation'!O98) -> 0 | ... Z38: =CHOOSE(CF!$G$1,'Capex Allocation'!U36,'Capex Allocation'!U98) -> 0
C39: Check (=100%)
C41: Hotel 01 - 336 Keys - Allocation %
C42: Land | K42: =SUM(L42:R42) -> 1 | M42: =CHOOSE(CF!$G$1,'Capex Allocation'!H39,'Capex Allocation'!H101) -> 1 | N42: =CHOOSE(CF!$G$1,'Capex Allocation'!I39,'Capex Allocation'!I101) -> 0 | O42: =CHOOSE(CF!$G$1,'Capex Allocation'!J39,'Capex Allocation'!J101) -> 0 | P42: =CHOOSE(CF!$G$1,'Capex Allocation'!K39,'Capex Allocation'!K101) -> 0 | Q42: =CHOOSE(CF!$G$1,'Capex Allocation'!L39,'Capex Allocation'!L101) -> 0 | R42: =CHOOSE(CF!$G$1,'Capex Allocation'!M39,'Capex Allocation'!M101) -> 0 | S42: =CHOOSE(CF!$G$1,'Capex Allocation'!N39,'Capex Allocation'!N101) -> 0 | T42: =CHOOSE(CF!$G$1,'Capex Allocation'!O39,'Capex Allocation'!O101) -> 0 | ... Z42: =CHOOSE(CF!$G$1,'Capex Allocation'!U39,'Capex Allocation'!U101) -> 0
C43: Construction (BUA + Parking) | K43: =SUM(L43:R43) -> 1 | M43: =CHOOSE(CF!$G$1,'Capex Allocation'!H40,'Capex Allocation'!H102) -> 0.1 | N43: =CHOOSE(CF!$G$1,'Capex Allocation'!I40,'Capex Allocation'!I102) -> 0.25 | O43: =CHOOSE(CF!$G$1,'Capex Allocation'!J40,'Capex Allocation'!J102) -> 0.3 | P43: =CHOOSE(CF!$G$1,'Capex Allocation'!K40,'Capex Allocation'!K102) -> 0.25 | Q43: =CHOOSE(CF!$G$1,'Capex Allocation'!L40,'Capex Allocation'!L102) -> 0.1 | R43: =CHOOSE(CF!$G$1,'Capex Allocation'!M40,'Capex Allocation'!M102) -> 0 | S43: =CHOOSE(CF!$G$1,'Capex Allocation'!N40,'Capex Allocation'!N102) -> 0 | T43: =CHOOSE(CF!$G$1,'Capex Allocation'!O40,'Capex Allocation'!O102) -> 0 | ... Z43: =CHOOSE(CF!$G$1,'Capex Allocation'!U40,'Capex Allocation'!U102) -> 0
C44: Infrastructure | K44: =SUM(L44:R44) -> 1 | M44: =CHOOSE(CF!$G$1,'Capex Allocation'!H41,'Capex Allocation'!H103) -> 0.1 | N44: =CHOOSE(CF!$G$1,'Capex Allocation'!I41,'Capex Allocation'!I103) -> 0.25 | O44: =CHOOSE(CF!$G$1,'Capex Allocation'!J41,'Capex Allocation'!J103) -> 0.3 | P44: =CHOOSE(CF!$G$1,'Capex Allocation'!K41,'Capex Allocation'!K103) -> 0.25 | Q44: =CHOOSE(CF!$G$1,'Capex Allocation'!L41,'Capex Allocation'!L103) -> 0.1 | R44: =CHOOSE(CF!$G$1,'Capex Allocation'!M41,'Capex Allocation'!M103) -> 0 | S44: =CHOOSE(CF!$G$1,'Capex Allocation'!N41,'Capex Allocation'!N103) -> 0 | T44: =CHOOSE(CF!$G$1,'Capex Allocation'!O41,'Capex Allocation'!O103) -> 0 | ... Z44: =CHOOSE(CF!$G$1,'Capex Allocation'!U41,'Capex Allocation'!U103) -> 0
C45: Landscaping | K45: =SUM(L45:R45) -> 1 | M45: =CHOOSE(CF!$G$1,'Capex Allocation'!H42,'Capex Allocation'!H104) -> 0.1 | N45: =CHOOSE(CF!$G$1,'Capex Allocation'!I42,'Capex Allocation'!I104) -> 0.25 | O45: =CHOOSE(CF!$G$1,'Capex Allocation'!J42,'Capex Allocation'!J104) -> 0.3 | P45: =CHOOSE(CF!$G$1,'Capex Allocation'!K42,'Capex Allocation'!K104) -> 0.25 | Q45: =CHOOSE(CF!$G$1,'Capex Allocation'!L42,'Capex Allocation'!L104) -> 0.1 | R45: =CHOOSE(CF!$G$1,'Capex Allocation'!M42,'Capex Allocation'!M104) -> 0 | S45: =CHOOSE(CF!$G$1,'Capex Allocation'!N42,'Capex Allocation'!N104) -> 0 | T45: =CHOOSE(CF!$G$1,'Capex Allocation'!O42,'Capex Allocation'!O104) -> 0 | ... Z45: =CHOOSE(CF!$G$1,'Capex Allocation'!U42,'Capex Allocation'!U104) -> 0
C46: Pre-operating | K46: =SUM(L46:R46) -> 1 | M46: =CHOOSE(CF!$G$1,'Capex Allocation'!H43,'Capex Allocation'!H105) -> 0.1 | N46: =CHOOSE(CF!$G$1,'Capex Allocation'!I43,'Capex Allocation'!I105) -> 0.25 | O46: =CHOOSE(CF!$G$1,'Capex Allocation'!J43,'Capex Allocation'!J105) -> 0.3 | P46: =CHOOSE(CF!$G$1,'Capex Allocation'!K43,'Capex Allocation'!K105) -> 0.25 | Q46: =CHOOSE(CF!$G$1,'Capex Allocation'!L43,'Capex Allocation'!L105) -> 0.1 | R46: =CHOOSE(CF!$G$1,'Capex Allocation'!M43,'Capex Allocation'!M105) -> 0 | S46: =CHOOSE(CF!$G$1,'Capex Allocation'!N43,'Capex Allocation'!N105) -> 0 | T46: =CHOOSE(CF!$G$1,'Capex Allocation'!O43,'Capex Allocation'!O105) -> 0 | ... Z46: =CHOOSE(CF!$G$1,'Capex Allocation'!U43,'Capex Allocation'!U105) -> 0
C47: Professional fee | K47: =SUM(L47:R47) -> 1 | M47: =CHOOSE(CF!$G$1,'Capex Allocation'!H44,'Capex Allocation'!H106) -> 0.1 | N47: =CHOOSE(CF!$G$1,'Capex Allocation'!I44,'Capex Allocation'!I106) -> 0.25 | O47: =CHOOSE(CF!$G$1,'Capex Allocation'!J44,'Capex Allocation'!J106) -> 0.3 | P47: =CHOOSE(CF!$G$1,'Capex Allocation'!K44,'Capex Allocation'!K106) -> 0.25 | Q47: =CHOOSE(CF!$G$1,'Capex Allocation'!L44,'Capex Allocation'!L106) -> 0.1 | R47: =CHOOSE(CF!$G$1,'Capex Allocation'!M44,'Capex Allocation'!M106) -> 0 | S47: =CHOOSE(CF!$G$1,'Capex Allocation'!N44,'Capex Allocation'!N106) -> 0 | T47: =CHOOSE(CF!$G$1,'Capex Allocation'!O44,'Capex Allocation'!O106) -> 0 | ... Z47: =CHOOSE(CF!$G$1,'Capex Allocation'!U44,'Capex Allocation'!U106) -> 0
C48: Commission | K48: =SUM(L48:R48) -> 1 | M48: =CHOOSE(CF!$G$1,'Capex Allocation'!H45,'Capex Allocation'!H107) -> 0.1 | N48: =CHOOSE(CF!$G$1,'Capex Allocation'!I45,'Capex Allocation'!I107) -> 0.25 | O48: =CHOOSE(CF!$G$1,'Capex Allocation'!J45,'Capex Allocation'!J107) -> 0.3 | P48: =CHOOSE(CF!$G$1,'Capex Allocation'!K45,'Capex Allocation'!K107) -> 0.25 | Q48: =CHOOSE(CF!$G$1,'Capex Allocation'!L45,'Capex Allocation'!L107) -> 0.1 | R48: =CHOOSE(CF!$G$1,'Capex Allocation'!M45,'Capex Allocation'!M107) -> 0 | S48: =CHOOSE(CF!$G$1,'Capex Allocation'!N45,'Capex Allocation'!N107) -> 0 | T48: =CHOOSE(CF!$G$1,'Capex Allocation'!O45,'Capex Allocation'!O107) -> 0 | ... Z48: =CHOOSE(CF!$G$1,'Capex Allocation'!U45,'Capex Allocation'!U107) -> 0
C49: Contingency | K49: =SUM(L49:R49) -> 1 | M49: =CHOOSE(CF!$G$1,'Capex Allocation'!H46,'Capex Allocation'!H108) -> 0.1 | N49: =CHOOSE(CF!$G$1,'Capex Allocation'!I46,'Capex Allocation'!I108) -> 0.25 | O49: =CHOOSE(CF!$G$1,'Capex Allocation'!J46,'Capex Allocation'!J108) -> 0.3 | P49: =CHOOSE(CF!$G$1,'Capex Allocation'!K46,'Capex Allocation'!K108) -> 0.25 | Q49: =CHOOSE(CF!$G$1,'Capex Allocation'!L46,'Capex Allocation'!L108) -> 0.1 | R49: =CHOOSE(CF!$G$1,'Capex Allocation'!M46,'Capex Allocation'!M108) -> 0 | S49: =CHOOSE(CF!$G$1,'Capex Allocation'!N46,'Capex Allocation'!N108) -> 0 | T49: =CHOOSE(CF!$G$1,'Capex Allocation'!O46,'Capex Allocation'!O108) -> 0 | ... Z49: =CHOOSE(CF!$G$1,'Capex Allocation'!U46,'Capex Allocation'!U108) -> 0
C50: Check (=100%)
C52: Support Retail (P2) - Allocation %
C53: Land | K53: =SUM(L53:R53) -> 1 | M53: =CHOOSE(CF!$G$1,'Capex Allocation'!H49,'Capex Allocation'!H111) -> 1 | N53: =CHOOSE(CF!$G$1,'Capex Allocation'!I49,'Capex Allocation'!I111) -> 0 | O53: =CHOOSE(CF!$G$1,'Capex Allocation'!J49,'Capex Allocation'!J111) -> 0 | P53: =CHOOSE(CF!$G$1,'Capex Allocation'!K49,'Capex Allocation'!K111) -> 0 | Q53: =CHOOSE(CF!$G$1,'Capex Allocation'!L49,'Capex Allocation'!L111) -> 0 | R53: =CHOOSE(CF!$G$1,'Capex Allocation'!M49,'Capex Allocation'!M111) -> 0 | S53: =CHOOSE(CF!$G$1,'Capex Allocation'!N49,'Capex Allocation'!N111) -> 0 | T53: =CHOOSE(CF!$G$1,'Capex Allocation'!O49,'Capex Allocation'!O111) -> 0 | ... Z53: =CHOOSE(CF!$G$1,'Capex Allocation'!U49,'Capex Allocation'!U111) -> 0
C54: Construction (BUA + Parking) | K54: =SUM(L54:R54) -> 1 | M54: =CHOOSE(CF!$G$1,'Capex Allocation'!H50,'Capex Allocation'!H112) -> 0.1 | N54: =CHOOSE(CF!$G$1,'Capex Allocation'!I50,'Capex Allocation'!I112) -> 0.25 | O54: =CHOOSE(CF!$G$1,'Capex Allocation'!J50,'Capex Allocation'!J112) -> 0.3 | P54: =CHOOSE(CF!$G$1,'Capex Allocation'!K50,'Capex Allocation'!K112) -> 0.25 | Q54: =CHOOSE(CF!$G$1,'Capex Allocation'!L50,'Capex Allocation'!L112) -> 0.1 | R54: =CHOOSE(CF!$G$1,'Capex Allocation'!M50,'Capex Allocation'!M112) -> 0 | S54: =CHOOSE(CF!$G$1,'Capex Allocation'!N50,'Capex Allocation'!N112) -> 0 | T54: =CHOOSE(CF!$G$1,'Capex Allocation'!O50,'Capex Allocation'!O112) -> 0 | ... Z54: =CHOOSE(CF!$G$1,'Capex Allocation'!U50,'Capex Allocation'!U112) -> 0
C55: Infrastructure | K55: =SUM(L55:R55) -> 1 | M55: =CHOOSE(CF!$G$1,'Capex Allocation'!H51,'Capex Allocation'!H113) -> 0.1 | N55: =CHOOSE(CF!$G$1,'Capex Allocation'!I51,'Capex Allocation'!I113) -> 0.25 | O55: =CHOOSE(CF!$G$1,'Capex Allocation'!J51,'Capex Allocation'!J113) -> 0.3 | P55: =CHOOSE(CF!$G$1,'Capex Allocation'!K51,'Capex Allocation'!K113) -> 0.25 | Q55: =CHOOSE(CF!$G$1,'Capex Allocation'!L51,'Capex Allocation'!L113) -> 0.1 | R55: =CHOOSE(CF!$G$1,'Capex Allocation'!M51,'Capex Allocation'!M113) -> 0 | S55: =CHOOSE(CF!$G$1,'Capex Allocation'!N51,'Capex Allocation'!N113) -> 0 | T55: =CHOOSE(CF!$G$1,'Capex Allocation'!O51,'Capex Allocation'!O113) -> 0 | ... Z55: =CHOOSE(CF!$G$1,'Capex Allocation'!U51,'Capex Allocation'!U113) -> 0
C56: Landscaping | K56: =SUM(L56:R56) -> 1 | M56: =CHOOSE(CF!$G$1,'Capex Allocation'!H52,'Capex Allocation'!H114) -> 0.1 | N56: =CHOOSE(CF!$G$1,'Capex Allocation'!I52,'Capex Allocation'!I114) -> 0.25 | O56: =CHOOSE(CF!$G$1,'Capex Allocation'!J52,'Capex Allocation'!J114) -> 0.3 | P56: =CHOOSE(CF!$G$1,'Capex Allocation'!K52,'Capex Allocation'!K114) -> 0.25 | Q56: =CHOOSE(CF!$G$1,'Capex Allocation'!L52,'Capex Allocation'!L114) -> 0.1 | R56: =CHOOSE(CF!$G$1,'Capex Allocation'!M52,'Capex Allocation'!M114) -> 0 | S56: =CHOOSE(CF!$G$1,'Capex Allocation'!N52,'Capex Allocation'!N114) -> 0 | T56: =CHOOSE(CF!$G$1,'Capex Allocation'!O52,'Capex Allocation'!O114) -> 0 | ... Z56: =CHOOSE(CF!$G$1,'Capex Allocation'!U52,'Capex Allocation'!U114) -> 0
C57: Pre-operating | K57: =SUM(L57:R57) -> 1 | M57: =CHOOSE(CF!$G$1,'Capex Allocation'!H53,'Capex Allocation'!H115) -> 0.1 | N57: =CHOOSE(CF!$G$1,'Capex Allocation'!I53,'Capex Allocation'!I115) -> 0.25 | O57: =CHOOSE(CF!$G$1,'Capex Allocation'!J53,'Capex Allocation'!J115) -> 0.3 | P57: =CHOOSE(CF!$G$1,'Capex Allocation'!K53,'Capex Allocation'!K115) -> 0.25 | Q57: =CHOOSE(CF!$G$1,'Capex Allocation'!L53,'Capex Allocation'!L115) -> 0.1 | R57: =CHOOSE(CF!$G$1,'Capex Allocation'!M53,'Capex Allocation'!M115) -> 0 | S57: =CHOOSE(CF!$G$1,'Capex Allocation'!N53,'Capex Allocation'!N115) -> 0 | T57: =CHOOSE(CF!$G$1,'Capex Allocation'!O53,'Capex Allocation'!O115) -> 0 | ... Z57: =CHOOSE(CF!$G$1,'Capex Allocation'!U53,'Capex Allocation'!U115) -> 0
C58: Professional fee | K58: =SUM(L58:R58) -> 1 | M58: =CHOOSE(CF!$G$1,'Capex Allocation'!H54,'Capex Allocation'!H116) -> 0.1 | N58: =CHOOSE(CF!$G$1,'Capex Allocation'!I54,'Capex Allocation'!I116) -> 0.25 | O58: =CHOOSE(CF!$G$1,'Capex Allocation'!J54,'Capex Allocation'!J116) -> 0.3 | P58: =CHOOSE(CF!$G$1,'Capex Allocation'!K54,'Capex Allocation'!K116) -> 0.25 | Q58: =CHOOSE(CF!$G$1,'Capex Allocation'!L54,'Capex Allocation'!L116) -> 0.1 | R58: =CHOOSE(CF!$G$1,'Capex Allocation'!M54,'Capex Allocation'!M116) -> 0 | S58: =CHOOSE(CF!$G$1,'Capex Allocation'!N54,'Capex Allocation'!N116) -> 0 | T58: =CHOOSE(CF!$G$1,'Capex Allocation'!O54,'Capex Allocation'!O116) -> 0 | ... Z58: =CHOOSE(CF!$G$1,'Capex Allocation'!U54,'Capex Allocation'!U116) -> 0
C59: Commission | K59: =SUM(L59:R59) -> 1 | M59: =CHOOSE(CF!$G$1,'Capex Allocation'!H55,'Capex Allocation'!H117) -> 0.1 | N59: =CHOOSE(CF!$G$1,'Capex Allocation'!I55,'Capex Allocation'!I117) -> 0.25 | O59: =CHOOSE(CF!$G$1,'Capex Allocation'!J55,'Capex Allocation'!J117) -> 0.3 | P59: =CHOOSE(CF!$G$1,'Capex Allocation'!K55,'Capex Allocation'!K117) -> 0.25 | Q59: =CHOOSE(CF!$G$1,'Capex Allocation'!L55,'Capex Allocation'!L117) -> 0.1 | R59: =CHOOSE(CF!$G$1,'Capex Allocation'!M55,'Capex Allocation'!M117) -> 0 | S59: =CHOOSE(CF!$G$1,'Capex Allocation'!N55,'Capex Allocation'!N117) -> 0 | T59: =CHOOSE(CF!$G$1,'Capex Allocation'!O55,'Capex Allocation'!O117) -> 0 | ... Z59: =CHOOSE(CF!$G$1,'Capex Allocation'!U55,'Capex Allocation'!U117) -> 0
C60: Contingency | K60: =SUM(L60:R60) -> 1 | M60: =CHOOSE(CF!$G$1,'Capex Allocation'!H56,'Capex Allocation'!H118) -> 0.1 | N60: =CHOOSE(CF!$G$1,'Capex Allocation'!I56,'Capex Allocation'!I118) -> 0.25 | O60: =CHOOSE(CF!$G$1,'Capex Allocation'!J56,'Capex Allocation'!J118) -> 0.3 | P60: =CHOOSE(CF!$G$1,'Capex Allocation'!K56,'Capex Allocation'!K118) -> 0.25 | Q60: =CHOOSE(CF!$G$1,'Capex Allocation'!L56,'Capex Allocation'!L118) -> 0.1 | R60: =CHOOSE(CF!$G$1,'Capex Allocation'!M56,'Capex Allocation'!M118) -> 0 | S60: =CHOOSE(CF!$G$1,'Capex Allocation'!N56,'Capex Allocation'!N118) -> 0 | T60: =CHOOSE(CF!$G$1,'Capex Allocation'!O56,'Capex Allocation'!O118) -> 0 | ... Z60: =CHOOSE(CF!$G$1,'Capex Allocation'!U56,'Capex Allocation'!U118) -> 0
C61: Check (=100%)
C63: Support Retail (P3) - Allocation %
C64: Land | K64: =SUM(L64:R64) -> 1 | M64: =CHOOSE(CF!$G$1,'Capex Allocation'!H59,'Capex Allocation'!H121) -> 1 | N64: =CHOOSE(CF!$G$1,'Capex Allocation'!I59,'Capex Allocation'!I121) -> 0 | O64: =CHOOSE(CF!$G$1,'Capex Allocation'!J59,'Capex Allocation'!J121) -> 0 | P64: =CHOOSE(CF!$G$1,'Capex Allocation'!K59,'Capex Allocation'!K121) -> 0 | Q64: =CHOOSE(CF!$G$1,'Capex Allocation'!L59,'Capex Allocation'!L121) -> 0 | R64: =CHOOSE(CF!$G$1,'Capex Allocation'!M59,'Capex Allocation'!M121) -> 0 | S64: =CHOOSE(CF!$G$1,'Capex Allocation'!N59,'Capex Allocation'!N121) -> 0 | T64: =CHOOSE(CF!$G$1,'Capex Allocation'!O59,'Capex Allocation'!O121) -> 0 | ... Z64: =CHOOSE(CF!$G$1,'Capex Allocation'!U59,'Capex Allocation'!U121) -> 0
C65: Construction (BUA + Parking) | K65: =SUM(L65:R65) -> 1 | M65: =CHOOSE(CF!$G$1,'Capex Allocation'!H60,'Capex Allocation'!H122) -> 0.1 | N65: =CHOOSE(CF!$G$1,'Capex Allocation'!I60,'Capex Allocation'!I122) -> 0.1 | O65: =CHOOSE(CF!$G$1,'Capex Allocation'!J60,'Capex Allocation'!J122) -> 0.25 | P65: =CHOOSE(CF!$G$1,'Capex Allocation'!K60,'Capex Allocation'!K122) -> 0.25 | Q65: =CHOOSE(CF!$G$1,'Capex Allocation'!L60,'Capex Allocation'!L122) -> 0.25 | R65: =CHOOSE(CF!$G$1,'Capex Allocation'!M60,'Capex Allocation'!M122) -> 0.05 | S65: =CHOOSE(CF!$G$1,'Capex Allocation'!N60,'Capex Allocation'!N122) -> 0 | T65: =CHOOSE(CF!$G$1,'Capex Allocation'!O60,'Capex Allocation'!O122) -> 0 | ... Z65: =CHOOSE(CF!$G$1,'Capex Allocation'!U60,'Capex Allocation'!U122) -> 0
C66: Infrastructure | K66: =SUM(L66:R66) -> 1 | M66: =CHOOSE(CF!$G$1,'Capex Allocation'!H61,'Capex Allocation'!H123) -> 0.1 | N66: =CHOOSE(CF!$G$1,'Capex Allocation'!I61,'Capex Allocation'!I123) -> 0.1 | O66: =CHOOSE(CF!$G$1,'Capex Allocation'!J61,'Capex Allocation'!J123) -> 0.25 | P66: =CHOOSE(CF!$G$1,'Capex Allocation'!K61,'Capex Allocation'!K123) -> 0.25 | Q66: =CHOOSE(CF!$G$1,'Capex Allocation'!L61,'Capex Allocation'!L123) -> 0.25 | R66: =CHOOSE(CF!$G$1,'Capex Allocation'!M61,'Capex Allocation'!M123) -> 0.05 | S66: =CHOOSE(CF!$G$1,'Capex Allocation'!N61,'Capex Allocation'!N123) -> 0 | T66: =CHOOSE(CF!$G$1,'Capex Allocation'!O61,'Capex Allocation'!O123) -> 0 | ... Z66: =CHOOSE(CF!$G$1,'Capex Allocation'!U61,'Capex Allocation'!U123) -> 0
C67: Landscaping | K67: =SUM(L67:R67) -> 1 | M67: =CHOOSE(CF!$G$1,'Capex Allocation'!H62,'Capex Allocation'!H124) -> 0.1 | N67: =CHOOSE(CF!$G$1,'Capex Allocation'!I62,'Capex Allocation'!I124) -> 0.1 | O67: =CHOOSE(CF!$G$1,'Capex Allocation'!J62,'Capex Allocation'!J124) -> 0.25 | P67: =CHOOSE(CF!$G$1,'Capex Allocation'!K62,'Capex Allocation'!K124) -> 0.25 | Q67: =CHOOSE(CF!$G$1,'Capex Allocation'!L62,'Capex Allocation'!L124) -> 0.25 | R67: =CHOOSE(CF!$G$1,'Capex Allocation'!M62,'Capex Allocation'!M124) -> 0.05 | S67: =CHOOSE(CF!$G$1,'Capex Allocation'!N62,'Capex Allocation'!N124) -> 0 | T67: =CHOOSE(CF!$G$1,'Capex Allocation'!O62,'Capex Allocation'!O124) -> 0 | ... Z67: =CHOOSE(CF!$G$1,'Capex Allocation'!U62,'Capex Allocation'!U124) -> 0
C68: Pre-operating | K68: =SUM(L68:R68) -> 1 | M68: =CHOOSE(CF!$G$1,'Capex Allocation'!H63,'Capex Allocation'!H125) -> 0.1 | N68: =CHOOSE(CF!$G$1,'Capex Allocation'!I63,'Capex Allocation'!I125) -> 0.1 | O68: =CHOOSE(CF!$G$1,'Capex Allocation'!J63,'Capex Allocation'!J125) -> 0.25 | P68: =CHOOSE(CF!$G$1,'Capex Allocation'!K63,'Capex Allocation'!K125) -> 0.25 | Q68: =CHOOSE(CF!$G$1,'Capex Allocation'!L63,'Capex Allocation'!L125) -> 0.25 | R68: =CHOOSE(CF!$G$1,'Capex Allocation'!M63,'Capex Allocation'!M125) -> 0.05 | S68: =CHOOSE(CF!$G$1,'Capex Allocation'!N63,'Capex Allocation'!N125) -> 0 | T68: =CHOOSE(CF!$G$1,'Capex Allocation'!O63,'Capex Allocation'!O125) -> 0 | ... Z68: =CHOOSE(CF!$G$1,'Capex Allocation'!U63,'Capex Allocation'!U125) -> 0
C69: Professional fee | K69: =SUM(L69:R69) -> 1 | M69: =CHOOSE(CF!$G$1,'Capex Allocation'!H64,'Capex Allocation'!H126) -> 0.1 | N69: =CHOOSE(CF!$G$1,'Capex Allocation'!I64,'Capex Allocation'!I126) -> 0.1 | O69: =CHOOSE(CF!$G$1,'Capex Allocation'!J64,'Capex Allocation'!J126) -> 0.25 | P69: =CHOOSE(CF!$G$1,'Capex Allocation'!K64,'Capex Allocation'!K126) -> 0.25 | Q69: =CHOOSE(CF!$G$1,'Capex Allocation'!L64,'Capex Allocation'!L126) -> 0.25 | R69: =CHOOSE(CF!$G$1,'Capex Allocation'!M64,'Capex Allocation'!M126) -> 0.05 | S69: =CHOOSE(CF!$G$1,'Capex Allocation'!N64,'Capex Allocation'!N126) -> 0 | T69: =CHOOSE(CF!$G$1,'Capex Allocation'!O64,'Capex Allocation'!O126) -> 0 | ... Z69: =CHOOSE(CF!$G$1,'Capex Allocation'!U64,'Capex Allocation'!U126) -> 0
C70: Commission | K70: =SUM(L70:R70) -> 1 | M70: =CHOOSE(CF!$G$1,'Capex Allocation'!H65,'Capex Allocation'!H127) -> 0.1 | N70: =CHOOSE(CF!$G$1,'Capex Allocation'!I65,'Capex Allocation'!I127) -> 0.1 | O70: =CHOOSE(CF!$G$1,'Capex Allocation'!J65,'Capex Allocation'!J127) -> 0.25 | P70: =CHOOSE(CF!$G$1,'Capex Allocation'!K65,'Capex Allocation'!K127) -> 0.25 | Q70: =CHOOSE(CF!$G$1,'Capex Allocation'!L65,'Capex Allocation'!L127) -> 0.25 | R70: =CHOOSE(CF!$G$1,'Capex Allocation'!M65,'Capex Allocation'!M127) -> 0.05 | S70: =CHOOSE(CF!$G$1,'Capex Allocation'!N65,'Capex Allocation'!N127) -> 0 | T70: =CHOOSE(CF!$G$1,'Capex Allocation'!O65,'Capex Allocation'!O127) -> 0 | ... Z70: =CHOOSE(CF!$G$1,'Capex Allocation'!U65,'Capex Allocation'!U127) -> 0
C71: Contingency | K71: =SUM(L71:R71) -> 1 | M71: =CHOOSE(CF!$G$1,'Capex Allocation'!H66,'Capex Allocation'!H128) -> 0.1 | N71: =CHOOSE(CF!$G$1,'Capex Allocation'!I66,'Capex Allocation'!I128) -> 0.1 | O71: =CHOOSE(CF!$G$1,'Capex Allocation'!J66,'Capex Allocation'!J128) -> 0.25 | P71: =CHOOSE(CF!$G$1,'Capex Allocation'!K66,'Capex Allocation'!K128) -> 0.25 | Q71: =CHOOSE(CF!$G$1,'Capex Allocation'!L66,'Capex Allocation'!L128) -> 0.25 | R71: =CHOOSE(CF!$G$1,'Capex Allocation'!M66,'Capex Allocation'!M128) -> 0.05 | S71: =CHOOSE(CF!$G$1,'Capex Allocation'!N66,'Capex Allocation'!N128) -> 0 | T71: =CHOOSE(CF!$G$1,'Capex Allocation'!O66,'Capex Allocation'!O128) -> 0 | ... Z71: =CHOOSE(CF!$G$1,'Capex Allocation'!U66,'Capex Allocation'!U128) -> 0
C72: Check (=100%)
B74: Branded Apartments T2 & T3 - Phase 2 (Residential)
C75: 1. Land cost | F75: Land sqm × rate × active | G75: ='Land Summary'!E36 -> 5718.413 | H75: ='Land Summary'!F36 -> 98450.587 | I75: 1 | K75: =G75*H75*I75/1000 -> 562981.12 | L75: =L$9*$K75 -> 0 | M75: =M$9*$K75 -> 562981.12 | N75: =N$9*$K75 -> 0 | O75: =O$9*$K75 -> 0 | P75: =P$9*$K75 -> 0 | Q75: =Q$9*$K75 -> 0 | R75: =R$9*$K75 -> 0 | S75: =S$9*$K75 -> 0 | ... Z75: =Z$9*$K75 -> 0
C76: 2. Construction (BUA) - by sub-unit
C77: 2.1 1 BR | F77: sqm × rate | G77: 47800 | H77: 6750 | K77: =G77*H77/1000 -> 322650
C78: 2.2 2 BR | F78: sqm × rate | G78: 36497 | H78: 6750 | K78: =G78*H78/1000 -> 246354.75
C79: 2.3 Support Area | F79: sqm × rate | G79: 46577 | H79: 6750 | K79: =G79*H79/1000 -> 314394.75
C80: Subtotal Construction (BUA) | G80: =SUM(G77:G79) -> 130874 | K80: =SUM(K77:K79) -> 883399.5 | L80: =L$10*$K80 -> 0 | M80: =M$10*$K80 -> 88339.95 | N80: =N$10*$K80 -> 220849.88 | O80: =O$10*$K80 -> 265019.85 | P80: =P$10*$K80 -> 220849.88 | Q80: =Q$10*$K80 -> 88339.95 | R80: =R$10*$K80 -> 0 | S80: =S$10*$K80 -> 0 | ... Z80: =Z$10*$K80 -> 0
C81: 3. Construction (Parking) | F81: Parking sqm × rate | G81: 26259 | H81: 2500 | K81: =G81*H81/1000 -> 65647.5 | L81: =L$10*$K81 -> 0 | M81: =M$10*$K81 -> 6564.75 | N81: =N$10*$K81 -> 16411.875 | O81: =O$10*$K81 -> 19694.25 | P81: =P$10*$K81 -> 16411.875 | Q81: =Q$10*$K81 -> 6564.75 | R81: =R$10*$K81 -> 0 | S81: =S$10*$K81 -> 0 | ... Z81: =Z$10*$K81 -> 0
C82: 4. Infrastructure | F82: Land sqm × % × rate | G82: =G75 -> 5718.413 | H82: 3000 | I82: 1 | K82: =G82*H82*I82/1000 -> 17155.239 | L82: =L$11*$K82 -> 0 | M82: =M$11*$K82 -> 1715.5239 | N82: =N$11*$K82 -> 4288.8098 | O82: =O$11*$K82 -> 5146.5717 | P82: =P$11*$K82 -> 4288.8098 | Q82: =Q$11*$K82 -> 1715.5239 | R82: =R$11*$K82 -> 0 | S82: =S$11*$K82 -> 0 | ... Z82: =Z$11*$K82 -> 0
C83: 5. Landscaping | F83: Land sqm × % × rate | G83: =G75 -> 5718.413 | H83: 1700 | I83: 0.36332 | K83: =G83*H83*I83/1000 -> 3531.9435 | L83: =L$12*$K83 -> 0 | M83: =M$12*$K83 -> 353.19435 | N83: =N$12*$K83 -> 882.98587 | O83: =O$12*$K83 -> 1059.583 | P83: =P$12*$K83 -> 882.98587 | Q83: =Q$12*$K83 -> 353.19435 | R83: =R$12*$K83 -> 0 | S83: =S$12*$K83 -> 0 | ... Z83: =Z$12*$K83 -> 0
C84: 6. Pre-operating | F84: % × (Const + Infra + Landscape) | G84: =K80+K81+K82+K83 -> 969734.18 | I84: 0.018 | K84: =G84*I84 -> 17455.215 | L84: =L$13*$K84 -> 0 | M84: =M$13*$K84 -> 1745.5215 | N84: =N$13*$K84 -> 4363.8038 | O84: =O$13*$K84 -> 5236.5646 | P84: =P$13*$K84 -> 4363.8038 | Q84: =Q$13*$K84 -> 1745.5215 | R84: =R$13*$K84 -> 0 | S84: =S$13*$K84 -> 0 | ... Z84: =Z$13*$K84 -> 0
C85: 7. Professional fee | F85: % × Construction (BUA + Parking) | G85: =K80+K81 -> 949047 | I85: 0.15 | K85: =G85*I85 -> 142357.05 | L85: =L$14*$K85 -> 0 | M85: =M$14*$K85 -> 14235.705 | N85: =N$14*$K85 -> 35589.262 | O85: =O$14*$K85 -> 42707.115 | P85: =P$14*$K85 -> 35589.262 | Q85: =Q$14*$K85 -> 14235.705 | R85: =R$14*$K85 -> 0 | S85: =S$14*$K85 -> 0 | ... Z85: =Z$14*$K85 -> 0
C86: 8. Commission fee | F86: % × Pre-sale & Post Operation Revenue | G86: =Revenue!J164+Revenue!J167 -> 2822041 | I86: 0.04 | K86: =G86*I86 -> 112881.64 | L86: =L$15*$K86 -> 0 | M86: =M$15*$K86 -> 11288.164 | N86: =N$15*$K86 -> 28220.41 | O86: =O$15*$K86 -> 33864.493 | P86: =P$15*$K86 -> 28220.41 | Q86: =Q$15*$K86 -> 11288.164 | R86: =R$15*$K86 -> 0 | S86: =S$15*$K86 -> 0 | ... Z86: =Z$15*$K86 -> 0
C87: 9. Contingency fee | F87: % × Construction (BUA + Parking) | G87: =K80+K81 -> 949047 | I87: 0.075 | K87: =G87*I87 -> 71178.525 | L87: =L$16*$K87 -> 0 | M87: =M$16*$K87 -> 7117.8525 | N87: =N$16*$K87 -> 17794.631 | O87: =O$16*$K87 -> 21353.557 | P87: =P$16*$K87 -> 17794.631 | Q87: =Q$16*$K87 -> 7117.8525 | R87: =R$16*$K87 -> 0 | S87: =S$16*$K87 -> 0 | ... Z87: =Z$16*$K87 -> 0
C88: TOTAL CAPEX (T2 & T3) Excl. Land | K88: =SUM(K80:K87) -> 1313606.6 | L88: =SUM(L80:L87) -> 0 | M88: =SUM(M80:M87) -> 131360.66 | N88: =SUM(N80:N87) -> 328401.65 | O88: =SUM(O80:O87) -> 394081.98 | P88: =SUM(P80:P87) -> 328401.65 | Q88: =SUM(Q80:Q87) -> 131360.66 | R88: =SUM(R80:R87) -> 0 | ... Z88: =SUM(Z80:Z87) -> 0
C90: TOTAL CAPEX (T2 & T3) Incl. Land | K90: =SUM(K75,K88) -> 1876587.7 | L90: =SUM(L75,L88) -> 0 | M90: =SUM(M75,M88) -> 694341.78 | N90: =SUM(N75,N88) -> 328401.65 | O90: =SUM(O75,O88) -> 394081.98 | P90: =SUM(P75,P88) -> 328401.65 | Q90: =SUM(Q75,Q88) -> 131360.66 | R90: =SUM(R75,R88) -> 0 | ... Z90: =SUM(Z75,Z88) -> 0
B92: Branded Apartments T4 & T5 - Phase 3 (Residential)
C93: 1. Land cost | F93: Land sqm × rate × active | G93: ='Land Summary'!E37 -> 6813.737 | H93: ='Land Summary'!F37 -> 61722.245 | I93: 1 | K93: =G93*H93*I93/1000 -> 420559.15 | L93: =L$20*$K93 -> 0 | M93: =M$20*$K93 -> 420559.15 | N93: =N$20*$K93 -> 0 | O93: =O$20*$K93 -> 0 | P93: =P$20*$K93 -> 0 | Q93: =Q$20*$K93 -> 0 | R93: =R$20*$K93 -> 0 | S93: =S$20*$K93 -> 0 | ... Z93: =Z$20*$K93 -> 0
C94: 2. Construction (BUA) - by sub-unit
C95: 2.1 Hotel Suite | F95: sqm × rate | G95: 28673 | H95: 6700 | K95: =G95*H95/1000 -> 192109.1
C96: 2.2 1 BR | F96: sqm × rate | G96: 64513 | H96: 6700 | K96: =G96*H96/1000 -> 432237.1
C97: 2.3 2 BR | F97: sqm × rate | G97: 50177 | H97: 6700 | K97: =G97*H97/1000 -> 336185.9
C98: Subtotal Construction (BUA) | G98: =SUM(G95:G97) -> 143363 | K98: =SUM(K95:K97) -> 960532.1 | L98: =L$21*$K98 -> 0 | M98: =M$21*$K98 -> 96053.21 | N98: =N$21*$K98 -> 96053.21 | O98: =O$21*$K98 -> 240133.02 | P98: =P$21*$K98 -> 240133.02 | Q98: =Q$21*$K98 -> 240133.02 | R98: =R$21*$K98 -> 48026.605 | S98: =S$21*$K98 -> 0 | ... Z98: =Z$21*$K98 -> 0
C99: 3. Construction (Parking) | F99: Parking sqm × rate (n/a) | G99: 40236 | H99: 2500 | K99: =G99*H99/1000 -> 100590 | L99: =L$21*$K99 -> 0 | M99: =M$21*$K99 -> 10059 | N99: =N$21*$K99 -> 10059 | O99: =O$21*$K99 -> 25147.5 | P99: =P$21*$K99 -> 25147.5 | Q99: =Q$21*$K99 -> 25147.5 | R99: =R$21*$K99 -> 5029.5 | S99: =S$21*$K99 -> 0 | ... Z99: =Z$21*$K99 -> 0
C100: 4. Infrastructure | F100: Land sqm × % × rate | G100: =G93 -> 6813.737 | H100: 3000 | I100: 1 | K100: =G100*H100*I100/1000 -> 20441.211 | L100: =L$22*$K100 -> 0 | M100: =M$22*$K100 -> 2044.1211 | N100: =N$22*$K100 -> 2044.1211 | O100: =O$22*$K100 -> 5110.3027 | P100: =P$22*$K100 -> 5110.3027 | Q100: =Q$22*$K100 -> 5110.3027 | R100: =R$22*$K100 -> 1022.0606 | S100: =S$22*$K100 -> 0 | ... Z100: =Z$22*$K100 -> 0
C101: 5. Landscaping | F101: Land sqm × % × rate | G101: =G93 -> 6813.737 | H101: 1700 | I101: 0.36029 | K101: =G101*H101*I101/1000 -> 4173.3662 | L101: =L$23*$K101 -> 0 | M101: =M$23*$K101 -> 417.33662 | N101: =N$23*$K101 -> 417.33662 | O101: =O$23*$K101 -> 1043.3416 | P101: =P$23*$K101 -> 1043.3416 | Q101: =Q$23*$K101 -> 1043.3416 | R101: =R$23*$K101 -> 208.66831 | S101: =S$23*$K101 -> 0 | ... Z101: =Z$23*$K101 -> 0
C102: 6. Pre-operating | F102: % × (Const + Infra + Landscape) | G102: =K98+K99+K100+K101 -> 1085736.7 | I102: 0.015 | K102: =G102*I102 -> 16286.05 | L102: =L$24*$K102 -> 0 | M102: =M$24*$K102 -> 1628.605 | N102: =N$24*$K102 -> 1628.605 | O102: =O$24*$K102 -> 4071.5125 | P102: =P$24*$K102 -> 4071.5125 | Q102: =Q$24*$K102 -> 4071.5125 | R102: =R$24*$K102 -> 814.30251 | S102: =S$24*$K102 -> 0 | ... Z102: =Z$24*$K102 -> 0
C103: 7. Professional fee | F103: % × Construction (BUA + Parking) | G103: =K98+K99 -> 1061122.1 | I103: 0.15 | K103: =G103*I103 -> 159168.32 | L103: =L$25*$K103 -> 0 | M103: =M$25*$K103 -> 15916.832 | N103: =N$25*$K103 -> 15916.832 | O103: =O$25*$K103 -> 39792.079 | P103: =P$25*$K103 -> 39792.079 | Q103: =Q$25*$K103 -> 39792.079 | R103: =R$25*$K103 -> 7958.4158 | S103: =S$25*$K103 -> 0 | ... Z103: =Z$25*$K103 -> 0
C104: 8. Commission fee | F104: % × Pre-sale & Post Operation Revenue | G104: =Revenue!J165+Revenue!J168 -> 2658024 | I104: 0.04 | K104: =G104*I104 -> 106320.96 | L104: =L$26*$K104 -> 0 | M104: =M$26*$K104 -> 10632.096 | N104: =N$26*$K104 -> 10632.096 | O104: =O$26*$K104 -> 26580.24 | P104: =P$26*$K104 -> 26580.24 | Q104: =Q$26*$K104 -> 26580.24 | R104: =R$26*$K104 -> 5316.048 | S104: =S$26*$K104 -> 0 | ... Z104: =Z$26*$K104 -> 0
C105: 9. Contingency fee | F105: % × Construction (BUA + Parking) | G105: =K98+K99 -> 1061122.1 | I105: 0.075 | K105: =G105*I105 -> 79584.158 | L105: =L$27*$K105 -> 0 | M105: =M$27*$K105 -> 7958.4158 | N105: =N$27*$K105 -> 7958.4158 | O105: =O$27*$K105 -> 19896.039 | P105: =P$27*$K105 -> 19896.039 | Q105: =Q$27*$K105 -> 19896.039 | R105: =R$27*$K105 -> 3979.2079 | S105: =S$27*$K105 -> 0 | ... Z105: =Z$27*$K105 -> 0
C106: TOTAL CAPEX (T4 & T5) Excl. Land | K106: =SUM(K98:K105) -> 1447096.2 | L106: =SUM(L98:L105) -> 0 | M106: =SUM(M98:M105) -> 144709.62 | N106: =SUM(N98:N105) -> 144709.62 | O106: =SUM(O98:O105) -> 361774.04 | P106: =SUM(P98:P105) -> 361774.04 | Q106: =SUM(Q98:Q105) -> 361774.04 | R106: =SUM(R98:R105) -> 72354.808 | ... Z106: =SUM(Z98:Z105) -> 0
C108: TOTAL CAPEX (T4 & T5) Incl. Land | K108: =SUM(K93,K106) -> 1867655.3 | L108: =SUM(L93,L106) -> 0 | M108: =SUM(M93,M106) -> 565268.76 | N108: =SUM(N93,N106) -> 144709.62 | O108: =SUM(O93,O106) -> 361774.04 | P108: =SUM(P93,P106) -> 361774.04 | Q108: =SUM(Q93,Q106) -> 361774.04 | R108: =SUM(R93,R106) -> 72354.808 | ... Z108: =SUM(Z93,Z106) -> 0
B110: Residential Tower 01 - Phase 2 (Residential)
C111: 1. Land cost | F111: Land sqm × rate × active | G111: ='Land Summary'!E39 -> 2088.9 | H111: ='Land Summary'!F39 -> 98450.587 | I111: 1 | K111: =G111*H111*I111/1000 -> 205653.43 | L111: =L$31*$K111 -> 0 | M111: =M$31*$K111 -> 205653.43 | N111: =N$31*$K111 -> 0 | O111: =O$31*$K111 -> 0 | P111: =P$31*$K111 -> 0 | Q111: =Q$31*$K111 -> 0 | R111: =R$31*$K111 -> 0 | S111: =S$31*$K111 -> 0 | ... Z111: =Z$31*$K111 -> 0
C112: 2. Construction (BUA) - by sub-unit
...

Sheet Sheet1
F2: Capex | G2: Commission
E3: Old | F3: 3591855 | G3: 286749.54
E4: Revised | F4: 3561464.5 | G4: 256359.08
E5: Diff | F5: =F3-F4 -> 30390.455 | G5: =G3-G4 -> 30390.455

Sheet Capex Allocation
B1: MAAD RESIDENTIAL WITH HOTEL - CAPEX | V1: KPMG | W1: 1
B2: All figures in SAR'000 | V2: Management | W2: 2
B3: Asset cost stack (5 assets, sub-units, land), depreciation schedule and variance vs main MAAD model.
F4: Total | H4: 2026 | I4: 2027 | J4: 2028 | K4: 2029 | L4: 2030 | M4: 2031 | N4: =M4+1 -> 2032 | O4: =N4+1 -> 2033 | P4: =O4+1 -> 2034 | Q4: =P4+1 -> 2035 | R4: =Q4+1 -> 2036 | S4: =R4+1 -> 2037 | T4: =S4+1 -> 2038 | U4: =T4+1 -> 2039
B6: Cash Flow Allocation - KPMG
C8: Branded Apartments T2 & T3 - Allocation %
C9: Land | F9: =SUM(H9:U9) -> 1 | H9: 1 | I9: 0 | J9: 0 | K9: 0 | L9: 0 | M9: 0 | N9: 0 | O9: 0 | P9: 0 | Q9: 0 | R9: 0 | S9: 0 | T9: 0 | U9: 0
C10: Construction (BUA + Parking) | F10: =SUM(H10:U10) -> 1 | H10: 0.3 | I10: 0.3 | J10: 0.3 | K10: 0.1 | L10: 0 | M10: 0 | N10: 0 | O10: 0 | P10: 0 | Q10: 0 | R10: 0 | S10: 0 | T10: 0 | U10: 0
C11: Infrastructure | F11: =SUM(H11:U11) -> 1 | H11: 1 | I11: 0 | J11: 0 | K11: 0 | L11: 0 | M11: 0 | N11: 0 | O11: 0 | P11: 0 | Q11: 0 | R11: 0 | S11: 0 | T11: 0 | U11: 0
C12: Landscaping | F12: =SUM(H12:U12) -> 1 | H12: 0 | I12: 0 | J12: 0 | K12: 1 | L12: 0 | M12: 0 | N12: 0 | O12: 0 | P12: 0 | Q12: 0 | R12: 0 | S12: 0 | T12: 0 | U12: 0
C13: Pre-operating | F13: =SUM(H13:U13) -> 1 | H13: 0.311 | I13: 0.294 | J13: 0.294 | K13: 0.101 | L13: 0 | M13: 0 | N13: 0 | O13: 0 | P13: 0 | Q13: 0 | R13: 0 | S13: 0 | T13: 0 | U13: 0
C14: Professional fee | F14: =SUM(H14:U14) -> 1 | H14: 0.3 | I14: 0.3 | J14: 0.3 | K14: 0.1 | L14: 0 | M14: 0 | N14: 0 | O14: 0 | P14: 0 | Q14: 0 | R14: 0 | S14: 0 | T14: 0 | U14: 0
C15: Commission | F15: =SUM(H15:U15) -> 1 | H15: 0.048 | I15: 0.292 | J15: 0.3 | K15: 0.256 | L15: 0.104 | M15: 0 | N15: 0 | O15: 0 | P15: 0 | Q15: 0 | R15: 0 | S15: 0 | T15: 0 | U15: 0
C16: Contingency | F16: =SUM(H16:U16) -> 1 | H16: 0.3 | I16: 0.3 | J16: 0.3 | K16: 0.1 | L16: 0 | M16: 0 | N16: 0 | O16: 0 | P16: 0 | Q16: 0 | R16: 0 | S16: 0 | T16: 0 | U16: 0
C18: Branded Apartments T4 & T5 - Allocation %
C19: Land | F19: =SUM(H19:U19) -> 1 | H19: 1 | I19: 0 | J19: 0 | K19: 0 | L19: 0 | M19: 0 | N19: 0 | O19: 0 | P19: 0 | Q19: 0 | R19: 0 | S19: 0 | T19: 0 | U19: 0
C20: Construction (BUA + Parking) | F20: =SUM(H20:U20) -> 1 | H20: 0.3 | I20: 0.3 | J20: 0.3 | K20: 0.1 | L20: 0 | M20: 0 | N20: 0 | O20: 0 | P20: 0 | Q20: 0 | R20: 0 | S20: 0 | T20: 0 | U20: 0
C21: Infrastructure | F21: =SUM(H21:U21) -> 1 | H21: 1 | I21: 0 | J21: 0 | K21: 0 | L21: 0 | M21: 0 | N21: 0 | O21: 0 | P21: 0 | Q21: 0 | R21: 0 | S21: 0 | T21: 0 | U21: 0
C22: Landscaping | F22: =SUM(H22:U22) -> 1 | H22: 0 | I22: 0 | J22: 0 | K22: 1 | L22: 0 | M22: 0 | N22: 0 | O22: 0 | P22: 0 | Q22: 0 | R22: 0 | S22: 0 | T22: 0 | U22: 0
C23: Pre-operating | F23: =SUM(H23:U23) -> 1 | H23: 0.312 | I23: 0.293 | J23: 0.293 | K23: 0.102 | L23: 0 | M23: 0 | N23: 0 | O23: 0 | P23: 0 | Q23: 0 | R23: 0 | S23: 0 | T23: 0 | U23: 0
C24: Professional fee | F24: =SUM(H24:U24) -> 1 | H24: 0.3 | I24: 0.3 | J24: 0.3 | K24: 0.1 | L24: 0 | M24: 0 | N24: 0 | O24: 0 | P24: 0 | Q24: 0 | R24: 0 | S24: 0 | T24: 0 | U24: 0
C25: Commission | F25: =SUM(H25:U25) -> 1 | H25: 0 | I25: 0.191 | J25: 0.196 | K25: 0.2 | L25: 0.308 | M25: 0.105 | N25: 0 | O25: 0 | P25: 0 | Q25: 0 | R25: 0 | S25: 0 | T25: 0 | U25: 0
C26: Contingency | F26: =SUM(H26:U26) -> 1 | H26: 0.3 | I26: 0.3 | J26: 0.3 | K26: 0.1 | L26: 0 | M26: 0 | N26: 0 | O26: 0 | P26: 0 | Q26: 0 | R26: 0 | S26: 0 | T26: 0 | U26: 0
C28: Residential Tower 01 - Allocation %
C29: Land | F29: =SUM(H29:U29) -> 1 | H29: 1 | I29: 0 | J29: 0 | K29: 0 | L29: 0 | M29: 0 | N29: 0 | O29: 0 | P29: 0 | Q29: 0 | R29: 0 | S29: 0 | T29: 0 | U29: 0
C30: Construction (BUA + Parking) | F30: =SUM(H30:U30) -> 1 | H30: 0.3 | I30: 0.3 | J30: 0.3 | K30: 0.1 | L30: 0 | M30: 0 | N30: 0 | O30: 0 | P30: 0 | Q30: 0 | R30: 0 | S30: 0 | T30: 0 | U30: 0
C31: Infrastructure | F31: =SUM(H31:U31) -> 1 | H31: 1 | I31: 0 | J31: 0 | K31: 0 | L31: 0 | M31: 0 | N31: 0 | O31: 0 | P31: 0 | Q31: 0 | R31: 0 | S31: 0 | T31: 0 | U31: 0
C32: Landscaping | F32: =SUM(H32:U32) -> 1 | H32: 0 | I32: 0 | J32: 0 | K32: 1 | L32: 0 | M32: 0 | N32: 0 | O32: 0 | P32: 0 | Q32: 0 | R32: 0 | S32: 0 | T32: 0 | U32: 0
C33: Pre-operating | F33: =SUM(H33:U33) -> 1 | H33: 0.312 | I33: 0.293 | J33: 0.293 | K33: 0.102 | L33: 0 | M33: 0 | N33: 0 | O33: 0 | P33: 0 | Q33: 0 | R33: 0 | S33: 0 | T33: 0 | U33: 0
C34: Professional fee | F34: =SUM(H34:U34) -> 1 | H34: 0.3 | I34: 0.3 | J34: 0.3 | K34: 0.1 | L34: 0 | M34: 0 | N34: 0 | O34: 0 | P34: 0 | Q34: 0 | R34: 0 | S34: 0 | T34: 0 | U34: 0
C35: Commission | F35: =SUM(H35:U35) -> 1 | H35: 0.048 | I35: 0.291 | J35: 0.299 | K35: 0.258 | L35: 0.104 | M35: 0 | N35: 0 | O35: 0 | P35: 0 | Q35: 0 | R35: 0 | S35: 0 | T35: 0 | U35: 0
C36: Contingency | F36: =SUM(H36:U36) -> 1 | H36: 0.3 | I36: 0.3 | J36: 0.3 | K36: 0.1 | L36: 0 | M36: 0 | N36: 0 | O36: 0 | P36: 0 | Q36: 0 | R36: 0 | S36: 0 | T36: 0 | U36: 0
C38: Hotel 01 - 336 Keys - Allocation %
C39: Land | F39: =SUM(H39:U39) -> 1 | H39: 1 | I39: 0 | J39: 0 | K39: 0 | L39: 0 | M39: 0 | N39: 0 | O39: 0 | P39: 0 | Q39: 0 | R39: 0 | S39: 0 | T39: 0 | U39: 0
C40: Construction (BUA + Parking) | F40: =SUM(H40:U40) -> 1 | H40: 0.3 | I40: 0.3 | J40: 0.3 | K40: 0.1 | L40: 0 | M40: 0 | N40: 0 | O40: 0 | P40: 0 | Q40: 0 | R40: 0 | S40: 0 | T40: 0 | U40: 0
C41: Infrastructure | F41: =SUM(H41:U41) -> 1 | H41: 1 | I41: 0 | J41: 0 | K41: 0 | L41: 0 | M41: 0 | N41: 0 | O41: 0 | P41: 0 | Q41: 0 | R41: 0 | S41: 0 | T41: 0 | U41: 0
C42: Landscaping | F42: =SUM(H42:U42) -> 1 | H42: 0 | I42: 0 | J42: 0 | K42: 1 | L42: 0 | M42: 0 | N42: 0 | O42: 0 | P42: 0 | Q42: 0 | R42: 0 | S42: 0 | T42: 0 | U42: 0
C43: Pre-operating | F43: =SUM(H43:U43) -> 1 | H43: 0.31 | I43: 0.294 | J43: 0.294 | K43: 0.102 | L43: 0 | M43: 0 | N43: 0 | O43: 0 | P43: 0 | Q43: 0 | R43: 0 | S43: 0 | T43: 0 | U43: 0
C44: Professional fee | F44: =SUM(H44:U44) -> 1 | H44: 0.3 | I44: 0.3 | J44: 0.3 | K44: 0.1 | L44: 0 | M44: 0 | N44: 0 | O44: 0 | P44: 0 | Q44: 0 | R44: 0 | S44: 0 | T44: 0 | U44: 0
C45: Commission | F45: =SUM(H45:U45) -> 1 | H45: 1 | I45: 0 | J45: 0 | K45: 0 | L45: 0 | M45: 0 | N45: 0 | O45: 0 | P45: 0 | Q45: 0 | R45: 0 | S45: 0 | T45: 0 | U45: 0
C46: Contingency | F46: =SUM(H46:U46) -> 1 | H46: 0.3 | I46: 0.3 | J46: 0.3 | K46: 0.1 | L46: 0 | M46: 0 | N46: 0 | O46: 0 | P46: 0 | Q46: 0 | R46: 0 | S46: 0 | T46: 0 | U46: 0
C48: Support Retail (P2) - Allocation %
C49: Land | F49: =SUM(H49:U49) -> 1 | H49: 1 | I49: 0 | J49: 0 | K49: 0 | L49: 0 | M49: 0 | N49: 0 | O49: 0 | P49: 0 | Q49: 0 | R49: 0 | S49: 0 | T49: 0 | U49: 0
C50: Construction (BUA + Parking) | F50: =SUM(H50:U50) -> 1 | H50: 0.3 | I50: 0.3 | J50: 0.3 | K50: 0.1 | L50: 0 | M50: 0 | N50: 0 | O50: 0 | P50: 0 | Q50: 0 | R50: 0 | S50: 0 | T50: 0 | U50: 0
C51: Infrastructure | F51: =SUM(H51:U51) -> 1 | H51: 1 | I51: 0 | J51: 0 | K51: 0 | L51: 0 | M51: 0 | N51: 0 | O51: 0 | P51: 0 | Q51: 0 | R51: 0 | S51: 0 | T51: 0 | U51: 0
C52: Landscaping | F52: =SUM(H52:U52) -> 1 | H52: 0 | I52: 0 | J52: 0 | K52: 1 | L52: 0 | M52: 0 | N52: 0 | O52: 0 | P52: 0 | Q52: 0 | R52: 0 | S52: 0 | T52: 0 | U52: 0
C53: Pre-operating | F53: =SUM(H53:U53) -> 1 | H53: 0.315 | I53: 0.292 | J53: 0.292 | K53: 0.101 | L53: 0 | M53: 0 | N53: 0 | O53: 0 | P53: 0 | Q53: 0 | R53: 0 | S53: 0 | T53: 0 | U53: 0
C54: Professional fee | F54: =SUM(H54:U54) -> 1 | H54: 0.3 | I54: 0.3 | J54: 0.3 | K54: 0.1 | L54: 0 | M54: 0 | N54: 0 | O54: 0 | P54: 0 | Q54: 0 | R54: 0 | S54: 0 | T54: 0 | U54: 0
C55: Commission | F55: =SUM(H55:U55) -> 1 | H55: 1 | I55: 0 | J55: 0 | K55: 0 | L55: 0 | M55: 0 | N55: 0 | O55: 0 | P55: 0 | Q55: 0 | R55: 0 | S55: 0 | T55: 0 | U55: 0
C56: Contingency | F56: =SUM(H56:U56) -> 1 | H56: 0.3 | I56: 0.3 | J56: 0.3 | K56: 0.1 | L56: 0 | M56: 0 | N56: 0 | O56: 0 | P56: 0 | Q56: 0 | R56: 0 | S56: 0 | T56: 0 | U56: 0
C58: Support Retail (P2) - Allocation %
C59: Land | F59: =SUM(H59:U59) -> 1 | H59: 1 | I59: 0 | J59: 0 | K59: 0 | L59: 0 | M59: 0 | N59: 0 | O59: 0 | P59: 0 | Q59: 0 | R59: 0 | S59: 0 | T59: 0 | U59: 0
C60: Construction (BUA + Parking) | F60: =SUM(H60:U60) -> 1 | H60: 0.3 | I60: 0.3 | J60: 0.3 | K60: 0.1 | L60: 0 | M60: 0 | N60: 0 | O60: 0 | P60: 0 | Q60: 0 | R60: 0 | S60: 0 | T60: 0 | U60: 0
C61: Infrastructure | F61: =SUM(H61:U61) -> 1 | H61: 1 | I61: 0 | J61: 0 | K61: 0 | L61: 0 | M61: 0 | N61: 0 | O61: 0 | P61: 0 | Q61: 0 | R61: 0 | S61: 0 | T61: 0 | U61: 0
C62: Landscaping | F62: =SUM(H62:U62) -> 1 | H62: 0 | I62: 0 | J62: 0 | K62: 1 | L62: 0 | M62: 0 | N62: 0 | O62: 0 | P62: 0 | Q62: 0 | R62: 0 | S62: 0 | T62: 0 | U62: 0
C63: Pre-operating | F63: =SUM(H63:U63) -> 1 | H63: 0.315 | I63: 0.292 | J63: 0.292 | K63: 0.101 | L63: 0 | M63: 0 | N63: 0 | O63: 0 | P63: 0 | Q63: 0 | R63: 0 | S63: 0 | T63: 0 | U63: 0
C64: Professional fee | F64: =SUM(H64:U64) -> 1 | H64: 0.3 | I64: 0.3 | J64: 0.3 | K64: 0.1 | L64: 0 | M64: 0 | N64: 0 | O64: 0 | P64: 0 | Q64: 0 | R64: 0 | S64: 0 | T64: 0 | U64: 0
C65: Commission | F65: =SUM(H65:U65) -> 1 | H65: 1 | I65: 0 | J65: 0 | K65: 0 | L65: 0 | M65: 0 | N65: 0 | O65: 0 | P65: 0 | Q65: 0 | R65: 0 | S65: 0 | T65: 0 | U65: 0
C66: Contingency | F66: =SUM(H66:U66) -> 1 | H66: 0.3 | I66: 0.3 | J66: 0.3 | K66: 0.1 | L66: 0 | M66: 0 | N66: 0 | O66: 0 | P66: 0 | Q66: 0 | R66: 0 | S66: 0 | T66: 0 | U66: 0
B68: Cash Flow Allocation - Management
C70: Branded Apartments T2 & T3 - Allocation %
C71: Land | F71: =SUM(H71:U71) -> 1 | H71: 1 | I71: 0 | J71: 0 | K71: 0 | L71: 0 | M71: 0 | O71: 0 | P71: 0 | Q71: 0 | R71: 0 | S71: 0 | T71: 0 | U71: 0
C72: Construction (BUA + Parking) | F72: =SUM(H72:U72) -> 1 | H72: 0.1 | I72: 0.25 | J72: 0.3 | K72: 0.25 | L72: 0.1 | M72: 0 | O72: 0 | P72: 0 | Q72: 0 | R72: 0 | S72: 0 | T72: 0 | U72: 0
C73: Infrastructure | F73: =SUM(H73:U73) -> 1 | H73: 0.1 | I73: 0.25 | J73: 0.3 | K73: 0.25 | L73: 0.1 | M73: 0 | O73: 0 | P73: 0 | Q73: 0 | R73: 0 | S73: 0 | T73: 0 | U73: 0
C74: Landscaping | F74: =SUM(H74:U74) -> 1 | H74: 0.1 | I74: 0.25 | J74: 0.3 | K74: 0.25 | L74: 0.1 | M74: 0 | O74: 0 | P74: 0 | Q74: 0 | R74: 0 | S74: 0 | T74: 0 | U74: 0
C75: Pre-operating | F75: =SUM(H75:U75) -> 1 | H75: 0.1 | I75: 0.25 | J75: 0.3 | K75: 0.25 | L75: 0.1 | M75: 0 | O75: 0 | P75: 0 | Q75: 0 | R75: 0 | S75: 0 | T75: 0 | U75: 0
C76: Professional fee | F76: =SUM(H76:U76) -> 1 | H76: 0.1 | I76: 0.25 | J76: 0.3 | K76: 0.25 | L76: 0.1 | M76: 0 | O76: 0 | P76: 0 | Q76: 0 | R76: 0 | S76: 0 | T76: 0 | U76: 0
C77: Commission | F77: =SUM(H77:U77) -> 1 | H77: 0.1 | I77: 0.25 | J77: 0.3 | K77: 0.25 | L77: 0.1 | M77: 0 | O77: 0 | P77: 0 | Q77: 0 | R77: 0 | S77: 0 | T77: 0 | U77: 0
C78: Contingency | F78: =SUM(H78:U78) -> 1 | H78: 0.1 | I78: 0.25 | J78: 0.3 | K78: 0.25 | L78: 0.1 | M78: 0 | O78: 0 | P78: 0 | Q78: 0 | R78: 0 | S78: 0 | T78: 0 | U78: 0
C80: Branded Apartments T4 & T5 - Allocation %
C81: Land | F81: =SUM(H81:U81) -> 1 | H81: 1 | I81: 0 | J81: 0 | K81: 0 | L81: 0 | M81: 0 | N81: 0 | O81: 0 | P81: 0 | Q81: 0 | R81: 0 | S81: 0 | T81: 0 | U81: 0
C82: Construction (BUA + Parking) | F82: =SUM(H82:U82) -> 1 | H82: 0.1 | I82: 0.1 | J82: 0.25 | K82: 0.25 | L82: 0.25 | M82: 0.05 | N82: 0 | O82: 0 | P82: 0 | Q82: 0 | R82: 0 | S82: 0 | T82: 0 | U82: 0
C83: Infrastructure | F83: =SUM(H83:U83) -> 1 | H83: 0.1 | I83: 0.1 | J83: 0.25 | K83: 0.25 | L83: 0.25 | M83: 0.05 | N83: 0 | O83: 0 | P83: 0 | Q83: 0 | R83: 0 | S83: 0 | T83: 0 | U83: 0
C84: Landscaping | F84: =SUM(H84:U84) -> 1 | H84: 0.1 | I84: 0.1 | J84: 0.25 | K84: 0.25 | L84: 0.25 | M84: 0.05 | N84: 0 | O84: 0 | P84: 0 | Q84: 0 | R84: 0 | S84: 0 | T84: 0 | U84: 0
C85: Pre-operating | F85: =SUM(H85:U85) -> 1 | H85: 0.1 | I85: 0.1 | J85: 0.25 | K85: 0.25 | L85: 0.25 | M85: 0.05 | N85: 0 | O85: 0 | P85: 0 | Q85: 0 | R85: 0 | S85: 0 | T85: 0 | U85: 0
C86: Professional fee | F86: =SUM(H86:U86) -> 1 | H86: 0.1 | I86: 0.1 | J86: 0.25 | K86: 0.25 | L86: 0.25 | M86: 0.05 | N86: 0 | O86: 0 | P86: 0 | Q86: 0 | R86: 0 | S86: 0 | T86: 0 | U86: 0
C87: Commission | F87: =SUM(H87:U87) -> 1 | H87: 0.1 | I87: 0.1 | J87: 0.25 | K87: 0.25 | L87: 0.25 | M87: 0.05 | N87: 0 | O87: 0 | P87: 0 | Q87: 0 | R87: 0 | S87: 0 | T87: 0 | U87: 0
C88: Contingency | F88: =SUM(H88:U88) -> 1 | H88: 0.1 | I88: 0.1 | J88: 0.25 | K88: 0.25 | L88: 0.25 | M88: 0.05 | N88: 0 | O88: 0 | P88: 0 | Q88: 0 | R88: 0 | S88: 0 | T88: 0 | U88: 0
C90: Residential Tower 01 - Allocation %
C91: Land | F91: =SUM(H91:U91) -> 1 | H91: 1 | I91: 0 | J91: 0 | K91: 0 | L91: 0 | M91: 0 | N91: 0 | O91: 0 | P91: 0 | Q91: 0 | R91: 0 | S91: 0 | T91: 0 | U91: 0
C92: Construction (BUA + Parking) | F92: =SUM(H92:U92) -> 1 | H92: 0.1 | I92: 0.25 | J92: 0.3 | K92: 0.25 | L92: 0.1 | M92: 0 | N92: 0 | O92: 0 | P92: 0 | Q92: 0 | R92: 0 | S92: 0 | T92: 0 | U92: 0
C93: Infrastructure | F93: =SUM(H93:U93) -> 1 | H93: 0.1 | I93: 0.25 | J93: 0.3 | K93: 0.25 | L93: 0.1 | M93: 0 | N93: 0 | O93: 0 | P93: 0 | Q93: 0 | R93: 0 | S93: 0 | T93: 0 | U93: 0
C94: Landscaping | F94: =SUM(H94:U94) -> 1 | H94: 0.1 | I94: 0.25 | J94: 0.3 | K94: 0.25 | L94: 0.1 | M94: 0 | N94: 0 | O94: 0 | P94: 0 | Q94: 0 | R94: 0 | S94: 0 | T94: 0 | U94: 0
C95: Pre-operating | F95: =SUM(H95:U95) -> 1 | H95: 0.1 | I95: 0.25 | J95: 0.3 | K95: 0.25 | L95: 0.1 | M95: 0 | N95: 0 | O95: 0 | P95: 0 | Q95: 0 | R95: 0 | S95: 0 | T95: 0 | U95: 0
C96: Professional fee | F96: =SUM(H96:U96) -> 1 | H96: 0.1 | I96: 0.25 | J96: 0.3 | K96: 0.25 | L96: 0.1 | M96: 0 | N96: 0 | O96: 0 | P96: 0 | Q96: 0 | R96: 0 | S96: 0 | T96: 0 | U96: 0
C97: Commission | F97: =SUM(H97:U97) -> 1 | H97: 0.1 | I97: 0.25 | J97: 0.3 | K97: 0.25 | L97: 0.1 | M97: 0 | N97: 0 | O97: 0 | P97: 0 | Q97: 0 | R97: 0 | S97: 0 | T97: 0 | U97: 0
C98: Contingency | F98: =SUM(H98:U98) -> 1 | H98: 0.1 | I98: 0.25 | J98: 0.3 | K98: 0.25 | L98: 0.1 | M98: 0 | N98: 0 | O98: 0 | P98: 0 | Q98: 0 | R98: 0 | S98: 0 | T98: 0 | U98: 0
C100: Hotel 01 - 336 Keys - Allocation %
C101: Land | F101: =SUM(H101:U101) -> 1 | H101: 1 | I101: 0 | J101: 0 | K101: 0 | L101: 0 | M101: 0 | N101: 0 | O101: 0 | P101: 0 | Q101: 0 | R101: 0 | S101: 0 | T101: 0 | U101: 0
C102: Construction (BUA + Parking) | F102: =SUM(H102:U102) -> 1 | H102: 0.1 | I102: 0.25 | J102: 0.3 | K102: 0.25 | L102: 0.1 | M102: 0 | N102: 0 | O102: 0 | P102: 0 | Q102: 0 | R102: 0 | S102: 0 | T102: 0 | U102: 0
C103: Infrastructure | F103: =SUM(H103:U103) -> 1 | H103: 0.1 | I103: 0.25 | J103: 0.3 | K103: 0.25 | L103: 0.1 | M103: 0 | N103: 0 | O103: 0 | P103: 0 | Q103: 0 | R103: 0 | S103: 0 | T103: 0 | U103: 0
C104: Landscaping | F104: =SUM(H104:U104) -> 1 | H104: 0.1 | I104: 0.25 | J104: 0.3 | K104: 0.25 | L104: 0.1 | M104: 0 | N104: 0 | O104: 0 | P104: 0 | Q104: 0 | R104: 0 | S104: 0 | T104: 0 | U104: 0
C105: Pre-operating | F105: =SUM(H105:U105) -> 1 | H105: 0.1 | I105: 0.25 | J105: 0.3 | K105: 0.25 | L105: 0.1 | M105: 0 | N105: 0 | O105: 0 | P105: 0 | Q105: 0 | R105: 0 | S105: 0 | T105: 0 | U105: 0
C106: Professional fee | F106: =SUM(H106:U106) -> 1 | H106: 0.1 | I106: 0.25 | J106: 0.3 | K106: 0.25 | L106: 0.1 | M106: 0 | N106: 0 | O106: 0 | P106: 0 | Q106: 0 | R106: 0 | S106: 0 | T106: 0 | U106: 0
C107: Commission | F107: =SUM(H107:U107) -> 1 | H107: 0.1 | I107: 0.25 | J107: 0.3 | K107: 0.25 | L107: 0.1 | M107: 0 | N107: 0 | O107: 0 | P107: 0 | Q107: 0 | R107: 0 | S107: 0 | T107: 0 | U107: 0
C108: Contingency | F108: =SUM(H108:U108) -> 1 | H108: 0.1 | I108: 0.25 | J108: 0.3 | K108: 0.25 | L108: 0.1 | M108: 0 | N108: 0 | O108: 0 | P108: 0 | Q108: 0 | R108: 0 | S108: 0 | T108: 0 | U108: 0
C110: Support Retail (P2) - Allocation %
C111: Land | F111: =SUM(H111:U111) -> 1 | H111: 1 | I111: 0 | J111: 0 | K111: 0 | L111: 0 | M111: 0 | N111: 0 | O111: 0 | P111: 0 | Q111: 0 | R111: 0 | S111: 0 | T111: 0 | U111: 0
C112: Construction (BUA + Parking) | F112: =SUM(H112:U112) -> 1 | H112: 0.1 | I112: 0.25 | J112: 0.3 | K112: 0.25 | L112: 0.1 | M112: 0 | N112: 0 | O112: 0 | P112: 0 | Q112: 0 | R112: 0 | S112: 0 | T112: 0 | U112: 0
A113: * | C113: Infrastructure | F113: =SUM(H113:U113) -> 1 | H113: 0.1 | I113: 0.25 | J113: 0.3 | K113: 0.25 | L113: 0.1 | M113: 0 | N113: 0 | O113: 0 | P113: 0 | Q113: 0 | R113: 0 | S113: 0 | T113: 0 | U113: 0
...

Sheet Debt
B1: MAAD RESIDENTIAL WITH HOTEL - DEBT SCHEDULE
B2: All figures in SAR'000
B3: T1 (SNB Phase 1) + T2 (Phase 2 & 3 capex-driven) debt facilities with interest, fees and capitalised IDC.
C4: DESCRIPTION | D4: Phase | E4: UOM | F4: Total | G4: Unit / Note | H4: 2025 | I4: =H4+1 -> 2026 | J4: =I4+1 -> 2027 | K4: =J4+1 -> 2028 | L4: =K4+1 -> 2029 | M4: =L4+1 -> 2030 | N4: =M4+1 -> 2031 | O4: =N4+1 -> 2032 | P4: =O4+1 -> 2033 | ... V4: =U4+1 -> 2039
B6: ASSUMPTIONS & INPUTS | F6: Value | G6: Unit / Note
C7: Minimum Cash | E7: SAR'000 | F7: 50000
C8: Tranche 1 - SNB Phase 1 (Start-Forward)
C9: Total Land Value | E9: SAR'000 | F9: 2408189
C10: Land Value Phase 2 &3 | E10: SAR'000 | F10: =Capex!$K$210 -> 1350681.9
C11: Land Value Phase 1 | F11: =F9-F10 -> 1057507.1
C12: Pre-Capex Voco | F12: 2624544
C13: Total Pre-Capex Voco | E13: SAR'000 | F13: =SUM(F11:F12) -> 3682051
C14: Pre-Equity Phase 1 | E14: SAR'000 | F14: =F13-F15 -> 1282051
C15: Facility size | E15: SAR'000 | F15: 2400000 | G15: SAR'000 (= 2.4 Bn). Hardcoded drawdown - NOT capex-driven.
C16: Interest rate - operating | E16: % | F16: 0.063 | G16: Per annum
C17: Interest Start | E17: Year | F17: 2026
C18: Tenor | E18: Years | F18: 7 | G18: Years
C19: Drawdown year | E19: Year | F19: 2025 | G19: Year fully drawn (start-forward)
C20: Repayment method | F20: Manual % schedule | G20: From SNB Repayment_V8_NEW (14/04/2026)
C21: Repayment Schedule | E21: % | F21: =SUM(H21:U21) -> 1 | H21: 0 | I21: 0 | J21: 0 | K21: 0.059985706 | L21: 0.066427344 | M21: 0.073810236 | N21: 0.081647406 | O21: 0.47391464 | P21: =1-SUM(H21:O21) -> 0.24421467 | Q21: 0 | R21: 0 | S21: 0 | T21: 0 | U21: 0 | V21: 0
C23: Tranche 2 - Inputs & drivers
C24: Debt Portion | E24: % | F24: 1
C25: Equity Portion | E25: % | F25: =1-F24 -> 0
C26: Interest rate during construction | E26: % | F26: 0.063
C27: Interest rate during operations | E27: % | F27: 0.063
C28: Upfront fee % of facility | E28: % | F28: 0.01
C29: Repayment start year | E29: % | F29: 2028
C30: Repayment Schedule | F30: =SUM(H30:V30) -> 1 | H30: 0 | I30: 0 | J30: 0 | K30: 0.038392147 | L30: 0.054815396 | M30: 0.059982694 | N30: 0.066424008 | O30: 0.07380653 | P30: 0.081643306 | Q30: =1-SUM(H30:P30) -> 0.62493592 | R30: 0 | S30: 0 | T30: 0 | U30: 0 | V30: 0
B32: Funding Phase 1
C34: TRANCHE 1 - SNB Phase 1 Loan
C35: Opening balance | H35: 0 | I35: =H38 -> 2400000 | J35: =I38 -> 2400000 | K35: =J38 -> 2400000 | L35: =K38 -> 2256034.3 | M35: =L38 -> 2096608.7 | N35: =M38 -> 1919464.1 | O35: =N38 -> 1723510.3 | P35: =O38 -> 586115.21 | ... V35: =U38 -> 0
C36: + Drawdown | F36: =SUM(H36:U36) -> 2400000 | H36: =IF(H$4=$F$19,$F$15,0) -> 2400000 | I36: =IF(I$4=$F$19,$F$15,0) -> 0 | J36: =IF(J$4=$F$19,$F$15,0) -> 0 | K36: =IF(K$4=$F$19,$F$15,0) -> 0 | L36: =IF(L$4=$F$19,$F$15,0) -> 0 | M36: =IF(M$4=$F$19,$F$15,0) -> 0 | N36: =IF(N$4=$F$19,$F$15,0) -> 0 | O36: =IF(O$4=$F$19,$F$15,0) -> 0 | ... V36: =IF(V$4=$F$19,$F$15,0) -> 0
C37: − Repayment | F37: =SUM(H37:U37) -> -2400000 | H37: =-MIN(H35+H36, $F$15*H21) -> 0 | I37: =-MIN(I35+I36, $F$15*I21) -> 0 | J37: =-MIN(J35+J36, $F$15*J21) -> 0 | K37: =-MIN(K35+K36, $F$15*K21) -> -143965.69 | L37: =-MIN(L35+L36, $F$15*L21) -> -159425.62 | M37: =-MIN(M35+M36, $F$15*M21) -> -177144.57 | N37: =-MIN(N35+N36, $F$15*N21) -> -195953.77 | O37: =-MIN(O35+O36, $F$15*O21) -> -1137395.1 | ... V37: =-MIN(V35+V36, $F$15*V21) -> 0
C38: Closing balance | H38: =IF(SUM(H35:H37)<1,0,SUM(H35:H37)) -> 2400000 | I38: =IF(SUM(I35:I37)<1,0,SUM(I35:I37)) -> 2400000 | J38: =IF(SUM(J35:J37)<1,0,SUM(J35:J37)) -> 2400000 | K38: =IF(SUM(K35:K37)<1,0,SUM(K35:K37)) -> 2256034.3 | L38: =IF(SUM(L35:L37)<1,0,SUM(L35:L37)) -> 2096608.7 | M38: =IF(SUM(M35:M37)<1,0,SUM(M35:M37)) -> 1919464.1 | N38: =IF(SUM(N35:N37)<1,0,SUM(N35:N37)) -> 1723510.3 | O38: =IF(SUM(O35:O37)<1,0,SUM(O35:O37)) -> 586115.21 | ... V38: =IF(SUM(V35:V37)<1,0,SUM(V35:V37)) -> 0
C40: Interest Expense | F40: =SUM(H40:U40) -> 994249.16 | H40: =IF(H4>=F17,(H35+H36)*$F$16,0) -> 0 | I40: =IF(I4>=G17,(I35+I36)*$F$16,0) -> 151200 | J40: =IF(J4>=H17,(J35+J36)*$F$16,0) -> 151200 | K40: =IF(K4>=I17,(K35+K36)*$F$16,0) -> 151200 | L40: =IF(L4>=J17,(L35+L36)*$F$16,0) -> 142130.16 | M40: =IF(M4>=K17,(M35+M36)*$F$16,0) -> 132086.35 | N40: =IF(N4>=L17,(N35+N36)*$F$16,0) -> 120926.24 | O40: =IF(O4>=M17,(O35+O36)*$F$16,0) -> 108581.15 | ... V40: =IF(V4>=T17,(V35+V36)*$F$16,0) -> 0
B42: Equity Funding Phase 1
C43: EQUITY CONTRIBUTION SCHEDULE
C45: BALANCE SCHEDULE
C46: Opening Balance | F46: =H46 -> 0 | H46: =G48 -> 0 | I46: =H48 -> 1282051 | J46: =I48 -> 1282051 | K46: =J48 -> 1282051 | L46: =K48 -> 1282051 | M46: =L48 -> 1282051 | N46: =M48 -> 1282051 | O46: =N48 -> 1282051 | ... V46: =U48 -> 1282051
C47: + Contribution | F47: =SUM(H47:V47) -> 1282051 | H47: =IF(H$4=$F$19,F14,0) -> 1282051 | I47: =IF(I$4=$F$19,G13,0) -> 0 | J47: =IF(J$4=$F$19,H13,0) -> 0 | K47: =IF(K$4=$F$19,I13,0) -> 0 | L47: =IF(L$4=$F$19,J13,0) -> 0 | M47: =IF(M$4=$F$19,K13,0) -> 0 | N47: =IF(N$4=$F$19,L13,0) -> 0 | O47: =IF(O$4=$F$19,M13,0) -> 0 | P47: =IF(P$4=$F$19,N13,0) -> 0 | ... V47: =IF(V$4=$F$19,T13,0) -> 0
C48: Closing Balance | H48: =SUM(H46:H47) -> 1282051 | I48: =SUM(I46:I47) -> 1282051 | J48: =SUM(J46:J47) -> 1282051 | K48: =SUM(K46:K47) -> 1282051 | L48: =SUM(L46:L47) -> 1282051 | M48: =SUM(M46:M47) -> 1282051 | N48: =SUM(N46:N47) -> 1282051 | O48: =SUM(O46:O47) -> 1282051 | ... V48: =SUM(V46:V47) -> 1282051
B50: TRANCHE 2 - Phase 2 & 3 Funding
C52: Total project capex (source MAAD R143) | F52: =SUM(H52:U52) -> 3561464.5 | H52: =Capex!L197 -> 0 | I52: =Capex!M197 -> 356146.45 | J52: =Capex!N197 -> 673301.7 | K52: =Capex!O197 -> 996084.54 | L52: =Capex!P197 -> 890366.12 | M52: =Capex!Q197 -> 573210.87 | N52: =Capex!R197 -> 72354.808 | O52: =Capex!S197 -> 0 | ... U52: =Capex!Y197 -> 0
C53: Advance received from customer (gross) | F53: =SUM(H53:U53) -> 4973234.7 | H53: =SUM(Revenue!L16:L18) -> 0 | I53: =SUM(Revenue!M16:M18) -> 37769.536 | J53: =SUM(Revenue!N16:N18) -> 725615.39 | K53: =SUM(Revenue!O16:O18) -> 1719744.3 | L53: =SUM(Revenue!P16:P18) -> 2002224.2 | M53: =SUM(Revenue!Q16:Q18) -> 408141.43 | N53: =SUM(Revenue!R16:R18) -> 79739.85 | O53: =SUM(Revenue!S16:S18) -> 0 | ... V53: =SUM(Revenue!Z16:Z18) -> 0
C54: Less: Inaccessible Funds Locked (Wafi) | F54: =SUM(H54:U54) -> -195739.79 | H54: ='Wafi Escrow'!G32 -> 0 | I54: ='Wafi Escrow'!H32 -> -1510.7814 | J54: ='Wafi Escrow'!I32 -> -29024.615 | K54: ='Wafi Escrow'!J32 -> -68789.773 | L54: ='Wafi Escrow'!K32 -> -80088.967 | M54: ='Wafi Escrow'!L32 -> -16325.657 | N54: ='Wafi Escrow'!M32 -> 0 | O54: ='Wafi Escrow'!N32 -> 0 | ... V54: ='Wafi Escrow'!U32 -> 0
C55: Add: Release of Inaccessible Funds (Wafi) | F55: =SUM(H55:U55) -> 195739.79 | H55: ='Wafi Escrow'!G33 -> 0 | I55: ='Wafi Escrow'!H33 -> 0 | J55: ='Wafi Escrow'!I33 -> 0 | K55: ='Wafi Escrow'!J33 -> 0 | L55: ='Wafi Escrow'!K33 -> 0 | M55: ='Wafi Escrow'!L33 -> 195739.79 | N55: ='Wafi Escrow'!M33 -> 0 | O55: ='Wafi Escrow'!N33 -> 0 | ... V55: ='Wafi Escrow'!U33 -> 0
C56: Advance received from customer (net) | F56: =SUM(F53:F55) -> 4973234.7 | H56: =SUM(H53:H55) -> 0 | I56: =SUM(I53:I55) -> 36258.754 | J56: =SUM(J53:J55) -> 696590.77 | K56: =SUM(K53:K55) -> 1650954.6 | L56: =SUM(L53:L55) -> 1922135.2 | M56: =SUM(M53:M55) -> 587555.57 | N56: =SUM(N53:N55) -> 79739.85 | O56: =SUM(O53:O55) -> 0 | ... V56: =SUM(V53:V55) -> 0
C57: Funding requirement fulfilled by pre sales (capped at capex) | F57: =SUM(H57:U57) -> 3241576.8 | H57: =MIN(MAX(H56,0),H52) -> 0 | I57: =MIN(MAX(I56,0),I52) -> 36258.754 | J57: =MIN(MAX(J56,0),J52) -> 673301.7 | K57: =MIN(MAX(K56,0),K52) -> 996084.54 | L57: =MIN(MAX(L56,0),L52) -> 890366.12 | M57: =MIN(MAX(M56,0),M52) -> 573210.87 | N57: =MIN(MAX(N56,0),N52) -> 72354.808 | O57: =MIN(MAX(O56,0),O52) -> 0 | ... V57: =MIN(MAX(V56,0),V52) -> 0
C59: Funding gap = MAX(Capex − Pre-sales, 0) per period | F59: =SUM(H59:U59) -> 1315972.2 | H59: =IF((H52-G57)>0,H52-G57,0) -> 0 | I59: =IF((I52-H57)>0,I52-H57,0) -> 356146.45 | J59: =IF((J52-I57)>0,J52-I57,0) -> 637042.95 | K59: =IF((K52-J57)>0,K52-J57,0) -> 322782.84 | L59: =IF((L52-K57)>0,L52-K57,0) -> 0 | M59: =IF((M52-L57)>0,M52-L57,0) -> 0 | N59: =IF((N52-M57)>0,N52-M57,0) -> 0 | O59: =IF((O52-N57)>0,O52-N57,0) -> 0 | ... V59: =IF((V52-U57)>0,V52-U57,0) -> 0
C61: Cash Available
C62: Opening Cash | H62: =CF!F70 -> 0 | I62: =CF!G70 -> 0 | J62: =CF!H70 -> 50000 | K62: =CF!I70 -> 50000 | L62: =CF!J70 -> 526101.77 | M62: =CF!K70 -> 1431657.2 | N62: =CF!L70 -> 2491660.6 | O62: =CF!M70 -> 2661736.6 | ... V62: =CF!T70 -> 2539620.5
C63: Cash from Operations | H63: =CF!F40 -> 0 | I63: =CF!G40 -> 205218.06 | J63: =CF!H40 -> 847318.7 | K63: =CF!I40 -> 1805988.6 | L63: =CF!J40 -> 2141450.5 | M63: =CF!K40 -> 1987071.5 | N63: =CF!L40 -> 604951.6 | O63: =CF!M40 -> 277444.46 | ... V63: =CF!T40 -> 5330644.6
C64: Cash from Investments | H64: =CF!F54 -> -3682051 | I64: =CF!G54 -> -356146.45 | J64: =CF!H54 -> -673301.7 | K64: =CF!I54 -> -996084.54 | L64: =CF!J54 -> -890366.12 | M64: =CF!K54 -> -573210.87 | N64: =CF!L54 -> -72354.808 | O64: =CF!M54 -> 0 | ... V64: =CF!T54 -> 0
C65: =CF!B56 -> Equity Drawdown - T1 | H65: =CF!F56 -> 1282051 | I65: =CF!G56 -> 0 | J65: =CF!H56 -> 0 | K65: =CF!I56 -> 0 | L65: =CF!J56 -> 0 | M65: =CF!K56 -> 0 | N65: =CF!L56 -> 0 | O65: =CF!M56 -> 0 | ... V65: =CF!T56 -> 0
C66: =CF!B58 -> Debt Drawdown - T1 | H66: =CF!F58 -> 2400000 | I66: =CF!G58 -> 0 | J66: =CF!H58 -> 0 | K66: =CF!I58 -> 0 | L66: =CF!J58 -> 0 | M66: =CF!K58 -> 0 | N66: =CF!L58 -> 0 | O66: =CF!M58 -> 0 | ... V66: =CF!T58 -> 0
C67: =CF!B61 -> Debt Repayment - T1 | H67: =CF!F61 -> 0 | I67: =CF!G61 -> 0 | J67: =CF!H61 -> 0 | K67: =CF!I61 -> -143965.69 | L67: =CF!J61 -> -159425.62 | M67: =CF!K61 -> -177144.57 | N67: =CF!L61 -> -195953.77 | O67: =CF!M61 -> -1137395.1 | ... V67: =CF!T61 -> 0
C68: =CF!B63 -> Finance Cost Paid - T1 | H68: =CF!F63 -> 0 | I68: =CF!G63 -> -151200 | J68: =CF!H63 -> -151200 | K68: =CF!I63 -> -151200 | L68: =CF!J63 -> -142130.16 | M68: =CF!K63 -> -132086.35 | N68: =CF!L63 -> -120926.24 | O68: =CF!M63 -> -108581.15 | ... V68: =CF!T63 -> 0
C69: Cash Available Before Debt Drawdown | H69: =SUM(H62:H68) -> 0 | I69: =SUM(I62:I68) -> -302128.39 | J69: =SUM(J62:J68) -> 72817.003 | K69: =SUM(K62:K68) -> 564738.33 | L69: =SUM(L62:L68) -> 1475630.3 | M69: =SUM(M62:M68) -> 2536286.8 | N69: =SUM(N62:N68) -> 2707377.4 | O69: =SUM(O62:O68) -> 1693204.8 | ... V69: =SUM(V62:V68) -> 7870265.1
C71: Cash Required before Minimum Cash | H71: =IF(H69<0,H69,0) -> 0 | I71: =IF(I69<0,I69,0) -> -302128.39 | J71: =IF(J69<0,J69,0) -> 0 | K71: =IF(K69<0,K69,0) -> 0 | L71: =IF(L69<0,L69,0) -> 0 | M71: =IF(M69<0,M69,0) -> 0 | N71: =IF(N69<0,N69,0) -> 0 | O71: =IF(O69<0,O69,0) -> 0 | ... V71: =IF(V69<0,V69,0) -> 0
C72: Minimum Cash | I72: =-$F$7 -> -50000 | J72: =-$F$7 -> -50000 | K72: =-$F$7 -> -50000 | L72: =-$F$7 -> -50000 | M72: =-$F$7 -> -50000 | N72: =-$F$7 -> -50000 | O72: =-$F$7 -> -50000 | P72: =-$F$7 -> -50000 | ... V72: =-$F$7 -> -50000
C73: Net Cash Required | H73: =IF(H71<0,SUM(H71:H72),0) -> 0 | I73: =IF(I71<0,SUM(I71:I72),0) -> -352128.39 | J73: =IF(J71<0,SUM(J71:J72),0) -> 0 | K73: =IF(K71<0,SUM(K71:K72),0) -> 0 | L73: =IF(L71<0,SUM(L71:L72),0) -> 0 | M73: =IF(M71<0,SUM(M71:M72),0) -> 0 | N73: =IF(N71<0,SUM(N71:N72),0) -> 0 | O73: =IF(O71<0,SUM(O71:O72),0) -> 0 | ... V73: =IF(V71<0,SUM(V71:V72),0) -> 0
C75: Debt Funding | F75: =SUM(H75:U75) -> 352128.39 | H75: =IF(H$73<0,-H$73,0)*$F24 -> 0 | I75: =IF(I$73<0,-I$73,0)*$F24 -> 352128.39 | J75: =IF(J$73<0,-J$73,0)*$F24 -> 0 | K75: =IF(K$73<0,-K$73,0)*$F24 -> 0 | L75: =IF(L$73<0,-L$73,0)*$F24 -> 0 | M75: =IF(M$73<0,-M$73,0)*$F24 -> 0 | N75: =IF(N$73<0,-N$73,0)*$F24 -> 0 | O75: =IF(O$73<0,-O$73,0)*$F24 -> 0 | ... V75: =IF(V$73<0,-V$73,0)*$F24 -> 0
C76: Equity Funding | F76: =SUM(H76:U76) -> 0 | H76: =IF(H$73<0,-H$73,0)*$F25 -> 0 | I76: =IF(I$73<0,-I$73,0)*$F25 -> 0 | J76: =IF(J$73<0,-J$73,0)*$F25 -> 0 | K76: =IF(K$73<0,-K$73,0)*$F25 -> 0 | L76: =IF(L$73<0,-L$73,0)*$F25 -> 0 | M76: =IF(M$73<0,-M$73,0)*$F25 -> 0 | N76: =IF(N$73<0,-N$73,0)*$F25 -> 0 | O76: =IF(O$73<0,-O$73,0)*$F25 -> 0 | ... V76: =IF(V$73<0,-V$73,0)*$F25 -> 0
C77: Total Funding Phase 2 & 3 | F77: =SUM(H77:U77) -> 352128.39 | H77: =SUM(H75:H76) -> 0 | I77: =SUM(I75:I76) -> 352128.39 | J77: =SUM(J75:J76) -> 0 | K77: =SUM(K75:K76) -> 0 | L77: =SUM(L75:L76) -> 0 | M77: =SUM(M75:M76) -> 0 | N77: =SUM(N75:N76) -> 0 | O77: =SUM(O75:O76) -> 0 | ... V77: =SUM(V75:V76) -> 0
C78: IDC during construction (capitalised) | F78: =SUM(H78:U78) -> 28932.29 | H78: =H88 -> 0 | I78: =I88 -> 27742.471 | J78: =J88 -> 1189.8196 | K78: =K88 -> 0 | L78: =L88 -> 0 | M78: =M88 -> 0 | N78: =N88 -> 0 | O78: =O88 -> 0 | ... V78: =V88 -> 0
C79: Total Funding Phase 2 & 3 Incl. Financing Cost | F79: =SUM(F77:F78) -> 381060.68 | H79: =SUM(H77:H78) -> 0 | I79: =SUM(I77:I78) -> 379870.86 | J79: =SUM(J77:J78) -> 1189.8196 | K79: =SUM(K77:K78) -> 0 | L79: =SUM(L77:L78) -> 0 | M79: =SUM(M77:M78) -> 0 | N79: =SUM(N77:N78) -> 0 | O79: =SUM(O77:O78) -> 0 | ... V79: =SUM(V77:V78) -> 0
B81: TRANCHE 2 DRAWDOWN & FINANCING SCHEDULE
C83: Construction window flag (1 = active) | H83: 0 | I83: 1 | J83: 1 | K83: 1 | L83: 1 | M83: 0 | N83: 0 | O83: 0 | P83: 0 | Q83: 0 | R83: 0 | S83: 0 | T83: 0 | U83: 0 | V83: 0
C84: Repayment window flag (1 = active) | H84: =IF(H$4>=$F$29,1,0) -> 0 | I84: =IF(I$4>=$F$29,1,0) -> 0 | J84: =IF(J$4>=$F$29,1,0) -> 0 | K84: =IF(K$4>=$F$29,1,0) -> 1 | L84: =IF(L$4>=$F$29,1,0) -> 1 | M84: =IF(M$4>=$F$29,1,0) -> 1 | N84: =IF(N$4>=$F$29,1,0) -> 1 | O84: =IF(O$4>=$F$29,1,0) -> 1 | ... V84: =IF(V$4>=$F$29,1,0) -> 1
C86: DRAWDOWN SCHEDULE
C87: Capex debt drawn (gap × 45%) | F87: =SUM(H87:V87) -> 352128.39 | H87: =H75 -> 0 | I87: =I75 -> 352128.39 | J87: =J75 -> 0 | K87: =K75 -> 0 | L87: =L75 -> 0 | M87: =M75 -> 0 | N87: =N75 -> 0 | O87: =O75 -> 0 | ... V87: =V75 -> 0
C88: Financing cost drawn (IDC + upfront fee) | F88: =SUM(H88:V88) -> 28932.29 | H88: =IF(H$83=1,MIN(H97+H99,MAX(0,$F$7-H69+H97+H99)),0) -> 0 | I88: =IF(I$83=1,MIN(I97+I99,MAX(0,$F$7-I69+I97+I99)),0) -> 27742.471 | J88: =IF(J$83=1,MIN(J97+J99,MAX(0,$F$7-J69+J97+J99)),0) -> 1189.8196 | K88: =IF(K$83=1,MIN(K97+K99,MAX(0,$F$7-K69+K97+K99)),0) -> 0 | L88: =IF(L$83=1,MIN(L97+L99,MAX(0,$F$7-L69+L97+L99)),0) -> 0 | M88: =IF(M$83=1,MIN(M97+M99,MAX(0,$F$7-M69+M97+M99)),0) -> 0 | N88: =IF(N$83=1,MIN(N97+N99,MAX(0,$F$7-N69+N97+N99)),0) -> 0 | O88: =IF(O$83=1,MIN(O97+O99,MAX(0,$F$7-O69+O97+O99)),0) -> 0 | ... V88: =IF(V$83=1,MIN(V97+V99,MAX(0,$F$7-V69+V97+V99)),0) -> 0
C89: Total T2 drawdown | F89: =SUM(H89:V89) -> 381060.68 | H89: =SUM(H87:H88) -> 0 | I89: =SUM(I87:I88) -> 379870.86 | J89: =SUM(J87:J88) -> 1189.8196 | K89: =SUM(K87:K88) -> 0 | L89: =SUM(L87:L88) -> 0 | M89: =SUM(M87:M88) -> 0 | N89: =SUM(N87:N88) -> 0 | O89: =SUM(O87:O88) -> 0 | ... V89: =SUM(V87:V88) -> 0
C91: BALANCE SCHEDULE
C92: Opening balance | F92: =H92 -> 0 | H92: 0 | I92: =H95 -> 0 | J92: =I95 -> 379870.86 | K92: =J95 -> 381060.68 | L92: =K95 -> 366430.94 | M92: =L95 -> 345542.95 | N92: =M95 -> 322685.9 | O92: =N95 -> 297374.32 | P92: =O95 -> 269249.56 | ... V92: =U95 -> 0
C93: + Drawdown | F93: =SUM(H93:V93) -> 381060.68 | H93: =H89 -> 0 | I93: =I89 -> 379870.86 | J93: =J89 -> 1189.8196 | K93: =K89 -> 0 | L93: =L89 -> 0 | M93: =M89 -> 0 | N93: =N89 -> 0 | O93: =O89 -> 0 | ... V93: =V89 -> 0
C94: − Repayment | F94: =SUM(H94:V94) -> -381060.68 | H94: =-H30*$F$89 -> 0 | I94: =-I30*$F$89 -> 0 | J94: =-J30*$F$89 -> 0 | K94: =-K30*$F$89 -> -14629.738 | L94: =-L30*$F$89 -> -20887.992 | M94: =-M30*$F$89 -> -22857.046 | N94: =-N30*$F$89 -> -25311.578 | O94: =-O30*$F$89 -> -28124.766 | ... V94: =-V30*$F$89 -> 0
C95: Closing balance | F95: =V95 -> 0 | H95: =IF(SUM(H92:H94)<1,0,SUM(H92:H94)) -> 0 | I95: =IF(SUM(I92:I94)<1,0,SUM(I92:I94)) -> 379870.86 | J95: =IF(SUM(J92:J94)<1,0,SUM(J92:J94)) -> 381060.68 | K95: =IF(SUM(K92:K94)<1,0,SUM(K92:K94)) -> 366430.94 | L95: =IF(SUM(L92:L94)<1,0,SUM(L92:L94)) -> 345542.95 | M95: =IF(SUM(M92:M94)<1,0,SUM(M92:M94)) -> 322685.9 | N95: =IF(SUM(N92:N94)<1,0,SUM(N92:N94)) -> 297374.32 | O95: =IF(SUM(O92:O94)<1,0,SUM(O92:O94)) -> 269249.56 | ... V95: =IF(SUM(V92:V94)<1,0,SUM(V92:V94)) -> 0
C96: FINANCING COSTS
C97: IDC during construction (capitalised) | F97: =SUM(H97:V97) -> 95030.659 | H97: =(H92+H93)*H$83*$F$26 -> 0 | I97: =(I92+I93)*I$83*$F$26 -> 23931.864 | J97: =(J92+J93)*J$83*$F$26 -> 24006.823 | K97: =(K92+K93)*K$83*$F$26 -> 24006.823 | L97: =(L92+L93)*L$83*$F$26 -> 23085.149 | M97: =(M92+M93)*M$83*$F$26 -> 0 | N97: =(N92+N93)*N$83*$F$26 -> 0 | O97: =(O92+O93)*O$83*$F$26 -> 0 | ... V97: =(V92+V93)*V$83*$F$26 -> 0
C98: Operating interest | F98: =SUM(H98:V98) -> 92798.448 | H98: =(H92+H93)*IF(H$83=1,0,H$84)*$F$27 -> 0 | I98: =(I92+I93)*IF(I$83=1,0,I$84)*$F$27 -> 0 | J98: =(J92+J93)*IF(J$83=1,0,J$84)*$F$27 -> 0 | K98: =(K92+K93)*IF(K$83=1,0,K$84)*$F$27 -> 0 | L98: =(L92+L93)*IF(L$83=1,0,L$84)*$F$27 -> 0 | M98: =(M92+M93)*IF(M$83=1,0,M$84)*$F$27 -> 21769.206 | N98: =(N92+N93)*IF(N$83=1,0,N$84)*$F$27 -> 20329.212 | O98: =(O92+O93)*IF(O$83=1,0,O$84)*$F$27 -> 18734.582 | ... V98: =(V92+V93)*IF(V$83=1,0,V$84)*$F$27 -> 0
C99: Upfront fee | F99: =SUM(H99:V99) -> 3810.6068 | H99: =IF(H$4=2026,$F$89*$F$28,0) -> 0 | I99: =IF(I$4=2026,$F$89*$F$28,0) -> 3810.6068 | J99: =IF(J$4=2026,$F$89*$F$28,0) -> 0 | K99: =IF(K$4=2026,$F$89*$F$28,0) -> 0 | L99: =IF(L$4=2026,$F$89*$F$28,0) -> 0 | M99: =IF(M$4=2026,$F$89*$F$28,0) -> 0 | N99: =IF(N$4=2026,$F$89*$F$28,0) -> 0 | O99: =IF(O$4=2026,$F$89*$F$28,0) -> 0 | ... V99: =IF(V$4=2026,$F$89*$F$28,0) -> 0
C100: Total Financing Cost | F100: =SUM(H100:V100) -> 191639.71 | H100: =SUM(H97:H99) -> 0 | I100: =SUM(I97:I99) -> 27742.471 | J100: =SUM(J97:J99) -> 24006.823 | K100: =SUM(K97:K99) -> 24006.823 | L100: =SUM(L97:L99) -> 23085.149 | M100: =SUM(M97:M99) -> 21769.206 | N100: =SUM(N97:N99) -> 20329.212 | O100: =SUM(O97:O99) -> 18734.582 | ... V100: =SUM(V97:V99) -> 0
B102: TOTAL DEBT - COMBINED SUMMARY (T1 + T2)
C104: DRAWDOWN
C105: Tranche 1 (SNB 2.4 Bn) | F105: =SUM(H105:V105) -> 2400000 | H105: =H36 -> 2400000 | I105: =I36 -> 0 | J105: =J36 -> 0 | K105: =K36 -> 0 | L105: =L36 -> 0 | M105: =M36 -> 0 | N105: =N36 -> 0 | O105: =O36 -> 0 | ... V105: =V36 -> 0
C106: Tranche 2 (Phase 2 & 3) | F106: =SUM(H106:V106) -> 381060.68 | H106: =H93 -> 0 | I106: =I93 -> 379870.86 | J106: =J93 -> 1189.8196 | K106: =K93 -> 0 | L106: =L93 -> 0 | M106: =M93 -> 0 | N106: =N93 -> 0 | O106: =O93 -> 0 | ... V106: =V93 -> 0
C107: Total drawdown | F107: =SUM(H107:V107) -> 2781060.7 | H107: =SUM(H105:H106) -> 2400000 | I107: =SUM(I105:I106) -> 379870.86 | J107: =SUM(J105:J106) -> 1189.8196 | K107: =SUM(K105:K106) -> 0 | L107: =SUM(L105:L106) -> 0 | M107: =SUM(M105:M106) -> 0 | N107: =SUM(N105:N106) -> 0 | O107: =SUM(O105:O106) -> 0 | ... V107: =SUM(V105:V106) -> 0
C109: REPAYMENT
C110: Tranche 1 | F110: =SUM(H110:V110) -> -2400000 | H110: =H37 -> 0 | I110: =I37 -> 0 | J110: =J37 -> 0 | K110: =K37 -> -143965.69 | L110: =L37 -> -159425.62 | M110: =M37 -> -177144.57 | N110: =N37 -> -195953.77 | O110: =O37 -> -1137395.1 | ... V110: =V37 -> 0
C111: Tranche 2 | F111: =SUM(H111:V111) -> -381060.68 | H111: =H94 -> 0 | I111: =I94 -> 0 | J111: =J94 -> 0 | K111: =K94 -> -14629.738 | L111: =L94 -> -20887.992 | M111: =M94 -> -22857.046 | N111: =N94 -> -25311.578 | O111: =O94 -> -28124.766 | ... V111: =V94 -> 0
C112: Total repayment | F112: =SUM(H112:V112) -> -2781060.7 | H112: =SUM(H110:H111) -> 0 | I112: =SUM(I110:I111) -> 0 | J112: =SUM(J110:J111) -> 0 | K112: =SUM(K110:K111) -> -158595.43 | L112: =SUM(L110:L111) -> -180313.62 | M112: =SUM(M110:M111) -> -200001.61 | N112: =SUM(N110:N111) -> -221265.35 | O112: =SUM(O110:O111) -> -1165519.9 | ... V112: =SUM(V110:V111) -> 0
C114: BALANCE
C115: Tranche 1 closing | F115: =V115 -> 0 | H115: =H38 -> 2400000 | I115: =I38 -> 2400000 | J115: =J38 -> 2400000 | K115: =K38 -> 2256034.3 | L115: =L38 -> 2096608.7 | M115: =M38 -> 1919464.1 | N115: =N38 -> 1723510.3 | O115: =O38 -> 586115.21 | ... V115: =V38 -> 0
C116: Tranche 2 closing | F116: =V116 -> 0 | H116: =H95 -> 0 | I116: =I95 -> 379870.86 | J116: =J95 -> 381060.68 | K116: =K95 -> 366430.94 | L116: =L95 -> 345542.95 | M116: =M95 -> 322685.9 | N116: =N95 -> 297374.32 | O116: =O95 -> 269249.56 | ... V116: =V95 -> 0
C117: Total closing balance | F117: =V117 -> 0 | H117: =SUM(H115:H116) -> 2400000 | I117: =SUM(I115:I116) -> 2779870.9 | J117: =SUM(J115:J116) -> 2781060.7 | K117: =SUM(K115:K116) -> 2622465.2 | L117: =SUM(L115:L116) -> 2442151.6 | M117: =SUM(M115:M116) -> 2242150 | N117: =SUM(N115:N116) -> 2020884.7 | O117: =SUM(O115:O116) -> 855364.77 | ... V117: =SUM(V115:V116) -> 0
C119: INTEREST & FINANCE COSTS
C120: T1 operating interest | F120: =SUM(H120:V120) -> 994249.16 | H120: =H40 -> 0 | I120: =I40 -> 151200 | J120: =J40 -> 151200 | K120: =K40 -> 151200 | L120: =L40 -> 142130.16 | M120: =M40 -> 132086.35 | N120: =N40 -> 120926.24 | O120: =O40 -> 108581.15 | ... V120: =V40 -> 0
C121: T2 operating interest (incl. grace) | F121: =SUM(H121:V121) -> 92798.448 | H121: =H98 -> 0 | I121: =I98 -> 0 | J121: =J98 -> 0 | K121: =K98 -> 0 | L121: =L98 -> 0 | M121: =M98 -> 21769.206 | N121: =N98 -> 20329.212 | O121: =O98 -> 18734.582 | ... V121: =V98 -> 0
C122: T2 IDC (capitalised - memo only) | F122: =SUM(H122:V122) -> 95030.659 | H122: =H97 -> 0 | I122: =I97 -> 23931.864 | J122: =J97 -> 24006.823 | K122: =K97 -> 24006.823 | L122: =L97 -> 23085.149 | M122: =M97 -> 0 | N122: =N97 -> 0 | O122: =O97 -> 0 | ... V122: =V97 -> 0
...

Sheet P&L
B1: MAAD RESIDENTIAL WITH HOTEL - INCOME STATEMENT (P&L)
B2: All figures in SAR'000
B3: Revenue → cost of sales → OpEx → NOI → D&A → EBIZ → capital gain → PBZ → Zakat → PAZ.
B4: DESCRIPTION | C4: Phase | D4: Total | E4: 2025 | F4: =E4+1 -> 2026 | G4: =F4+1 -> 2027 | H4: =G4+1 -> 2028 | I4: =H4+1 -> 2029 | J4: =I4+1 -> 2030 | K4: =J4+1 -> 2031 | L4: =K4+1 -> 2032 | M4: =L4+1 -> 2033 | ... S4: =R4+1 -> 2039
B5: Residential Revenue
B6: =CF!B8 -> Pre-Sales from Branded Apartments T2 & T3 | C6: 2 | D6: =SUM(E6:S6) -> 2539826.9 | E6: =Revenue!L164 -> 0 | F6: =Revenue!M164 -> 42332.123 | G6: =Revenue!N164 -> 550297.5 | H6: =Revenue!O164 -> 1058262.9 | I6: =Revenue!P164 -> 888934.39 | J6: =Revenue!Q164 -> 0 | K6: =Revenue!R164 -> 0 | L6: =Revenue!S164 -> 0 | ... S6: =Revenue!Z164 -> 0
B7: =CF!B9 -> Pre-Sales from Branded Apartments T4 & T5 | C7: 3 | D7: =SUM(E7:S7) -> 1594797 | E7: =Revenue!L165 -> 0 | F7: =Revenue!M165 -> 0 | G7: =Revenue!N165 -> 159479.7 | H7: =Revenue!O165 -> 478439.1 | I7: =Revenue!P165 -> 797398.5 | J7: =Revenue!Q165 -> 159479.7 | K7: =Revenue!R165 -> 0 | L7: =Revenue!S165 -> 0 | ... S7: =Revenue!Z165 -> 0
B8: =CF!B10 -> Pre-Sales from Residential Tower 01 | C8: 2 | D8: =SUM(E8:S8) -> 838610.8 | E8: =Revenue!L166 -> 0 | F8: =Revenue!M166 -> 0 | G8: =Revenue!N166 -> 0 | H8: =Revenue!O166 -> 0 | I8: =Revenue!P166 -> 0 | J8: =Revenue!Q166 -> 838610.8 | K8: =Revenue!R166 -> 0 | L8: =Revenue!S166 -> 0 | ... S8: =Revenue!Z166 -> 0
B9: =CF!B11 -> Branded Apartments T2 & T3 | C9: 2 | D9: =SUM(E9:S9) -> 282214.16 | E9: =Revenue!L167 -> 0 | F9: =Revenue!M167 -> 0 | G9: =Revenue!N167 -> 0 | H9: =Revenue!O167 -> 0 | I9: =Revenue!P167 -> 0 | J9: =Revenue!Q167 -> 282214.16 | K9: =Revenue!R167 -> 0 | L9: =Revenue!S167 -> 0 | ... S9: =Revenue!Z167 -> 0
B10: =CF!B12 -> Branded Apartments T4 & T5 | C10: 3 | D10: =SUM(E10:S10) -> 1063227 | E10: =Revenue!L168 -> 0 | F10: =Revenue!M168 -> 0 | G10: =Revenue!N168 -> 0 | H10: =Revenue!O168 -> 0 | I10: =Revenue!P168 -> 0 | J10: =Revenue!Q168 -> 797413 | K10: =Revenue!R168 -> 265814 | L10: =Revenue!S168 -> 0 | ... S10: =Revenue!Z168 -> 0
B11: =CF!B13 -> Residential Tower 01 | C11: 2 | D11: =SUM(E11:S11) -> 90301.2 | E11: =Revenue!L169 -> 0 | F11: =Revenue!M169 -> 0 | G11: =Revenue!N169 -> 0 | H11: =Revenue!O169 -> 0 | I11: =Revenue!P169 -> 0 | J11: =Revenue!Q169 -> 90301.2 | K11: =Revenue!R169 -> 0 | L11: =Revenue!S169 -> 0 | ... S11: =Revenue!Z169 -> 0
B12: Total Residential Revenue | D12: =SUM(D6:D11) -> 6408977 | E12: =SUM(E6:E11) -> 0 | F12: =SUM(F6:F11) -> 42332.123 | G12: =SUM(G6:G11) -> 709777.2 | H12: =SUM(H6:H11) -> 1536702 | I12: =SUM(I6:I11) -> 1686332.9 | J12: =SUM(J6:J11) -> 2168018.9 | K12: =SUM(K6:K11) -> 265814 | ... S12: =SUM(S6:S11) -> 0
B14: Hospitality Revenue
B15: VOCO Hotel (Phase 1) | C15: 1 | D15: =SUM(E15:S15) -> 5814328.9 | E15: =Revenue!L223 -> 0 | F15: =Revenue!M223 -> 323867.37 | G15: =Revenue!N223 -> 336217.37 | H15: =Revenue!O223 -> 348567.37 | I15: =Revenue!P223 -> 362217.37 | J15: =Revenue!Q223 -> 377617.37 | K15: =Revenue!R223 -> 400216.51 | L15: =Revenue!S223 -> 412223.01 | ... S15: =Revenue!Z223 -> 506982.3
B16: Residential Tower 01 (Phase 2) | C16: 2 | D16: =SUM(E16:S16) -> 998402.5 | E16: =Revenue!L224 -> 0 | F16: =Revenue!M224 -> 0 | G16: =Revenue!N224 -> 0 | H16: =Revenue!O224 -> 0 | I16: =Revenue!P224 -> 50085.648 | J16: =Revenue!Q224 -> 59495.9 | K16: =Revenue!R224 -> 78346.31 | L16: =Revenue!S224 -> 91332.947 | ... S16: =Revenue!Z224 -> 112021.1
B17: Hotel 01 - 336 Keys (Phase 2) | C17: 2 | D17: =SUM(E17:S17) -> 970246.36 | E17: =Revenue!L225 -> 0 | F17: =Revenue!M225 -> 0 | G17: =Revenue!N225 -> 0 | H17: =Revenue!O225 -> 0 | I17: =Revenue!P225 -> 60561.716 | J17: =Revenue!Q225 -> 68319.383 | K17: =Revenue!R225 -> 77252.885 | L17: =Revenue!S225 -> 86108.352 | ... S17: =Revenue!Z225 -> 105613.06
B18: Total Hospitality Revenue | D18: =SUM(E18:S18) -> 7782977.7 | E18: =SUM(E15:E17) -> 0 | F18: =SUM(F15:F17) -> 323867.37 | G18: =SUM(G15:G17) -> 336217.37 | H18: =SUM(H15:H17) -> 348567.37 | I18: =SUM(I15:I17) -> 472864.73 | J18: =SUM(J15:J17) -> 505432.65 | K18: =SUM(K15:K17) -> 555815.71 | L18: =SUM(L15:L17) -> 589664.3 | ... S18: =SUM(S15:S17) -> 724616.46
B20: Retail Revenue
B21: Support Retail (Phase 2) | C21: 2 | D21: =SUM(E21:S21) -> 220121.29 | E21: =Revenue!L324 -> 0 | F21: =Revenue!M324 -> 0 | G21: =Revenue!N324 -> 0 | H21: =Revenue!O324 -> 0 | I21: =Revenue!P324 -> 9598.2878 | J21: =Revenue!Q324 -> 13117.66 | K21: =Revenue!R324 -> 16807.002 | L21: =Revenue!S324 -> 20672.612 | ... S21: =Revenue!Z324 -> 24573.24
B22: Support Retail (Phase 3) | C22: 3 | D22: =SUM(E22:S22) -> 115889.21 | E22: =Revenue!L325 -> 0 | F22: =Revenue!M325 -> 0 | G22: =Revenue!N325 -> 0 | H22: =Revenue!O325 -> 0 | I22: =Revenue!P325 -> 5053.296 | J22: =Revenue!Q325 -> 6906.1712 | K22: =Revenue!R325 -> 8848.5318 | L22: =Revenue!S325 -> 10883.694 | ... S22: =Revenue!Z325 -> 12937.292
B23: Total Retail Revenue | D23: =SUM(E23:S23) -> 336010.5 | E23: =SUM(E21:E22) -> 0 | F23: =SUM(F21:F22) -> 0 | G23: =SUM(G21:G22) -> 0 | H23: =SUM(H21:H22) -> 0 | I23: =SUM(I21:I22) -> 14651.584 | J23: =SUM(J21:J22) -> 20023.831 | K23: =SUM(K21:K22) -> 25655.534 | L23: =SUM(L21:L22) -> 31556.306 | ... S23: =SUM(S21:S22) -> 37510.532
B25: Total Revenue | D25: =SUM(E25:S25) -> 14527965 | E25: =SUM(E12,E18,E23) -> 0 | F25: =SUM(F12,F18,F23) -> 366199.49 | G25: =SUM(G12,G18,G23) -> 1045994.6 | H25: =SUM(H12,H18,H23) -> 1885269.4 | I25: =SUM(I12,I18,I23) -> 2173849.2 | J25: =SUM(J12,J18,J23) -> 2693475.3 | K25: =SUM(K12,K18,K23) -> 847285.24 | L25: =SUM(L12,L18,L23) -> 621220.61 | ... S25: =SUM(S12,S18,S23) -> 762126.99
B27: Cost of Sales
B28: Retail cost of sales | D28: =SUM(E28:S28) -> 0
B29: Residential cost of sales | D29: =SUM(E29:S29) -> 0
B30: Branded Apartments T2 & T3 (Phase 2) | C30: 2 | D30: =SUM(E30:S30) -> -1876587.7 | E30: =-Costs!J174 -> 0 | F30: =-Costs!K174 -> -10415.127 | G30: =-Costs!L174 -> -204360.99 | H30: =-Costs!M174 -> -614066.75 | I30: =-Costs!N174 -> -741861.49 | J30: =-Costs!O174 -> -305883.37 | K30: =-Costs!P174 -> 0 | L30: =-Costs!Q174 -> 0 | ... S30: =-Costs!X174 -> 0
B31: Branded Apartments T4 & T5 (Phase 3) | C31: 3 | D31: =SUM(E31:S31) -> -1867655.3 | E31: =-Costs!J175 -> 0 | F31: =-Costs!K175 -> 0 | G31: =-Costs!L175 -> -42598.703 | H31: =-Costs!M175 -> -214621.88 | I31: =-Costs!N175 -> -516883.71 | J31: =-Costs!O175 -> -906785.49 | K31: =-Costs!P175 -> -186765.53 | L31: =-Costs!Q175 -> 0 | ... S31: =-Costs!X175 -> 0
B32: Residential Tower 01 (Phase 2) | C32: 2 | D32: =SUM(E32:S32) -> -649071.73 | E32: =-Costs!J176 -> 0 | F32: =-Costs!K176 -> 0 | G32: =-Costs!L176 -> 0 | H32: =-Costs!M176 -> 0 | I32: =-Costs!N176 -> 0 | J32: =-Costs!O176 -> -649071.73 | K32: =-Costs!P176 -> 0 | L32: =-Costs!Q176 -> 0 | ... S32: =-Costs!X176 -> 0
B33: Total Cost of Sales | D33: =SUM(E33:S33) -> -4393314.8 | E33: =SUM(E28:E32) -> 0 | F33: =SUM(F28:F32) -> -10415.127 | G33: =SUM(G28:G32) -> -246959.7 | H33: =SUM(H28:H32) -> -828688.63 | I33: =SUM(I28:I32) -> -1258745.2 | J33: =SUM(J28:J32) -> -1861740.6 | K33: =SUM(K28:K32) -> -186765.53 | L33: =SUM(L28:L32) -> 0 | ... S33: =SUM(S28:S32) -> 0
B35: Operating Expenses
B36: Hospitality operating expenses | D36: =SUM(E36:S36) -> 0
B37: VOCO Hotel (Phase 1) | C37: 1 | D37: =SUM(E37:S37) -> -3068478.3 | E37: =Costs!J56 -> 0 | F37: =Costs!K56 -> -167777.86 | G37: =Costs!L56 -> -174173.58 | H37: =Costs!M56 -> -175382.8 | I37: =Costs!N56 -> -187388.59 | J37: =Costs!O56 -> -200727.57 | K37: =Costs!P56 -> -212915.18 | L37: =Costs!Q56 -> -219302.64 | ... S37: =Costs!X56 -> -269714.58
B38: Residential Tower 01 (Phase 2) | C38: 2 | D38: =SUM(E38:S38) -> -742885.42 | E38: =Costs!J57 -> 0 | F38: =Costs!K57 -> 0 | G38: =Costs!L57 -> 0 | H38: =Costs!M57 -> 0 | I38: =Costs!N57 -> -37267.432 | J38: =Costs!O57 -> -44269.357 | K38: =Costs!P57 -> -58295.458 | L38: =Costs!Q57 -> -67958.478 | ... S38: =Costs!X57 -> -83351.995
B39: Hotel 01 - 336 Keys (Phase 2) | C39: 2 | D39: =SUM(E39:S39) -> -579908.79 | E39: =Costs!J58 -> 0 | F39: =Costs!K58 -> 0 | G39: =Costs!L58 -> 0 | H39: =Costs!M58 -> 0 | I39: =Costs!N58 -> -36197.272 | J39: =Costs!O58 -> -40833.97 | K39: =Costs!P58 -> -46173.455 | L39: =Costs!Q58 -> -51466.3 | ... S39: =Costs!X58 -> -63124.114
B40: Retail operating expenses | D40: =SUM(E40:S40) -> 0
B41: Support Retail (Phase 2) | C41: 2 | D41: =SUM(E41:S41) -> -26414.554 | E41: =Costs!J60 -> 0 | F41: =Costs!K60 -> 0 | G41: =Costs!L60 -> 0 | H41: =Costs!M60 -> 0 | I41: =Costs!N60 -> -1151.7945 | J41: =Costs!O60 -> -1574.1192 | K41: =Costs!P60 -> -2016.8402 | L41: =Costs!Q60 -> -2480.7135 | ... S41: =Costs!X60 -> -2948.7888
B42: Support Retail (Phase 3) | C42: 3 | D42: =SUM(E42:S42) -> -13906.705 | E42: =Costs!J61 -> 0 | F42: =Costs!K61 -> 0 | G42: =Costs!L61 -> 0 | H42: =Costs!M61 -> 0 | I42: =Costs!N61 -> -606.39552 | J42: =Costs!O61 -> -828.74054 | K42: =Costs!P61 -> -1061.8238 | L42: =Costs!Q61 -> -1306.0433 | ... S42: =Costs!X61 -> -1552.4751
B43: Total Operating Expenses | D43: =SUM(E43:S43) -> -4431593.8 | E43: =SUM(E37:E42) -> 0 | F43: =SUM(F37:F42) -> -167777.86 | G43: =SUM(G37:G42) -> -174173.58 | H43: =SUM(H37:H42) -> -175382.8 | I43: =SUM(I37:I42) -> -262611.48 | J43: =SUM(J37:J42) -> -288233.76 | K43: =SUM(K37:K42) -> -320462.76 | L43: =SUM(L37:L42) -> -342514.17 | ... S43: =SUM(S37:S42) -> -420691.96
B45: EBIZDA | D45: =SUM(E45:S45) -> 5703056.7 | E45: =SUM(E25,E33,E43) -> 0 | F45: =SUM(F25,F33,F43) -> 188006.51 | G45: =SUM(G25,G33,G43) -> 624861.3 | H45: =SUM(H25,H33,H43) -> 881197.93 | I45: =SUM(I25,I33,I43) -> 652492.52 | J45: =SUM(J25,J33,J43) -> 543501 | K45: =SUM(K25,K33,K43) -> 340056.95 | L45: =SUM(L25,L33,L43) -> 278706.44 | ... S45: =SUM(S25,S33,S43) -> 341435.03
B46: EBIZDA Margin | D46: =IFERROR(D45/D$25,0) -> 0.39255715 | E46: =IFERROR(E45/E$25,0) -> 0 | F46: =IFERROR(F45/F$25,0) -> 0.51339914 | G46: =IFERROR(G45/G$25,0) -> 0.59738484 | H46: =IFERROR(H45/H$25,0) -> 0.46741222 | I46: =IFERROR(I45/I$25,0) -> 0.30015537 | J46: =IFERROR(J45/J$25,0) -> 0.20178429 | K46: =IFERROR(K45/K$25,0) -> 0.40134884 | ... S46: =IFERROR(S45/S$25,0) -> 0.44800281
B48: Depreciation and Amortization (D&A) | D48: =SUM(E48:S48) -> -227484.9 | F48: =Capex!M298 -> 0 | G48: =Capex!N298 -> 0 | H48: =Capex!O298 -> 0 | I48: =Capex!P298 -> 0 | J48: =Capex!Q298 -> 0 | K48: =Capex!R298 -> -28413.918 | L48: =Capex!S298 -> -28413.918 | M48: =Capex!T298 -> -28413.918 | ... S48: =Capex!Z298 -> -14293.737
B49: EBIZ (Earning before interest and zakat) | D49: =SUM(E49:S49) -> 5475571.8 | E49: =SUM(E45,E48) -> 0 | F49: =SUM(F45,F48) -> 188006.51 | G49: =SUM(G45,G48) -> 624861.3 | H49: =SUM(H45,H48) -> 881197.93 | I49: =SUM(I45,I48) -> 652492.52 | J49: =SUM(J45,J48) -> 543501 | K49: =SUM(K45,K48) -> 311643.03 | L49: =SUM(L45,L48) -> 250292.52 | ... S49: =SUM(S45,S48) -> 327141.3
B50: EBIZDA Margin | D50: =IFERROR(D49/D$25,0) -> 0.37689874 | E50: =IFERROR(E49/E$25,0) -> 0 | F50: =IFERROR(F49/F$25,0) -> 0.51339914 | G50: =IFERROR(G49/G$25,0) -> 0.59738484 | H50: =IFERROR(H49/H$25,0) -> 0.46741222 | I50: =IFERROR(I49/I$25,0) -> 0.30015537 | J50: =IFERROR(J49/J$25,0) -> 0.20178429 | K50: =IFERROR(K49/K$25,0) -> 0.36781359 | ... S50: =IFERROR(S49/S$25,0) -> 0.42924775
B52: Capital gain/(loss) | D52: =SUM(E52:S52) -> 0
B53: Interest and financing cost | D53: =SUM(E53:S53) -> -1087047.6 | E53: =-Debt!H128 -> 0 | F53: =-Debt!I128 -> -151200 | G53: =-Debt!J128 -> -151200 | H53: =-Debt!K128 -> -151200 | I53: =-Debt!L128 -> -142130.16 | J53: =-Debt!M128 -> -153855.55 | K53: =-Debt!N128 -> -141255.45 | L53: =-Debt!O128 -> -127315.73 | ... S53: =-Debt!V128 -> 0
B54: Interest income | D54: =SUM(E54:S54) -> 0
B55: PBZ (Profit before Zakat) | D55: =SUM(E55:S55) -> 4388524.2 | E55: =SUM(E49,E52:E54) -> 0 | F55: =SUM(F49,F52:F54) -> 36806.507 | G55: =SUM(G49,G52:G54) -> 473661.3 | H55: =SUM(H49,H52:H54) -> 729997.93 | I55: =SUM(I49,I52:I54) -> 510362.36 | J55: =SUM(J49,J52:J54) -> 389645.45 | K55: =SUM(K49,K52:K54) -> 170387.58 | L55: =SUM(L49,L52:L54) -> 122976.79 | ... S55: =SUM(S49,S52:S54) -> 327141.3
B56: PBZ Margin | D56: =IFERROR(D55/D$25,0) -> 0.30207425 | E56: =IFERROR(E55/E$25,0) -> 0 | F56: =IFERROR(F55/F$25,0) -> 0.10050944 | G56: =IFERROR(G55/G$25,0) -> 0.45283342 | H56: =IFERROR(H55/H$25,0) -> 0.38721147 | I56: =IFERROR(I55/I$25,0) -> 0.23477358 | J56: =IFERROR(J55/J$25,0) -> 0.14466271 | K56: =IFERROR(K55/K$25,0) -> 0.20109825 | ... S56: =IFERROR(S55/S$25,0) -> 0.42924775
B58: Zakat | C58: 0.025 | D58: =SUM(E58:S58) -> -109713.1 | E58: =-IF(E55>0,E55*$C$58,0) -> 0 | F58: =-IF(F55>0,F55*$C$58,0) -> -920.16267 | G58: =-IF(G55>0,G55*$C$58,0) -> -11841.532 | H58: =-IF(H55>0,H55*$C$58,0) -> -18249.948 | I58: =-IF(I55>0,I55*$C$58,0) -> -12759.059 | J58: =-IF(J55>0,J55*$C$58,0) -> -9741.1362 | K58: =-IF(K55>0,K55*$C$58,0) -> -4259.6895 | L58: =-IF(L55>0,L55*$C$58,0) -> -3074.4196 | ... S58: =-IF(S55>0,S55*$C$58,0) -> -8178.5324
B59: PAZ (Profit after Zakat) | D59: =SUM(E59:S59) -> 4278811.1 | E59: =SUM(E55,E58) -> 0 | F59: =SUM(F55,F58) -> 35886.344 | G59: =SUM(G55,G58) -> 461819.76 | H59: =SUM(H55,H58) -> 711747.98 | I59: =SUM(I55,I58) -> 497603.3 | J59: =SUM(J55,J58) -> 379904.31 | K59: =SUM(K55,K58) -> 166127.89 | L59: =SUM(L55,L58) -> 119902.37 | ... S59: =SUM(S55,S58) -> 318962.77
B60: PAZ Margin | D60: =IFERROR(D59/D$25,0) -> 0.29452239 | E60: =IFERROR(E59/E$25,0) -> 0 | F60: =IFERROR(F59/F$25,0) -> 0.097996706 | G60: =IFERROR(G59/G$25,0) -> 0.44151258 | H60: =IFERROR(H59/H$25,0) -> 0.37753119 | I60: =IFERROR(I59/I$25,0) -> 0.22890424 | J60: =IFERROR(J59/J$25,0) -> 0.14104614 | K60: =IFERROR(K59/K$25,0) -> 0.19607079 | ... S60: =IFERROR(S59/S$25,0) -> 0.41851656
B62: End of Sheet

Sheet CF
B1: MAAD RESIDENTIAL WITH HOTEL - CASH FLOW STATEMENT | E1: Live >>>> | F1: Management | G1: =SUMIF('Capex Allocation'!$V$1:$V$2,$F$1,'Capex Allocation'!$W$1:$W$2) -> 2
B2: All figures in SAR'000
B3: Revenue received → costs paid → capex → financing → net cash flow / closing cash, with Wafi escrow integrated.
B5: DESCRIPTION | C5: Phase | E5: Total | F5: 2025 | G5: =F5+1 -> 2026 | H5: =G5+1 -> 2027 | I5: =H5+1 -> 2028 | J5: =I5+1 -> 2029 | K5: =J5+1 -> 2030 | L5: =K5+1 -> 2031 | M5: =L5+1 -> 2032 | N5: =M5+1 -> 2033 | ... T5: =S5+1 -> 2039
B6: Revenue Received
B7: Residential revenue
B8: Pre-Sales from Branded Apartments T2 & T3 | C8: 2 | E8: =SUM(F8:T8) -> 2539826.9 | F8: =Revenue!L16 -> 0 | G8: =Revenue!M16 -> 28221.416 | H8: =Revenue!N16 -> 465636.61 | I8: =Revenue!O16 -> 973601.98 | J8: =Revenue!P16 -> 945375.54 | K8: =Revenue!Q16 -> 126991.34 | L8: =Revenue!R16 -> 0 | M8: =Revenue!S16 -> 0 | ... T8: =Revenue!Z16 -> 0
B9: Pre-Sales from Branded Apartments T4 & T5 | C9: 3 | E9: =SUM(F9:T9) -> 1594797 | F9: =Revenue!L17 -> 0 | G9: =Revenue!M17 -> 0 | H9: =Revenue!N17 -> 106319.8 | I9: =Revenue!O17 -> 425279.2 | J9: =Revenue!P17 -> 744238.6 | K9: =Revenue!Q17 -> 239219.55 | L9: =Revenue!R17 -> 79739.85 | M9: =Revenue!S17 -> 0 | ... T9: =Revenue!Z17 -> 0
B10: Pre-Sales from Residential Tower 01 | C10: 2 | E10: =SUM(F10:T10) -> 838610.8 | F10: =Revenue!L18 -> 0 | G10: =Revenue!M18 -> 9548.12 | H10: =Revenue!N18 -> 153658.98 | I10: =Revenue!O18 -> 320863.14 | J10: =Revenue!P18 -> 312610.02 | K10: =Revenue!Q18 -> 41930.54 | L10: =Revenue!R18 -> 0 | M10: =Revenue!S18 -> 0 | ... T10: =Revenue!Z18 -> 0
B11: Branded Apartments T2 & T3 | C11: 2 | E11: =SUM(F11:T11) -> 282214.16 | F11: =Revenue!L19 -> 0 | G11: =Revenue!M19 -> 0 | H11: =Revenue!N19 -> 0 | I11: =Revenue!O19 -> 0 | J11: =Revenue!P19 -> 0 | K11: =Revenue!Q19 -> 282214.16 | L11: =Revenue!R19 -> 0 | M11: =Revenue!S19 -> 0 | ... T11: =Revenue!Z19 -> 0
B12: Branded Apartments T4 & T5 | C12: 3 | E12: =SUM(F12:T12) -> 1063227 | F12: =Revenue!L20 -> 0 | G12: =Revenue!M20 -> 0 | H12: =Revenue!N20 -> 0 | I12: =Revenue!O20 -> 0 | J12: =Revenue!P20 -> 0 | K12: =Revenue!Q20 -> 797413 | L12: =Revenue!R20 -> 265814 | M12: =Revenue!S20 -> 0 | ... T12: =Revenue!Z20 -> 0
B13: Residential Tower 01 | C13: 2 | E13: =SUM(F13:T13) -> 90301.2 | F13: =Revenue!L21 -> 0 | G13: =Revenue!M21 -> 0 | H13: =Revenue!N21 -> 0 | I13: =Revenue!O21 -> 0 | J13: =Revenue!P21 -> 0 | K13: =Revenue!Q21 -> 90301.2 | L13: =Revenue!R21 -> 0 | M13: =Revenue!S21 -> 0 | ... T13: =Revenue!Z21 -> 0
B14: Hospitality revenue
B15: VOCO Hotel | C15: 1 | E15: =SUM(F15:T15) -> 5814328.9 | F15: =Revenue!L223 -> 0 | G15: =Revenue!M223 -> 323867.37 | H15: =Revenue!N223 -> 336217.37 | I15: =Revenue!O223 -> 348567.37 | J15: =Revenue!P223 -> 362217.37 | K15: =Revenue!Q223 -> 377617.37 | L15: =Revenue!R223 -> 400216.51 | M15: =Revenue!S223 -> 412223.01 | ... T15: =Revenue!Z223 -> 506982.3
B16: Residential Tower 01 | C16: 2 | E16: =SUM(F16:T16) -> 998402.5 | F16: =Revenue!L224 -> 0 | G16: =Revenue!M224 -> 0 | H16: =Revenue!N224 -> 0 | I16: =Revenue!O224 -> 0 | J16: =Revenue!P224 -> 50085.648 | K16: =Revenue!Q224 -> 59495.9 | L16: =Revenue!R224 -> 78346.31 | M16: =Revenue!S224 -> 91332.947 | ... T16: =Revenue!Z224 -> 112021.1
B17: Hotel 01 - 336 Keys | C17: 2 | E17: =SUM(F17:T17) -> 970246.36 | F17: =Revenue!L225 -> 0 | G17: =Revenue!M225 -> 0 | H17: =Revenue!N225 -> 0 | I17: =Revenue!O225 -> 0 | J17: =Revenue!P225 -> 60561.716 | K17: =Revenue!Q225 -> 68319.383 | L17: =Revenue!R225 -> 77252.885 | M17: =Revenue!S225 -> 86108.352 | ... T17: =Revenue!Z225 -> 105613.06
B18: Retail revenue
B19: Support Retail | C19: 2 | E19: =SUM(F19:T19) -> 220121.29 | F19: =Revenue!L324 -> 0 | G19: =Revenue!M324 -> 0 | H19: =Revenue!N324 -> 0 | I19: =Revenue!O324 -> 0 | J19: =Revenue!P324 -> 9598.2878 | K19: =Revenue!Q324 -> 13117.66 | L19: =Revenue!R324 -> 16807.002 | M19: =Revenue!S324 -> 20672.612 | ... T19: =Revenue!Z324 -> 24573.24
B20: Support Retail | C20: 3 | E20: =SUM(F20:T20) -> 115889.21 | F20: =Revenue!L325 -> 0 | G20: =Revenue!M325 -> 0 | H20: =Revenue!N325 -> 0 | I20: =Revenue!O325 -> 0 | J20: =Revenue!P325 -> 5053.296 | K20: =Revenue!Q325 -> 6906.1712 | L20: =Revenue!R325 -> 8848.5318 | M20: =Revenue!S325 -> 10883.694 | ... T20: =Revenue!Z325 -> 12937.292
B21: Total Revenue Received | E21: =SUM(F21:T21) -> 14527965 | F21: =SUM(F7:F20) -> 0 | G21: =SUM(G7:G20) -> 361636.91 | H21: =SUM(H7:H20) -> 1061832.8 | I21: =SUM(I7:I20) -> 2068311.7 | J21: =SUM(J7:J20) -> 2489740.5 | K21: =SUM(K7:K20) -> 2103526.3 | L21: =SUM(L7:L20) -> 927025.09 | M21: =SUM(M7:M20) -> 621220.61 | ... T21: =SUM(T7:T20) -> 762126.99
B22: Less: Inaccessible Funds Locked (Wafi) | E22: =SUM(F22:T22) -> -195739.79 | F22: ='Wafi Escrow'!G32 -> 0 | G22: ='Wafi Escrow'!H32 -> -1510.7814 | H22: ='Wafi Escrow'!I32 -> -29024.615 | I22: ='Wafi Escrow'!J32 -> -68789.773 | J22: ='Wafi Escrow'!K32 -> -80088.967 | K22: ='Wafi Escrow'!L32 -> -16325.657 | L22: ='Wafi Escrow'!M32 -> 0 | M22: ='Wafi Escrow'!N32 -> 0 | ... T22: ='Wafi Escrow'!U32 -> 0
B23: Add: Release of Inaccessible Funds (Wafi) | E23: =SUM(F23:T23) -> 195739.79 | F23: ='Wafi Escrow'!G33 -> 0 | G23: ='Wafi Escrow'!H33 -> 0 | H23: ='Wafi Escrow'!I33 -> 0 | I23: ='Wafi Escrow'!J33 -> 0 | J23: ='Wafi Escrow'!K33 -> 0 | K23: ='Wafi Escrow'!L33 -> 195739.79 | L23: ='Wafi Escrow'!M33 -> 0 | M23: ='Wafi Escrow'!N33 -> 0 | ... T23: ='Wafi Escrow'!U33 -> 0
B24: Net Cash Flow Adjustment | E24: =SUM(E22:E23) -> 0 | F24: =SUM(F22:F23) -> 0 | G24: =SUM(G22:G23) -> -1510.7814 | H24: =SUM(H22:H23) -> -29024.615 | I24: =SUM(I22:I23) -> -68789.773 | J24: =SUM(J22:J23) -> -80088.967 | K24: =SUM(K22:K23) -> 179414.14 | L24: =SUM(L22:L23) -> 0 | ... T24: =SUM(T22:T23) -> 0
B26: Expenses and Costs Paid
B27: Operating Expenses Paid
B28: Hospitality
B29: VOCO Hotel (Phase 1) | C29: 1 | E29: =SUM(F29:T29) -> -3046310 | F29: =Costs!J100 -> 0 | G29: =Costs!K100 -> -153987.9 | H29: =Costs!L100 -> -173647.9 | I29: =Costs!M100 -> -175283.41 | J29: =Costs!N100 -> -186401.81 | K29: =Costs!O100 -> -199631.22 | L29: =Costs!P100 -> -211913.46 | M29: =Costs!Q100 -> -218777.64 | ... T29: =Costs!X100 -> -269068.91
B30: Residential Tower 01 (Phase 2) | C30: 1 | E30: =SUM(F30:T30) -> -736034.57 | F30: =Costs!J101 -> 0 | G30: =Costs!K101 -> 0 | H30: =Costs!L101 -> 0 | I30: =Costs!M101 -> 0 | J30: =Costs!N101 -> -34204.356 | K30: =Costs!O101 -> -43693.856 | L30: =Costs!P101 -> -57142.628 | M30: =Costs!Q101 -> -67164.257 | ... T30: =Costs!X101 -> -83152.455
B31: Hotel 01 - 336 Keys (Phase 2) | C31: 1 | E31: =SUM(F31:T31) -> -574720.5 | F31: =Costs!J102 -> 0 | G31: =Costs!K102 -> 0 | H31: =Costs!L102 -> 0 | I31: =Costs!M102 -> 0 | J31: =Costs!N102 -> -33222.153 | K31: =Costs!O102 -> -40452.871 | L31: =Costs!P102 -> -45734.593 | M31: =Costs!Q102 -> -51031.271 | ... T31: =Costs!X102 -> -62972.999
B32: Retail
B33: Support Retail (Phase 2) | C33: 2 | E33: =SUM(F33:T33) -> -26172.188 | F33: =Costs!J104 -> 0 | G33: =Costs!K104 -> 0 | H33: =Costs!L104 -> 0 | I33: =Costs!M104 -> 0 | J33: =Costs!N104 -> -1057.1265 | K33: =Costs!O104 -> -1539.4076 | L33: =Costs!P104 -> -1980.4522 | M33: =Costs!Q104 -> -2442.5869 | ... T33: =Costs!X104 -> -2942.8774
B34: Support Retail (Phase 3) | C34: 3 | E34: =SUM(F34:T34) -> -13779.105 | F34: =Costs!J105 -> 0 | G34: =Costs!K105 -> 0 | H34: =Costs!L105 -> 0 | I34: =Costs!M105 -> 0 | J34: =Costs!N105 -> -556.55479 | K34: =Costs!O105 -> -810.46561 | L34: =Costs!P105 -> -1042.6663 | M34: =Costs!Q105 -> -1285.9705 | ... T34: =Costs!X105 -> -1549.3628
B35: Total Operating Expenses Paid | E35: =SUM(F35:T35) -> -4397016.4 | F35: =SUM(F27:F34) -> 0 | G35: =SUM(G27:G34) -> -153987.9 | H35: =SUM(H27:H34) -> -173647.9 | I35: =SUM(I27:I34) -> -175283.41 | J35: =SUM(J27:J34) -> -255442 | K35: =SUM(K27:K34) -> -286127.82 | L35: =SUM(L27:L34) -> -317813.8 | M35: =SUM(M27:M34) -> -340701.73 | ... T35: =SUM(T27:T34) -> -419686.6
B36: Zakat Paid | E36: =SUM(F36:T36) -> -109713.1 | F36: ='P&L'!E58 -> 0 | G36: ='P&L'!F58 -> -920.16267 | H36: ='P&L'!G58 -> -11841.532 | I36: ='P&L'!H58 -> -18249.948 | J36: ='P&L'!I58 -> -12759.059 | K36: ='P&L'!J58 -> -9741.1362 | L36: ='P&L'!K58 -> -4259.6895 | M36: ='P&L'!L58 -> -3074.4196 | ... T36: ='P&L'!S58 -> -8178.5324
B37: Total Costs Paid | E37: =SUM(F37:T37) -> -4506729.5 | F37: =SUM(F35:F36) -> 0 | G37: =SUM(G35:G36) -> -154908.06 | H37: =SUM(H35:H36) -> -185489.44 | I37: =SUM(I35:I36) -> -193533.36 | J37: =SUM(J35:J36) -> -268201.06 | K37: =SUM(K35:K36) -> -295868.96 | L37: =SUM(L35:L36) -> -322073.49 | M37: =SUM(M35:M36) -> -343776.15 | ... T37: =SUM(T35:T36) -> -427865.13
B39: Exit Value | D39: 2039 | E39: =SUM(F39:T39) -> 4996382.7 | F39: =IF(F$5=$D$39,(SUM(F21,F37)*(1+WACC!$G$35))/WACC!$G$37,0) -> 0 | G39: =IF(G$5=$D$39,(SUM(G21,G37)*(1+WACC!$G$35))/WACC!$G$37,0) -> 0 | H39: =IF(H$5=$D$39,(SUM(H21,H37)*(1+WACC!$G$35))/WACC!$G$37,0) -> 0 | I39: =IF(I$5=$D$39,(SUM(I21,I37)*(1+WACC!$G$35))/WACC!$G$37,0) -> 0 | J39: =IF(J$5=$D$39,(SUM(J21,J37)*(1+WACC!$G$35))/WACC!$G$37,0) -> 0 | K39: =IF(K$5=$D$39,(SUM(K21,K37)*(1+WACC!$G$35))/WACC!$G$37,0) -> 0 | L39: =IF(L$5=$D$39,(SUM(L21,L37)*(1+WACC!$G$35))/WACC!$G$37,0) -> 0 | M39: =IF(M$5=$D$39,(SUM(M21,M37)*(1+WACC!$G$35))/WACC!$G$37,0) -> 0 | ... S39: =IF(S$5=$D$39,(SUM(S21,S37)*(1+WACC!$G$35))/WACC!$G$37,0) -> 0 | T39: =IF(T$5=$D$39,SUM(T21,T37)*(1+WACC!$G$35)/WACC!$G$37,0) -> 4996382.7
B40: Cash Flow from operations | E40: 15819785 | F40: =SUM(F21,F24,F37,F39) -> 0 | G40: =SUM(G21,G24,G37,G39) -> 205218.06 | H40: =SUM(H21,H24,H37,H39) -> 847318.7 | I40: =SUM(I21,I24,I37,I39) -> 1805988.6 | J40: =SUM(J21,J24,J37,J39) -> 2141450.5 | K40: =SUM(K21,K24,K37,K39) -> 1987071.5 | L40: =SUM(L21,L24,L37,L39) -> 604951.6 | M40: =SUM(M21,M24,M37,M39) -> 277444.46 | ... T40: =SUM(T21,T24,T37,T39) -> 5330644.6
B42: Capital expenditure excl. inventory cost
B43: Residential Capex
B44: Branded Apartments T2 & T3 | C44: 2 | E44: =SUM(F44:T44) -> -1313606.6 | F44: =-Capex!L189 -> 0 | G44: =-Capex!M189 -> -131360.66 | H44: =-Capex!N189 -> -328401.65 | I44: =-Capex!O189 -> -394081.98 | J44: =-Capex!P189 -> -328401.65 | K44: =-Capex!Q189 -> -131360.66 | L44: =-Capex!R189 -> 0 | M44: =-Capex!S189 -> 0 | ... T44: =-Capex!Z189 -> 0
B45: Branded Apartments T4 & T5 | C45: 3 | E45: =SUM(F45:T45) -> -1447096.2 | F45: =-Capex!L190 -> 0 | G45: =-Capex!M190 -> -144709.62 | H45: =-Capex!N190 -> -144709.62 | I45: =-Capex!O190 -> -361774.04 | J45: =-Capex!P190 -> -361774.04 | K45: =-Capex!Q190 -> -361774.04 | L45: =-Capex!R190 -> -72354.808 | M45: =-Capex!S190 -> 0 | ... T45: =-Capex!Z190 -> 0
B46: Residential Tower 01 | C46: 2 | E46: =SUM(F46:T46) -> -443418.29 | F46: =-Capex!L191 -> 0 | G46: =-Capex!M191 -> -44341.829 | H46: =-Capex!N191 -> -110854.57 | I46: =-Capex!O191 -> -133025.49 | J46: =-Capex!P191 -> -110854.57 | K46: =-Capex!Q191 -> -44341.829 | L46: =-Capex!R191 -> 0 | M46: =-Capex!S191 -> 0 | ... T46: =-Capex!Z191 -> 0
B47: Hospitality Capex
B48: Hotel 01 - 336 Keys | C48: 2 | E48: =SUM(F48:T48) -> -245218.5 | F48: =-Capex!L193 -> 0 | G48: =-Capex!M193 -> -24521.85 | H48: =-Capex!N193 -> -61304.624 | I48: =-Capex!O193 -> -73565.549 | J48: =-Capex!P193 -> -61304.624 | K48: =-Capex!Q193 -> -24521.85 | L48: =-Capex!R193 -> 0 | M48: =-Capex!S193 -> 0 | ... T48: =-Capex!Z193 -> 0
B49: Retail Capex
B50: Support Retail | C50: 2 | E50: =SUM(F50:T50) -> -76409.113 | F50: =-Capex!L195 -> 0 | G50: =-Capex!M195 -> -7640.9113 | H50: =-Capex!N195 -> -19102.278 | I50: =-Capex!O195 -> -22922.734 | J50: =-Capex!P195 -> -19102.278 | K50: =-Capex!Q195 -> -7640.9113 | L50: =-Capex!R195 -> 0 | M50: =-Capex!S195 -> 0 | ... T50: =-Capex!Z195 -> 0
B51: Support Retail | C51: 3 | E51: =SUM(F51:T51) -> -35715.818 | F51: =-Capex!L196 -> 0 | G51: =-Capex!M196 -> -3571.5818 | H51: =-Capex!N196 -> -8928.9546 | I51: =-Capex!O196 -> -10714.746 | J51: =-Capex!P196 -> -8928.9546 | K51: =-Capex!Q196 -> -3571.5818 | L51: =-Capex!R196 -> 0 | M51: =-Capex!S196 -> 0 | ... T51: =-Capex!Z196 -> 0
B52: Total Capex excl. inventory cost | E52: =SUM(F52:T52) -> -3561464.5 | F52: =SUM(F43:F51) -> 0 | G52: =SUM(G43:G51) -> -356146.45 | H52: =SUM(H43:H51) -> -673301.7 | I52: =SUM(I43:I51) -> -996084.54 | J52: =SUM(J43:J51) -> -890366.12 | K52: =SUM(K43:K51) -> -573210.87 | L52: =SUM(L43:L51) -> -72354.808 | M52: =SUM(M43:M51) -> 0 | ... T52: =SUM(T43:T51) -> 0
B53: Pre-Capex VOCO | C53: 1 | E53: =SUM(F53:T53) -> -3682051 | F53: =-IF(F$5=Debt!$F$19,Debt!$F$13,0) -> -3682051 | G53: =-IF(G$5=Debt!$F$19,Debt!$F$13,0) -> 0 | H53: =-IF(H$5=Debt!$F$19,Debt!$F$13,0) -> 0 | I53: =-IF(I$5=Debt!$F$19,Debt!$F$13,0) -> 0 | J53: =-IF(J$5=Debt!$F$19,Debt!$F$13,0) -> 0 | K53: =-IF(K$5=Debt!$F$19,Debt!$F$13,0) -> 0 | L53: =-IF(L$5=Debt!$F$19,Debt!$F$13,0) -> 0 | M53: =-IF(M$5=Debt!$F$19,Debt!$F$13,0) -> 0 | ... T53: =-IF(T$5=Debt!$F$19,Debt!$F$13,0) -> 0
B54: Cash Flow from invetsment | E54: =SUM(F54:T54) -> -7243515.5 | F54: =SUM(F52:F53) -> -3682051 | G54: =SUM(G52:G53) -> -356146.45 | H54: =SUM(H52:H53) -> -673301.7 | I54: =SUM(I52:I53) -> -996084.54 | J54: =SUM(J52:J53) -> -890366.12 | K54: =SUM(K52:K53) -> -573210.87 | L54: =SUM(L52:L53) -> -72354.808 | M54: =SUM(M52:M53) -> 0 | ... T54: =SUM(T52:T53) -> 0
B56: Equity Drawdown - T1 | C56: 1 | E56: =SUM(F56:T56) -> 1282051 | F56: =Debt!H141 -> 1282051 | G56: =Debt!I141 -> 0 | H56: =Debt!J141 -> 0 | I56: =Debt!K141 -> 0 | J56: =Debt!L141 -> 0 | K56: =Debt!M141 -> 0 | L56: =Debt!N141 -> 0 | M56: =Debt!O141 -> 0 | ... T56: =Debt!V141 -> 0
B57: Equity Drawdown - T2 | C57: 2 & 3 | E57: =SUM(F57:T57) -> 0 | F57: =Debt!H142 -> 0 | G57: =Debt!I142 -> 0 | H57: =Debt!J142 -> 0 | I57: =Debt!K142 -> 0 | J57: =Debt!L142 -> 0 | K57: =Debt!M142 -> 0 | L57: =Debt!N142 -> 0 | M57: =Debt!O142 -> 0 | ... T57: =Debt!V142 -> 0
B58: Debt Drawdown - T1 | C58: 1 | E58: =SUM(F58:T58) -> 2400000 | F58: =Debt!H105 -> 2400000 | G58: =Debt!I105 -> 0 | H58: =Debt!J105 -> 0 | I58: =Debt!K105 -> 0 | J58: =Debt!L105 -> 0 | K58: =Debt!M105 -> 0 | L58: =Debt!N105 -> 0 | M58: =Debt!O105 -> 0 | ... T58: =Debt!V105 -> 0
B59: Debt Drawdown - T2 | C59: 2 & 3 | E59: =SUM(F59:T59) -> 352128.39 | F59: =Debt!H87 -> 0 | G59: =Debt!I87 -> 352128.39 | H59: =Debt!J87 -> 0 | I59: =Debt!K87 -> 0 | J59: =Debt!L87 -> 0 | K59: =Debt!M87 -> 0 | L59: =Debt!N87 -> 0 | M59: =Debt!O87 -> 0 | ... T59: =Debt!V87 -> 0
B60: Debt Drawdown - T2 (IDC) | C60: 2 & 3 | E60: =SUM(F60:T60) -> 28932.29 | F60: =Debt!H88 -> 0 | G60: =Debt!I88 -> 27742.471 | H60: =Debt!J88 -> 1189.8196 | I60: =Debt!K88 -> 0 | J60: =Debt!L88 -> 0 | K60: =Debt!M88 -> 0 | L60: =Debt!N88 -> 0 | M60: =Debt!O88 -> 0 | ... T60: =Debt!V88 -> 0
B61: Debt Repayment - T1 | C61: 1 | E61: =SUM(F61:T61) -> -2400000 | F61: =Debt!H110 -> 0 | G61: =Debt!I110 -> 0 | H61: =Debt!J110 -> 0 | I61: =Debt!K110 -> -143965.69 | J61: =Debt!L110 -> -159425.62 | K61: =Debt!M110 -> -177144.57 | L61: =Debt!N110 -> -195953.77 | M61: =Debt!O110 -> -1137395.1 | ... T61: =Debt!V110 -> 0
B62: Debt Repayment - T2 | C62: 2 & 3 | E62: =SUM(F62:T62) -> -381060.68 | F62: =Debt!H111 -> 0 | G62: =Debt!I111 -> 0 | H62: =Debt!J111 -> 0 | I62: =Debt!K111 -> -14629.738 | J62: =Debt!L111 -> -20887.992 | K62: =Debt!M111 -> -22857.046 | L62: =Debt!N111 -> -25311.578 | M62: =Debt!O111 -> -28124.766 | ... T62: =Debt!V111 -> 0
B63: Finance Cost Paid - T1 | C63: 1 | E63: =SUM(F63:T63) -> -994249.16 | F63: =-Debt!H120 -> 0 | G63: =-Debt!I120 -> -151200 | H63: =-Debt!J120 -> -151200 | I63: =-Debt!K120 -> -151200 | J63: =-Debt!L120 -> -142130.16 | K63: =-Debt!M120 -> -132086.35 | L63: =-Debt!N120 -> -120926.24 | M63: =-Debt!O120 -> -108581.15 | ... T63: =-Debt!V120 -> 0
B64: Finance Cost Paid - T2 (IDC) | C64: 2 & 3 | E64: =SUM(F64:T64) -> -95030.659 | F64: =-Debt!H122 -> 0 | G64: =-Debt!I122 -> -23931.864 | H64: =-Debt!J122 -> -24006.823 | I64: =-Debt!K122 -> -24006.823 | J64: =-Debt!L122 -> -23085.149 | K64: =-Debt!M122 -> 0 | L64: =-Debt!N122 -> 0 | M64: =-Debt!O122 -> 0 | ... T64: =-Debt!V122 -> 0
B65: Finance Cost Paid - T2 (Operations) | C65: 2 & 3 | E65: =SUM(F65:T65) -> -92798.448 | F65: =-Debt!H121 -> 0 | G65: =-Debt!I121 -> 0 | H65: =-Debt!J121 -> 0 | I65: =-Debt!K121 -> 0 | J65: =-Debt!L121 -> 0 | K65: =-Debt!M121 -> -21769.206 | L65: =-Debt!N121 -> -20329.212 | M65: =-Debt!O121 -> -18734.582 | ... T65: =-Debt!V121 -> 0
B66: Upfront Fees - T2 | C66: 2 & 3 | E66: =SUM(F66:T66) -> -3810.6068 | F66: =-Debt!H123 -> 0 | G66: =-Debt!I123 -> -3810.6068 | H66: =-Debt!J123 -> 0 | I66: =-Debt!K123 -> 0 | J66: =-Debt!L123 -> 0 | K66: =-Debt!M123 -> 0 | L66: =-Debt!N123 -> 0 | M66: =-Debt!O123 -> 0 | ... T66: =-Debt!V123 -> 0
B67: Cash Flow from Financing | E67: =SUM(F67:T67) -> 96162.149 | F67: =SUM(F56:F66) -> 3682051 | G67: =SUM(G56:G66) -> 200928.39 | H67: =SUM(H56:H66) -> -174017 | I67: =SUM(I56:I66) -> -333802.25 | J67: =SUM(J56:J66) -> -345528.93 | K67: =SUM(K56:K66) -> -353857.16 | L67: =SUM(L56:L66) -> -362520.8 | M67: =SUM(M56:M66) -> -1292835.6 | ... T67: =SUM(T56:T66) -> 0
B69: Net Cash Flow | E69: =SUM(E40,E54,E67) -> 8672431.2 | F69: =SUM(F40,F54,F67) -> 0 | G69: =SUM(G40,G54,G67) -> 50000 | H69: =SUM(H40,H54,H67) -> 0 | I69: =SUM(I40,I54,I67) -> 476101.77 | J69: =SUM(J40,J54,J67) -> 905555.4 | K69: =SUM(K40,K54,K67) -> 1060003.4 | L69: =SUM(L40,L54,L67) -> 170075.99 | ... T69: =SUM(T40,T54,T67) -> 5330644.6
B70: Opening Cash | F70: =E71 -> 0 | G70: =F71 -> 0 | H70: =G71 -> 50000 | I70: =H71 -> 50000 | J70: =I71 -> 526101.77 | K70: =J71 -> 1431657.2 | L70: =K71 -> 2491660.6 | M70: =L71 -> 2661736.6 | ... T70: =S71 -> 2539620.5
B71: Closing Cash | F71: =SUM(F69,F70) -> 0 | G71: =SUM(G69,G70) -> 50000 | H71: =SUM(H69,H70) -> 50000 | I71: =SUM(I69,I70) -> 526101.77 | J71: =SUM(J69,J70) -> 1431657.2 | K71: =SUM(K69,K70) -> 2491660.6 | L71: =SUM(L69,L70) -> 2661736.6 | M71: =SUM(M69,M70) -> 1646345.4 | ... T71: =SUM(T69,T70) -> 7870265.1
B73: KPIs Summary
B75: EBITDA - Hospitality
B76: =B15 -> VOCO Hotel | E76: =SUM(F76:T76) -> 2768018.8 | F76: =SUM(F15,F29) -> 0 | G76: =SUM(G15,G29) -> 169879.47 | H76: =SUM(H15,H29) -> 162569.47 | I76: =SUM(I15,I29) -> 173283.96 | J76: =SUM(J15,J29) -> 175815.56 | K76: =SUM(K15,K29) -> 177986.15 | L76: =SUM(L15,L29) -> 188303.05 | M76: =SUM(M15,M29) -> 193445.36 | ... T76: =SUM(T15,T29) -> 237913.4
B77: =B16 -> Residential Tower 01 | E77: =SUM(F77:T77) -> 262367.93 | F77: =SUM(F16,F30) -> 0 | G77: =SUM(G16,G30) -> 0 | H77: =SUM(H16,H30) -> 0 | I77: =SUM(I16,I30) -> 0 | J77: =SUM(J16,J30) -> 15881.292 | K77: =SUM(K16,K30) -> 15802.044 | L77: =SUM(L16,L30) -> 21203.682 | M77: =SUM(M16,M30) -> 24168.69 | ... T77: =SUM(T16,T30) -> 28868.642
B78: =B17 -> Hotel 01 - 336 Keys | E78: =SUM(F78:T78) -> 395525.86 | F78: =SUM(F17,F31) -> 0 | G78: =SUM(G17,G31) -> 0 | H78: =SUM(H17,H31) -> 0 | I78: =SUM(I17,I31) -> 0 | J78: =SUM(J17,J31) -> 27339.562 | K78: =SUM(K17,K31) -> 27866.512 | L78: =SUM(L17,L31) -> 31518.292 | M78: =SUM(M17,M31) -> 35077.081 | ... T78: =SUM(T17,T31) -> 42640.062
B79: =B33 -> Support Retail (Phase 2) | E79: =SUM(F79:T79) -> 193949.1 | F79: =SUM(F19,F33) -> 0 | G79: =SUM(G19,G33) -> 0 | H79: =SUM(H19,H33) -> 0 | I79: =SUM(I19,I33) -> 0 | J79: =SUM(J19,J33) -> 8541.1613 | K79: =SUM(K19,K33) -> 11578.252 | L79: =SUM(L19,L33) -> 14826.55 | M79: =SUM(M19,M33) -> 18230.025 | ... T79: =SUM(T19,T33) -> 21630.362
B80: =B34 -> Support Retail (Phase 3) | E80: =SUM(F80:T80) -> 102110.11 | F80: =SUM(F20,F34) -> 0 | G80: =SUM(G20,G34) -> 0 | H80: =SUM(H20,H34) -> 0 | I80: =SUM(I20,I34) -> 0 | J80: =SUM(J20,J34) -> 4496.7412 | K80: =SUM(K20,K34) -> 6095.7056 | L80: =SUM(L20,L34) -> 7805.8655 | M80: =SUM(M20,M34) -> 9597.7237 | ... T80: =SUM(T20,T34) -> 11387.929
B81: TOTAL EBITDA - Hospitality | E81: =SUM(F81:T81) -> 3721971.8 | F81: =SUM(F76:F80) -> 0 | G81: =SUM(G76:G80) -> 169879.47 | H81: =SUM(H76:H80) -> 162569.47 | I81: =SUM(I76:I80) -> 173283.96 | J81: =SUM(J76:J80) -> 232074.32 | K81: =SUM(K76:K80) -> 239328.67 | L81: =SUM(L76:L80) -> 263657.44 | M81: =SUM(M76:M80) -> 280518.88 | ... T81: =SUM(T76:T80) -> 342440.39
B83: Total Interest Cost | E83: =SUM(F83:T83) -> -1185888.9 | F83: =-SUM(F63:F66) -> 0 | G83: =SUM(G63:G66) -> -178942.47 | H83: =SUM(H63:H66) -> -175206.82 | I83: =SUM(I63:I66) -> -175206.82 | J83: =SUM(J63:J66) -> -165215.31 | K83: =SUM(K63:K66) -> -153855.55 | L83: =SUM(L63:L66) -> -141255.45 | M83: =SUM(M63:M66) -> -127315.73 | N83: =SUM(N63:N66) -> -53887.98 | ... T83: =SUM(T63:T66) -> 0
B85: Pre - Sales Revenue Received
B86: =B92 -> Branded Apartments T2 & T3 | E86: =SUM(F86:T86) -> 2539826.9 | F86: =F8 -> 0 | G86: =G8 -> 28221.416 | H86: =H8 -> 465636.61 | I86: =I8 -> 973601.98 | J86: =J8 -> 945375.54 | K86: =K8 -> 126991.34 | L86: =L8 -> 0 | M86: =M8 -> 0 | ... T86: =T8 -> 0
B87: =B93 -> Branded Apartments T4 & T5 | E87: =SUM(F87:T87) -> 1594797 | F87: =F9 -> 0 | G87: =G9 -> 0 | H87: =H9 -> 106319.8 | I87: =I9 -> 425279.2 | J87: =J9 -> 744238.6 | K87: =K9 -> 239219.55 | L87: =L9 -> 79739.85 | M87: =M9 -> 0 | ... T87: =T9 -> 0
B88: =B94 -> Residential Tower 01 | E88: =SUM(F88:T88) -> 838610.8 | F88: =F10 -> 0 | G88: =G10 -> 9548.12 | H88: =H10 -> 153658.98 | I88: =I10 -> 320863.14 | J88: =J10 -> 312610.02 | K88: =K10 -> 41930.54 | L88: =L10 -> 0 | M88: =M10 -> 0 | ... T88: =T10 -> 0
B89: Total Revenue Received | E89: =SUM(F89:T89) -> 4973234.7 | F89: =SUM(F86:F88) -> 0 | G89: =SUM(G86:G88) -> 37769.536 | H89: =SUM(H86:H88) -> 725615.39 | I89: =SUM(I86:I88) -> 1719744.3 | J89: =SUM(J86:J88) -> 2002224.2 | K89: =SUM(K86:K88) -> 408141.43 | L89: =SUM(L86:L88) -> 79739.85 | M89: =SUM(M86:M88) -> 0 | ... T89: =SUM(T86:T88) -> 0
B91: % Area Sold - Pre Sales
B92: Branded Apartments T2 & T3 | E92: =SUM(F92:T92) -> 0.9 | F92: =AVERAGE(Revenue!L28:L29) -> 0 | G92: =AVERAGE(Revenue!M28:M29) -> 0.05 | H92: =AVERAGE(Revenue!N28:N29) -> 0.3 | I92: =AVERAGE(Revenue!O28:O29) -> 0.3 | J92: =AVERAGE(Revenue!P28:P29) -> 0.25 | K92: =AVERAGE(Revenue!Q28:Q29) -> 0 | L92: =AVERAGE(Revenue!R28:R29) -> 0 | M92: =AVERAGE(Revenue!S28:S29) -> 0 | ... T92: =AVERAGE(Revenue!Z28:Z29) -> 0
B93: Branded Apartments T4 & T5 | E93: =SUM(F93:T93) -> 0.6 | F93: =AVERAGE(Revenue!L57:L58) -> 0 | G93: =AVERAGE(Revenue!M57:M58) -> 0 | H93: =AVERAGE(Revenue!N57:N58) -> 0.2 | I93: =AVERAGE(Revenue!O57:O58) -> 0.2 | J93: =AVERAGE(Revenue!P57:P58) -> 0.2 | K93: =AVERAGE(Revenue!Q57:Q58) -> 0 | L93: =AVERAGE(Revenue!R57:R58) -> 0 | M93: =AVERAGE(Revenue!S57:S58) -> 0 | ... T93: =AVERAGE(Revenue!Z57:Z58) -> 0
B94: Residential Tower 01 | E94: =SUM(F94:T94) -> 0.9 | F94: =AVERAGE(Revenue!L86:L88) -> 0 | G94: =AVERAGE(Revenue!M86:M88) -> 0.05 | H94: =AVERAGE(Revenue!N86:N88) -> 0.3 | I94: =AVERAGE(Revenue!O86:O88) -> 0.3 | J94: =AVERAGE(Revenue!P86:P88) -> 0.25 | K94: =AVERAGE(Revenue!Q86:Q88) -> 0 | L94: =AVERAGE(Revenue!R86:R88) -> 0 | M94: =AVERAGE(Revenue!S86:S88) -> 0 | ... T94: =AVERAGE(Revenue!Z86:Z88) -> 0
B96: % Area Sold - Operations
B97: =B92 -> Branded Apartments T2 & T3 | E97: =SUM(F97:T97) -> 0.1 | F97: =AVERAGE(Revenue!L118:L119) -> 0 | G97: =AVERAGE(Revenue!M118:M119) -> 0 | H97: =AVERAGE(Revenue!N118:N119) -> 0 | I97: =AVERAGE(Revenue!O118:O119) -> 0 | J97: =AVERAGE(Revenue!P118:P119) -> 0 | K97: =AVERAGE(Revenue!Q118:Q119) -> 0.1 | L97: =AVERAGE(Revenue!R118:R119) -> 0 | M97: =AVERAGE(Revenue!S118:S119) -> 0 | ... T97: =AVERAGE(Revenue!Z118:Z119) -> 0
B98: =B93 -> Branded Apartments T4 & T5 | E98: =SUM(F98:T98) -> 0.4 | F98: =AVERAGE(Revenue!L133:L134) -> 0 | G98: =AVERAGE(Revenue!M133:M134) -> 0 | H98: =AVERAGE(Revenue!N133:N134) -> 0 | I98: =AVERAGE(Revenue!O133:O134) -> 0 | J98: =AVERAGE(Revenue!P133:P134) -> 0 | K98: =AVERAGE(Revenue!Q133:Q134) -> 0.3 | L98: =AVERAGE(Revenue!R133:R134) -> 0.1 | M98: =AVERAGE(Revenue!S133:S134) -> 0 | ... T98: =AVERAGE(Revenue!Z133:Z134) -> 0
B99: =B94 -> Residential Tower 01 | E99: =SUM(F99:T99) -> 0.096774194 | F99: =IF(F$5=Revenue!$D$237,Revenue!$G$237,0) -> 0 | G99: =IF(G$5=Revenue!$D$237,Revenue!$G$237,0) -> 0 | H99: =IF(H$5=Revenue!$D$237,Revenue!$G$237,0) -> 0 | I99: =IF(I$5=Revenue!$D$237,Revenue!$G$237,0) -> 0 | J99: =IF(J$5=Revenue!$D$237,Revenue!$G$237,0) -> 0 | K99: =IF(K$5=Revenue!$D$237,Revenue!$G$237,0) -> 0.096774194 | L99: =IF(L$5=Revenue!$D$237,Revenue!$G$237,0) -> 0 | M99: =IF(M$5=Revenue!$D$237,Revenue!$G$237,0) -> 0 | ... T99: =IF(T$5=Revenue!$D$237,Revenue!$G$237,0) -> 0
B101: % Payment Plan - Pre Sales
